[{"TEN":"Adapter Silicon Power xDrive L03 – Mở rộng bộ nhớ cho Macbook","GIA":199000,"HINHANH":"SSD/Adapter_Silicon_Power-xDrive_L03-280x315.jpg","MOTA":"Thông số kĩ thuật Nhà sản xuất Silicon Power Model L03 Chuẩn giao tiếp – Adapter 23 * 24 * 2.1 mm – MicroSDXC (không bao gồm thẻ nhớ) Kích thước 23 * 24 * 2.1 mm Dòng máy hỗ trợ – Macbook Air 13″ – Macbook Pro 13″ – Macbook Pro 15″ – Macbook Pro 15″ Retina (Trước 2013) Tương thích – Tương thích các chuẩn MicroSDXC – Không tương thích các dòng SD và đầu đọc SD Bảo hành 12 tháng Adapter SIlicon Power SP xDrive L03 Mở rộng dung lượng lưu trữ cho MacBook của bạn. Thiết kế đặc biệt dành riêng cho các dòng MacBook, Adapter Silicon Power SP xDrive cung cấp một giải pháp lý tưởng để mở rộng thêm từ 64GB dung lượng lưu trữ cho MacBook của bạn. Giúp bạn có thể lưu trữ thêm rất nhiều dữ liệu yêu thích của bạn như Video FullHD, nhạc và các hình ảnh… Khe cắm thiết kế đặc biệt Với phương châm luôn tạo sự tin tưởng và thoải mái cho người dùng, Adapter SIlicon Power SP xDrive L03 được thiết kế khe cắm đặc biệt có rãnh để giúp bạn dễ dàng tháo lắp vào Macbook. Hơn nữa, Adapter SIlicon Power SP xDrive L03 cũng được thiết kế theo kích thước của khe cắm với màu bạc đặc trưng, phù hợp với phong cách của Apple. Đáp ứng tốc độ cao. Adapter SIlicon Power SP xDrive L03 bao gồm một khe cắm thẻ Flash UHS-1 microSDXC hỗ trợ UHS-1 và đáp ứng tốc độ truyền dữ liệu lên đến 90MB/s đọc, không chỉ giúp bạn nhanh chóng chuyển và lưu trữ file giữa Adapter SIlicon Power SP xDrive L03 và MacBook mà còn giúp tăng cường chất lượng của video 1080p Giải pháp mở rộng tốt nhất. Thiết kế đặc biết, hỗ trợ tốc độ cao và hoàn toàn phù hợp với phong cách của Macbook là giải pháp mở rộng bộ nhớ lưu trữ tốt nhất cho Macbook của bạn. Ngoài ra bạn cũng có thể dùng trên các dòng Laptop, Notebook và các loại máy tính bảng khác có hỗ trợ SDXC. Thương hiệu SiliconPower","NHASANXUAT":"Silicon Power","MODEL":"L03","CHUANGIAOTIEP":"– Adapter 23 * 24 * 2.1 mm – MicroSDXC (không bao gồm thẻ nhớ)","BAOHANH":"12 tháng"},{"TEN":"Adapter chuyển đổi SSD Macbook 12+16 Pin sang M.2 PCIE cho PC","GIA":250000,"HINHANH":"SSD/Mac-12pin-16pin-to-PCIe-02-280x315.jpg","MOTA":"Thông số kĩ thuật Nhà sản xuất OEM Model OEM Kích thước M.2 2242 2260 2280 22110 Chuần giao tiếp – SSD Macbook 12+ 16 Pin – M.2 PCIe Tốc độ hỗ trợ PCIe Bảo hành 6 tháng Adapter chuyển đổi SSD Macbook 12+16 Pin sang M.2 PCIE cho PC Hỗ trợ chuyển đổi chuẩn ổ cứng của Macbook sang chuẩn M.2 PCIe dùng cho Mainboard máy bàn. Các dòng ổ cứng Macbook tương thích: 2013 Macbook Pro: A1493, A1502 (MD864, MD865, MD293, Md294) 2013 MacBook Pro Retina: A1398, A1502 (ME864, ME865, ME866, ME293, ME294) 2013 Macbook Air: A1465, A1466 (MD711, MD712, MD760, MD761) 2014 Macbook Air: A1465, A1466 (MD711, MD712, MD760, MD761) 2014 MacBook Pro Retina: A1502, A1398 (MGX72, MGX82, MGX92, MGXA2, MGXC2) 2015 MacBook Pro Retina: A1502, A1398 (MF839, MF840, MF841, MGXA2, MGXC2) 2015 MacBook Air: A1465, A1466 (MJVM2, MJVP2, MJVE2, MJVG2) Mac Pro: ME253, MD878","NHASANXUAT":"OEM","MODEL":"OEM","BAOHANH":"6 tháng"},{"TEN":"Thẻ mở rộng bộ nhớ Silicon Power xDrive L13 64GB","GIA":790000,"HINHANH":"SSD/The-mo-rong-bo-nho-Silicon-Power-xDrive-L13-64GB-280x315.jpg","MOTA":"Thông số kĩ thuật Nhà sản xuất Silicon Power Model L13 Kích thước 22.6 * 28.4 * 3.1 mm Dòng máy hỗ trợ -MacBookAir 13″ (Late 2010~Early 2015) -MacBookPro 13″ (Mid 2009~Mid 2012) -MacBookPro 15″ (Mid 2009~Mid 2012) -MacBook Pro 15″ (Retina) (Mid 2012~Early 2013) Dung lượng 64 GB Tốc độ đọc ~ 90MB/s Tốc độ ghi ~ 60MB/s Bảo hành 24 tháng Silicon Power xDrive L13 Giải pháp tốt nhất để mở rộng bộ nhớ cho MacBook Thẻ nhớ mở rộng bộ nhớ Silicon Power xDrive L13 giúp bạn giải quyết vấn đề cực nhanh khi không gian lưu trữ trên Macbook của bạn bị hạn chế với dung lượng lên đến 128GB, đủ để lưu trữ 48.000 hình ảnh độ phân giải cao, 33.000 bài hát MP3 hoặc 28 giờ Full HD (9Mbps) Video. Tốc độ truyền tải siêu nhanh lên đến 90MB/s đọc và 60MB/s ghi Thẻ nhớ mở rộng bộ nhớ Silicon Power xDrive L13 được trang bị tốc độ rất nhanh lên tới 90MB/s đọc và 60 MB/s ghi, giúp mở rộng dung lượng của MacBook mà không làm giảm hiệu năng của hệ thống. Thiết kế liền mạch Phù hợp với phong cách Mac Thẻ nhớ mở rộng bộ nhớ Silicon Power xDrive L13 cung cấp các giải pháp mở rộng không gian lưu trữ ngay lập tức cho người sử dụng MacBook, thẻ nhớ mở rộng bộ nhớ Silicon Power xDrive L13 được thiết kế đặc biệt với kích thước để có thể được gắn thật sát trong MacBook Air và MacBook Pro, không bị dư ra và rất đẹp mắt. Dễ dàng tháo lắp Thẻ nhớ mở rộng bộ nhớ Silicon Power xDrive L13 được trang bị với các thiết kế sáng tạo để mang sự thuận tiện hơn và sử dụng trực quan hơn. Dấu chấm nổi độc quyền được thiết kế cho người dùng để bạn có thể nhanh chóng theo dõi vị trí của khe cắm thẻ nhớ mà không cần phải tìm kiếm. Và thiết kế 2 rãnh đặc biệt hai bên rất nhỉ giúp bạn dễ dàng tháo sản phẩm ra khi không cần sử dụng.","NHASANXUAT":"Silicon Power","MODEL":"L13","DUNGLUONG":"64 GB","BAOHANH":"24 tháng"},{"TEN":"SSD Apacer Armor AS681 SATA III 2.5 Inch 120GB","GIA":890000,"HINHANH":"SSD/AS681-01-280x315.jpg","MOTA":"Thông số kĩ thuật Nhà sản xuất Apacer Model AS681 Chuẩn giao tiếp Sata III Kích thước 2.5″ Dung lượng 120 GB Random 4k 95.000 IOPS Đọc tuần tự 495 MB/s Ghi tuần tự 385 MB/s MTBF 1.000.000 h NAND Flash TLC Bảo hành 36 tháng Ổ cứng SSD Apacer Armor AS681 SATA III 2.5 Inch Trang bị không thể thiếu của những vương quốc máy tính Với nhu cầu ngày càng cao về tốc độ đáp ứng của bộ nhớ trong các hệ thống máy tính. Apacer đã cho ra mắt sản phẩm mới nhất của mình: ổ cứng SSD Apacer Armor AS681 SATA III 2.5 Inch chất lượng cao, đáng tin cậy, cho phép máy tính của bạn hoạt động với tốc độ nhanh nhất. Với những điểm chú trọng tất cả cho hiệu năng và tốc độ của ổ cứng, ổ cứng SSD Apacer Armor AS681 SATA III 2.5 Inch được trang bị chuẩn giao tiếp SATA III thế hệ mới nhất. Mang đến hiệu suất tuyệt vời khi tốc độ đọc/ghi đạt 545/520 MB/s (test với bản dung lượng 960GB). Ổ cứng SSD Apacer Armor AS681 SATA III 2.5 Inch thật sự là một giải pháp nâng cấp hiệu năng hoàn hảo cho máy tính để bàn chơi game và máy tính xách tay của bạn. Tốc độ siêu nhanh lên đến 545MB/s Với những công nghệ hàng đầu và quy mô thị trường rất lớn trong lĩnh vực SSD cho phép thương hiệu Apacer tung ra các sản phẩm SSD xuất sắc nhất và rất hiệu quả về kinh tế. Người dùng có thể dễ dàng trải nghiệm tốc độ cao của SSD với giá thành rẻ nhất. Ổ cứng SSD Apacer Armor AS681 SATA III 2.5 Inch được trang bị chuẩn giao tiếp SATA III thế hệ mới nhất, cung cấp tốc độ truyền tải cực nhanh 6 Gbps, cùng với thiết kế truyền dẫn đồng bộ 8 kênh tiên tiến nhất. Do đó, tốc độ đọc/ghi lên đến 545/520 MB/s. Tiết kiệm điện năng Ổ cứng SSD Apacer Armor AS681 SATA III 2.5 Inch tự hào có các chức năng nâng cao Wear-Leveling và ECC (Error Correction Code), hỗ trợ Windows 7 TRIM. Điều này không chỉ kéo dài tuổi thọ SSD và cải thiện tính ổn định của hoạt động, mà còn duy trì hiệu suất lâu dài. Ổ cứng SSD Apacer Armor AS681 SATA III 2.5 Inch được hỗ trợ bảo hành toàn cầu 3 năm. Nhiều dung lượng cho bạn lựa chọn Apacer muốn rằng ổ cứng SSD Apacer Armor AS681 SATA III 2.5 Inch có thể làm ổ đĩa hệ thống, và ổ đĩa lưu trữ dữ liệu cho người dùng. Nên ổ cứng SSD Apacer Armor AS681 SATA III 2.5 Inch được trang bị dung lượng 120/240/480/960GB để đáp ứng mọi nhu cầu của người dùng khác nhau. Ngoài ra, phần mềm Widget SSD đi kèm sẽ cho phép người dùng kiểm tra trạng thái SSD cũng như cập nhật Firmware thường xuyên. Thương hiệu Apacer Dung lượng ổ cứng 120GB – 128GB Dạng ổ cứng 2.5 Inches Chuẩn giao tiếp SATA III 6Gb/s","NHASANXUAT":"Apacer","MODEL":"AS681","CHUANGIAOTIEP":"Sata III","DUNGLUONG":"120 GB","BAOHANH":"36 tháng"},{"TEN":"Thẻ mở rộng bộ nhớ Transcend JetDrive Lite 350 64GB cho MacBook Pro Retina 15″","GIA":990000,"HINHANH":"SSD/The-mo-rong-bo-nho-Transcend-JetDrive-Lite-350-64GB-280x315.jpg","MOTA":"Thông số kĩ thuật Nhà sản xuất Transcend Model TS64GJDL350 Dung lượng 64 GB Tốc độ đọc 95 MB/s Tốc Độ ghi 60 MB/s Flash Type Synchronous MLC Dòng máy hỗ trợ MacBook Pro Retina, 15″ Mid 2012 ~ Early 2013 Bảo hành 24 tháng JetDrive Lite – Thẻ mở rộng bộ nhớ cho Macbook Air Transcend JetDrive Lite thẻ mở rộng lưu trữ cho MacBook Air và MacBook Pro Retina. JetDrive Lite mở rộng bộ nhớ Macbook của bạn một cách nhanh chóng và dễ dàng khi bạn cần có không gian lưu trữ lớn hơn mà không cần thay thế bất kỳ thiết bị nào của MacBook. Dễ dàng sử dụng Chỉ cần gắn JetDrive Lite vào khe đọc thẻ ở mặt bên của MacBook của bạn là không gian lưu trữ đã được tăng lên. Với dung lượng lên đến 128GB, bạn có thể lưu trữ lên đến 62.000 bức ảnh, 32.000 bài hát hoặc 1920 phút video Full HD. Blazing tốc độ cao Thẻ JetDrive Lite được thiết kế với chất lượng cao nhất và công nghệ flash MLC có thể đạt được tốc độ đọc tối đa 95 MB/s và tốc độ ghi lên đến 60MB/s. Cho độ bền và đáp ứng tốc độ rất cao, không làm suy hao hiệu năng của Macbook. Độ tương thích cao Được thiết kế thích hợp cho từng model MacBook, thẻ mở rộng Transcend JetDrive Lite được thiết kế để tích hợp liền mạch với MacBook của bạn. Bảo vệ an toàn cho dữ liệu của bạn JetDrive Lite được hỗ trợ thêm phần mềm độc quyền và hoàn toàn miễn phí của Transcend JetDrive Toolbox cho phép người dùng khôi phục lại hình ảnh, video, file MP3 và PDF vô tình xóa chỉ trong một vài cú nhấp chuột đơn giản. Chống nước hoàn hảo JetDrive Lite flash được sản xuất bằng công nghệ COB tiên tiến (chip-on-board), giúp cho sản phẩm chịu được nước, bụi, và sốc. Vì vậy, bất kể có tác nhân vật lý nào ngoại trừ những tác nhân làm gãy, nứt hoặc cháy, JetDrive Lite vẫn đảm bảo an toàn cho dữ liệu của bạn. Phù hợp với nhiều dòng Macbook JetDrive Lite được thiết kế đặc biệt dành cho MacBook Air và MacBook Pro Retina. Hiện có bốn kích cỡ khác nhau, mỗi loại được thiết kế kích thước phù hợp cho từng loại khe cắm có kích thước khác nhau. Lựa chọn sản phẩm phù hợp với máy Mac của bạn Model SSD tương thích JetDrive Lite tương thích Macbook Air 11″ \u0026 13″ Late 2010 MacbookAir 3,1 MC505xx/A MC506xx/A Chỉ hỗ trợ JetDrive 500 240GB Late 2010 MacbookAir 3,2 MC503xx/A MC504xx/A JetDrive 500 JetDrive Lite 130 Mid 2011 MacbookAir 4,1 MC968xx/A MC969xx/A Mid 2011 MacbookAir 4,2 MC965xx/A MC966xx/A JetDrive Lite 130 Mid 2012 MacbookAir 5,1 MD223xx/A MD224xx/A JetDrive 520 Mid 2012 MacbookAir 5,2 MD231xx/A MD232xx/A JetDrive Lite 130 Mid 2013 MacbookAir 6,2 MD760xx/A MD761xx/A Early 2014 MacbookAir 6,2 MD760xx/B MD761xx/B Early 2015 Macbook Pro 13″ Mid 2009 MacbookPro 5,5 MB990xx/A MB991xx/A JetDrive 420 Mid 2010 MacbookPro 7,1 MC374xx/A MC375xx/A Early 2011 MacbookPro 8,1 MC700xx/A MC724xx/A Late 2011 MacbookPro 8,1 MD313xx/A MC314xx/A Mid 2012 MacbookPro 9,2 MD101xx/A MD102xx/A Late 2012 MacbookPro 10,2 MD212 MD213 JetDrive 720 JetDrive Lite 330 Early 2013 MacbookPro 10,2 MD212xx/A ME662xx/A Late 2013 MacbookPro 11,1 ME864xx/A ME865xx/A ME866xx/A Mid 2014 MacbookPro 11,1 MGX72xx/A MGX82xx/A MGX92xx/A Early 2015 Macbook Pro 15″ Late 2008 MacbookPro 5,1 MB470xx/A MB471xx/A MC026xx/A JetDrive 420 Mid 2009 MacbookPro 5,3 MB985xx/A MB986xx/A MC118xx/A Mid 2010 MacbookPro 6,2 MC371xx/A MC372xx/A MC373xx/A Early2011 Late2011 MacbookPro 8,2 MD318xx/A MD322xx/A MC721xx/A MC723xx/A Mid 2012 MacbookPro 9,1 MD103xx/A MD104xx/A JetDrive Lite 350 MacbookPro 10,1 MC975xx/A MC976xx/A JetDrive 725 Early 2013 MacbookPro 10,1 ME664xx/A ME665xx/A Late 2013 MacbookPro 11,2 MacbookPro 11,3 ME293xx/A ME294xx/A JetDrive Lite 360 Mid 2014 MacbookPro 11,2 MacbookPro 11,3 MGXA2xx/A MGXC2xx/A Mid 2015 Macbook Pro 17″ Late 2008 MacbookPro 5,1 MB766xx/A JetDrive 420 Early 2009 Mid 2009 MacbookPro 5,2 MB604xx/A MC226xx/A Mid 2010 MacbookPro 6,1 MC024xx/A Early 2011 Late 2011 MacbookPro 8,3 MC725xx/A MD311xx/A Macbook 13″ Early 2008 Late 2008 Macbook 4,1 MB402xx/B MB402xx/A MB403xx/A MB404xx/A JetDrive 420 Aluminum Late 2008 Macbook 5,1 MB466xx/A MB467xx/A Early 2009 Mid 2009 Macbook 5,2 MB881xx/A MC240LL/A Late 2009 Macbook 6,1 MC207xx/A Mid 2010 Macbook 7,1 MC516xx/A Mac Mini Mid 2010 MacMini 4,1 / 5,1 / 5,2 / 6,1 / 6,2 MC270xx/A MC438xx/A JetDrive 420 Mid 2011 MC936xx/A MC816xx/A MC815xx/A Late 2012 MD389xx/A MD388xx/A MD387xx/A","NHASANXUAT":"Transcend","MODEL":"TS64GJDL350","DUNGLUONG":"64 GB","BAOHANH":"24 tháng"},{"TEN":"SSD Apacer M.2 2280 SATA III 120GB AST280","GIA":1030000,"HINHANH":"SSD/AST280-01-280x315.jpg","MOTA":"Thông số kĩ thuật Nhà sản xuất Apacer Model AST280 Chuẩn giao tiếp M.2 2280 SATA III Kích thước 22mm x 80mm Dung lượng 120 GB Tốc độ đọc 500 MB/s Tốc độ ghi 470 MB/s 4k Random 80.000 IOPs NAND Flash TLC TBW 300 TB Bảo hành 36 tháng Ổ cứng SSD Apacer M.2 2280 SATA III Z280 Siêu nhanh – Siêu nhỏ gọn Ngày nay, nhu cầu sử dụng SSD tốc độ cao của người tiêu dùng đang là xu hướng cần được sự quan tâm của các nhà sản xuất bộ nhớ trên thế giới. Nhận thức được xu hướng đó, Apacer Technology Inc đã cho ra đời ổ cứng SSD Apacer M.2 2280 SATA III AST280 với tốc độ lên đến 500MB/s, giúp giảm thiểu tối đa thời gian đáp ứng của hệ thống, kích thước nhỏ gọn cùng dung lượng cực cao lên đến 240GB. Ổ cứng tương thích với các máy tính xách tay và các dòng Mainboard cao cấp hỗ trợ cổng giao tiếp M.2 2280. Kích thước nhỏ gọn Ổ cứng SSD Apacer M.2 2280 SATA III AST280 với kích thước M.2 2280 cùng với chuẩn tốc độ của chuẩn SATA III 6Gbps sẽ mang đến một hiệu suất cùng độ tin cậy tuyệt với trong hình hài bé nhỏ. Tốc độ cực cao Với tốc độ đọc lên đến 520MB/s sẽ đáp ứng mọi nhu cầu về tốc độ của các Game thủ. Giảm thiểu tối đa độ trễ, tăng hiệu suất máy tính cũng như giúp bạn trải nghiệm tốt nhất khi chơi Games. Độ tin cậy cực cao Ổ cứng SSD Apacer M.2 2280 SATA III AST280 được trang bị những công nghệ tiên tiến nhất như: ECC tự sửa lỗi, hỗ trợ S.M.A.R.T, TRIM,… cùng các công nghệ khác giúp theo dõi lỗi và tự sửa lỗi khi cần thiết. Thương hiệu Apacer Dạng ổ cứng M.2 Chuẩn giao tiếp SATA III 6Gb/s Dung lượng ổ cứng 120GB – 128GB","NHASANXUAT":"Apacer","MODEL":"AST280","CHUANGIAOTIEP":"M.2 2280 SATA III","DUNGLUONG":"120 GB","BAOHANH":"36 tháng"},{"TEN":"SSD Western Digital Green Sata III 120GB","GIA":1040000,"HINHANH":"SSD/WD_GREEN_SSD-280x315.jpg","MOTA":"Thông số kĩ thuật Nhà sản xuất Western Digital Model WDS120G2G0A Chuẩn giao tiếp Sata III Kích thước 2.5 inch Dung lượng 120 GB Random 4k 65.000 IOPS Tốc độ đọc 540 MB/s Tốc độ ghi 100 MB/s MTTF 1.750.000 giờ Bảo hành 36 tháng Ổ cứng SSD Western Digital Green Sata III Ổ cứng SSD Western Digital Green Sata III là giải pháp tốt nhất để tối ưu hóa hiệu năng của máy tính, cung cấp hiệu suất và độ tin cậy cực cao khi được trang bị tất cả các công nghệ tiên tiến nhất hiện nay. Sản phẩm được kiểm tra, thử nghiệm và đã vượt qua tất cả các bài test trong WD F.I.T Lab, mang đến cho bạn giải pháp nâng cấp máy tính tuyệt vời nhất. Hiệu suất siêu cao Ổ cứng SSD Western Digital Green Sata III có tốc độ đọc lên đến 540MB/s giúp cho các ứng dụng chạy nhanh hơn, thời gian đáp ứng thấp hơn và tăng tốc độ truyền tải dữ liệu. Với ổ cứng SSD Western Digital Green Sata III, bạn sẽ có được một trải nghiệm tuyệt vời trên hệ thống máy tính của bạn và tiết kiệm được rất nhiều thời gian. WesternDigital – Thương hiệu hàng đầu thế giới Với tuổi thọ hoạt động (MTTF) lên đến 1.750.000 giờ, Ổ cứng SSD Western Digital Green Sata III cho chất lượng về độ bền tuyệt vời nhất. Cùng với các công nghệ tự sửa lỗi (ECC), ổ cứng SSD Western Digital Green Sata III sẽ bảo vệ dữ liệu của bạn với độ tin cậy cực kì lâu dài. Tối ưu hóa đa nhiệm Ổ cứng SSD Western Digital Green Sata III có thể chạy nhiều ứng dụng đồng thời cùng 1 lúc một cách dễ dàng. Chỉnh sửa video 4K, kiểm tra Email của bạn và quét virus ở chế độ ẩn,… tất cả mọi thứ có thể chạy cùng một lúc mà không hề làm chậm hệ thống của bạn. Tương thích mọi máy tính Ổ cứng SSD Western Digital Green Sata III có kích thước chuẩn 2,5 inch và có cả phiên bản M.2 2280, đáp ứng mọi nhu cầu cho các hệ thống máy tính để bàn máy tính xách tay của bạn. Chất lượng đã được kiểm chứng Ổ cứng SSD Western Digital Green Sata III đã vượt qua tất cả các bài test về khả năng tương thích và độ tin cậy, và được chứng nhận bởi WD FIT Labs. Phần mềm quản lý WD SSD Dashboard đi kèm WD SSD Dashborad cung cấp cho bạn một bộ công cụ mạnh mẽ để theo dõi những thứ như hiệu năng, sức khỏe ổ đĩa, cập nhật phiên bản firmware, các thuộc tính SMART, và nhiều hơn nữa. Trọng lượng 200 kg Kích thước 150 x 120 x 25 cm Thương hiệu Western Digital Dạng ổ cứng 2.5 Inches Chuẩn giao tiếp SATA III 6Gb/s","NHASANXUAT":"Western Digital","MODEL":"WDS120G2G0A","CHUANGIAOTIEP":"Sata III","DUNGLUONG":"120 GB","BAOHANH":"36 tháng"},{"TEN":"SSD Western Digital Green M.2 2280 Sata III 120GB","GIA":1050000,"HINHANH":"SSD/SSD_M.2_2280_WD_Green_240GB-280x315.jpg","MOTA":"Thông số kĩ thuật Nhà sản xuất Western Digital Model WDS120G2G0B Chuẩn giao tiếp M.2 Sata III Kích thước M.2 2280 Dung lượng 120 GB Random 4k 63.000 IOPS Tốc độ đọc 540 MB/s Tốc độ ghi 100 MB/s MTTF 1.750.000 giờ Bảo hành 36 tháng Ổ cứng SSD Western Digital Green Sata III Ổ cứng SSD Western Digital Green Sata III là giải pháp tốt nhất để tối ưu hóa hiệu năng của máy tính, cung cấp hiệu suất và độ tin cậy cực cao khi được trang bị tất cả các công nghệ tiên tiến nhất hiện nay. Sản phẩm được kiểm tra, thử nghiệm và đã vượt qua tất cả các bài test trong WD F.I.T Lab, mang đến cho bạn giải pháp nâng cấp máy tính tuyệt vời nhất. Hiệu suất siêu cao Ổ cứng SSD Western Digital Green Sata III có tốc độ đọc lên đến 540MB/s giúp cho các ứng dụng chạy nhanh hơn, thời gian đáp ứng thấp hơn và tăng tốc độ truyền tải dữ liệu. Với ổ cứng SSD Western Digital Green Sata III, bạn sẽ có được một trải nghiệm tuyệt vời trên hệ thống máy tính của bạn và tiết kiệm được rất nhiều thời gian. WesternDigital – Thương hiệu hàng đầu thế giới Với tuổi thọ hoạt động (MTTF) lên đến 1.750.000 giờ, Ổ cứng SSD Western Digital Green Sata III cho chất lượng về độ bền tuyệt vời nhất. Cùng với các công nghệ tự sửa lỗi (ECC), ổ cứng SSD Western Digital Green Sata III sẽ bảo vệ dữ liệu của bạn với độ tin cậy cực kì lâu dài. Tối ưu hóa đa nhiệm Ổ cứng SSD Western Digital Green Sata III có thể chạy nhiều ứng dụng đồng thời cùng 1 lúc một cách dễ dàng. Chỉnh sửa video 4K, kiểm tra Email của bạn và quét virus ở chế độ ẩn,… tất cả mọi thứ có thể chạy cùng một lúc mà không hề làm chậm hệ thống của bạn. Tương thích mọi máy tính Ổ cứng SSD Western Digital Green Sata III có kích thước chuẩn 2,5 inch và có cả phiên bản M.2 2280, đáp ứng mọi nhu cầu cho các hệ thống máy tính để bàn máy tính xách tay của bạn. Chất lượng đã được kiểm chứng Ổ cứng SSD Western Digital Green Sata III đã vượt qua tất cả các bài test về khả năng tương thích và độ tin cậy, và được chứng nhận bởi WD FIT Labs. Phần mềm quản lý WD SSD Dashboard đi kèm WD SSD Dashborad cung cấp cho bạn một bộ công cụ mạnh mẽ để theo dõi những thứ như hiệu năng, sức khỏe ổ đĩa, cập nhật phiên bản firmware, các thuộc tính SMART, và nhiều hơn nữa. Chuẩn giao tiếp SATA III 6Gb/s Dạng ổ cứng M.2 Thương hiệu Western Digital Dung lượng ổ cứng 120GB – 128GB","NHASANXUAT":"Western Digital","MODEL":"WDS120G2G0B","CHUANGIAOTIEP":"M.2 Sata III","DUNGLUONG":"120 GB","BAOHANH":"36 tháng"}]