[
    {
        "TEN": "Ổ cứng để bàn HDD 3TB Western Digital My Book WDBBGB0030HBK-SEN",
        "GIA": 3350000,
        "HINHANH": "Ổ Cứng Desktop  Cloud/WD-MyBook-2017-01-280x315.jpg",
        "MOTA": "Thông số kĩ thuật Nhà sản xuất Western Digital Model My Book Chuẩn giao tiếp USB 3.0 Dung lượng 3 TB Chia sẻ trực tuyến qua Internet Không Số ổ cứng Single Drive Phần mềm hỗ trợ trên máy tính WD Discovery (Hỗ trợ trên Windows. Bạn có thể dowload tại ĐÂY) Bảo hành 36 tháng Ổ cứng để bàn HDD Western Digital My Book – Tự động sao lưu dữ liệu Cuộc sống của chúng ta luôn bận rộn và tạo ra hàng tấn nội dung kĩ thuật số hàng ngày, và bạn luôn có một nỗi lo lắng đối với việc lưu trữ khối lượng dữ liệu lớn. Ổ cứng để bàn HDD Western Digital My Book có dung lượng lưu trữ cực lớn để bạn có thể tự tin sao lưu các dữ liệu của mình. Mở rộng không gian lưu trữ ảnh, video, nhạc và tài liệu của bạn. Complete Backup, Tương thích Time Machine Được trang bị phần mềm WD Backup cho Windows và Apple Time Machine tương thích cho Mac, ổ cứng để bàn HDD Western Digital My Book có thể sao lưu ảnh, video, nhạc và tài liệu của bạn. Ổ cứng máy tính để bàn My Book cũng hoạt động tốt với phần mềm Acronis True Image WD Edition để lên kế hoạch sao lưu toàn bộ hệ thống. Bảo vệ mật khẩu bằng Hardware Encryption Với mã hóa phần cứng AES 256-bit được tích hợp với phần mềm Bảo mật của WD, bạn có thể đặt mật khẩu cá nhân của riêng mình để giúp giữ cho dữ liệu của bạn an toàn và riêng tư. Dễ dàng sử dụng Ổ cứng để bàn HDD Western Digital My Book với chuẩn giao tiếp USB 3.0 chỉ cần cắm và sử dụng, luông sẵn sàng để bạn lưu lại những kỷ niệm và sao lưu tất cả dữ liệu. Phần mềm WD Backup và WD Security giúp bảo vệ dữ liệu của bạn. Ổ cứng để bàn HDD Western Digital My Book cũng tương thích hoàn toàn với Apple Time Machine. Thiết kế nhỏ gọn Với thiết kế nhỏ gọn và cực kỳ thời trang của ổ cứng để bàn HDD Western Digital My Book mang lại sự tinh tế và sang trọng cho khu vực làm việc. Với dung lượng lưu trữ tối đa 8TB, bạn có thể thoải mái lưu trữ thế giới kỹ thuật số của bạn. Dung lượng cực lớn Với dung lượng từ 3TB lên tới 8TB, sẽ có rất nhiều chỗ để bạn có thể lưu trữ số lượng lớn các ảnh, video và âm nhạc bạn yêu thích cộng với các tài liệu quan trọng của bạn. Western Digital – Chất lượng hàng đầu thế giới Hàng triệu người trên thế giới hiện đang tin tưởng và lưu trữ dữ liệu của họ vào ổ cứng để bàn HDD Western Digital My Book. Được thiết kế để đáp ứng các yêu cầu khắt khe của WD đối với độ bền, khả năng chịu sốc và độ tin cậy lâu dài, ổ cứng để bàn HDD Western Digital My Book cực kỳ đáng tin cậy với chế độ bảo hành lên đến 3 năm. Thương hiệu Western Digital",
        "NHASANXUAT": "Western Digital",
        "MODEL": "My Book",
        "CHUANGIAOTIEP": "USB 3.0",
        "DUNGLUONG": "3 TB",
        "BAOHANH": "36 tháng"
    },
    {
        "TEN": "Ổ cứng mạng HDD 2TB Western Digital My Cloud Home WDBVXC0020HWT",
        "GIA": 3790000,
        "HINHANH": "Ổ Cứng Desktop  Cloud/WD-MyCloud-2017-01-280x315.jpg",
        "MOTA": "Thông số kĩ thuật Nhà sản xuất Western Digital Model My Cloud Home Chuẩn giao tiếp Gigabit Lan 10/100/1000 Ethernet port Dung lượng 2TB Chuẩn giao tiếp USB mở rộng USB 3.0 Chia sẻ trực tuyến qua Internet Có Số ổ cứng Single Drive Phần mềm hỗ trợ trên thiết bị di động MyCloud (có sẵn trên Appstore, Google Play,…) Phần mềm hỗ trợ trên máy tính WD Discovery (Hỗ trợ trên Windows. Bạn có thể dowload tại ĐÂY) Bảo hành 24 tháng Ổ cứng mạng HDD Western Digital My Cloud Home Chia sẻ dữ liệu trên Cloud theo cách riêng của bạn Ổ cứng mạng HDD Western Digital My Cloud Home là thiết bị lưu trữ hoàn toàn mới thuộc dòng sản phẩm My Cloud Home của Western Digital. Bạn chỉ cần cắm trực tiếp vào bộ định tuyến Wi-Fi ở nhà là có thể dễ dàng lưu trữ, sắp xếp, kiểm soát, chia sẻ toàn bộ dữ liệu của bạn một cách tập trung ở bất kỳ nơi đâu, chỉ cần có Internet. MyCloud Home – Lưu trữ dữ liệu tập trung Ổ cứng mạng HDD Western Digital My Cloud Home giúp bạn có nhiều không gian lưu trữ để lưu giữ ảnh, video và dữ liệu của bạn từ điện thoại, máy tính bảng, máy tính cá nhân và thiết bị lưu trữ bên ngoài của bạn ở một nơi và bạn có thể truy cập bất kỳ lúc nào ở bất kỳ nơi đâu, chỉ cần có Internet. Truy cập dữ liệu từ di động – On The Go Bạn có thể sử dụng ứng dụng dành cho điện thoại di động “My Cloud“, ứng dụng dành cho máy tính để bàn “WD Discovery” hoặc truy cập trực tiếp trên trang chủ “MyCloud.com” để upload, truy cập và chia sẻ những hình ảnh và Video của bạn ở bất cứ nơi nào bạn có kết nối internet. Cực kỳ nhanh chóng và dễ dàng. Tự động sao lưu hình ảnh và Video trên điện thoại của bạn Cổng USB hỗ trợ USB giúp mở rộng bộ nhớ thêm cho ổ cứng Desktop Sync Tính năng Desktop Sync giúp bạn lưu giữ các thư mục yêu thích của bạn trên máy tính PC Windows và máy Mac đồng thời liên tục đồng bộ dữ liệu với thiết bị My Cloud Home, vừa giúp backup dữ liệu vừa cho phép bạn truy cập dữ liệu cực kỳ linh động. Streaming Video cực kỳ mượt Ổ cứng mạng HDD Western Digital My Cloud Home có thể Streaming các Video cá nhân của bạn ở mọi nơi, tính năng được hỗ trợ trên phần mềm “My Cloud” của thiết bị di dộng, “WD Discovery” trên máy tính hoặc trên trang chủ MyCloud.com. Tính năng nổi bật: Dễ dàng tìm kiếm nội dung: chức năng tìm kiếm được tích hợp giúp bạn tìm nhanh ảnh, video, phim và tài liệu trên My Cloud Home hoặc trên MyCloud.com. Khả năng phân quyền truy cập cho từng người dùng: bạn có thể cho phép rất nhiều người dùng sử dụng chung My Cloud Home, mỗi người sẽ có tài khoản cá nhân riêng. Dựa vào tài khoản riêng bạn có thể thiết lập không gian riêng tư cho từng người mà chỉ có họ mới có thể truy cập vào thư mục bạn đã chỉ định. Họ có thể quản lý, truy cập và chia sẻ nội dung của họ theo ý muốn. Rất an toàn. Đồng bộ dữ liệu từ các dịch vụ Cloud khác: My Cloud Home giúp bạn lưu trữ mọi thứ ở một nơi, bao gồm các dịch vụ lưu trữ Cloud khác như: Dropbox, Box, Google Drive ™, Facebook,… Tất cả sẽ được tự động tải về và lưu trữ tập trung tại một nơi. Tự động Backup máy tính cá nhân và máy MacOS: My Cloud Home có dung lượng rất lớn và được cắm trực tiếp vào mạng nội bộ trong nhà hoặc cơ quan làm việc của bạn. Nó không chỉ hỗ trợ lưu dữ liệu bình thường mà còn có chức năng lưu trữ Backup cả hệ thống máy tính cho bạn. Hoạt động cực kỳ mượt mà với phần mềm Windows Backup và Time Machine. Bảo vệ bằng mật khẩu: Giúp bảo vệ tất cả dữ liệu của bạn bằng mật khẩu để tránh bị truy cập trái phép, hỗ trợ cả Passcode và Touch ID trên Smartphone. Thương hiệu Western Digital",
        "NHASANXUAT": "Western Digital",
        "MODEL": "My Cloud Home",
        "CHUANGIAOTIEP": "USB mở rộng USB 3.0",
        "DUNGLUONG": "2TB",
        "BAOHANH": "24 tháng"
    },
    {
        "TEN": "Ổ cứng để bàn HDD 4TB Western Digital My Book WDBBGB0040HBK-SEN",
        "GIA": 4350000,
        "HINHANH": "Ổ Cứng Desktop  Cloud/WD-MyBook-2017-01-280x315.jpg",
        "MOTA": "Thông số kĩ thuật Nhà sản xuất Western Digital Model My Book Chuẩn giao tiếp USB 3.0 Dung lượng 4 TB Chia sẻ trực tuyến qua Internet Không Số ổ cứng Single Drive Phần mềm hỗ trợ trên máy tính WD Discovery (Hỗ trợ trên Windows. Bạn có thể dowload tại ĐÂY) Bảo hành 36 tháng Ổ cứng để bàn HDD Western Digital My Book – Tự động sao lưu dữ liệu Cuộc sống của chúng ta luôn bận rộn và tạo ra hàng tấn nội dung kĩ thuật số hàng ngày, và bạn luôn có một nỗi lo lắng đối với việc lưu trữ khối lượng dữ liệu lớn. Ổ cứng để bàn HDD Western Digital My Book có dung lượng lưu trữ cực lớn để bạn có thể tự tin sao lưu các dữ liệu của mình. Mở rộng không gian lưu trữ ảnh, video, nhạc và tài liệu của bạn. Complete Backup, Tương thích Time Machine Được trang bị phần mềm WD Backup cho Windows và Apple Time Machine tương thích cho Mac, ổ cứng để bàn HDD Western Digital My Book có thể sao lưu ảnh, video, nhạc và tài liệu của bạn. Ổ cứng máy tính để bàn My Book cũng hoạt động tốt với phần mềm Acronis True Image WD Edition để lên kế hoạch sao lưu toàn bộ hệ thống. Bảo vệ mật khẩu bằng Hardware Encryption Với mã hóa phần cứng AES 256-bit được tích hợp với phần mềm Bảo mật của WD, bạn có thể đặt mật khẩu cá nhân của riêng mình để giúp giữ cho dữ liệu của bạn an toàn và riêng tư. Dễ dàng sử dụng Ổ cứng để bàn HDD Western Digital My Book với chuẩn giao tiếp USB 3.0 chỉ cần cắm và sử dụng, luông sẵn sàng để bạn lưu lại những kỷ niệm và sao lưu tất cả dữ liệu. Phần mềm WD Backup và WD Security giúp bảo vệ dữ liệu của bạn. Ổ cứng để bàn HDD Western Digital My Book cũng tương thích hoàn toàn với Apple Time Machine. Thiết kế nhỏ gọn Với thiết kế nhỏ gọn và cực kỳ thời trang của ổ cứng để bàn HDD Western Digital My Book mang lại sự tinh tế và sang trọng cho khu vực làm việc. Với dung lượng lưu trữ tối đa 8TB, bạn có thể thoải mái lưu trữ thế giới kỹ thuật số của bạn. Dung lượng cực lớn Với dung lượng từ 3TB lên tới 8TB, sẽ có rất nhiều chỗ để bạn có thể lưu trữ số lượng lớn các ảnh, video và âm nhạc bạn yêu thích cộng với các tài liệu quan trọng của bạn. Western Digital – Chất lượng hàng đầu thế giới Hàng triệu người trên thế giới hiện đang tin tưởng và lưu trữ dữ liệu của họ vào ổ cứng để bàn HDD Western Digital My Book. Được thiết kế để đáp ứng các yêu cầu khắt khe của WD đối với độ bền, khả năng chịu sốc và độ tin cậy lâu dài, ổ cứng để bàn HDD Western Digital My Book cực kỳ đáng tin cậy với chế độ bảo hành lên đến 3 năm. Thương hiệu Western Digital",
        "NHASANXUAT": "Western Digital",
        "MODEL": "My Book",
        "CHUANGIAOTIEP": "USB 3.0",
        "DUNGLUONG": "4 TB",
        "BAOHANH": "36 tháng"
    },
    {
        "TEN": "Ổ cứng mạng HDD 4TB Western Digital My Cloud Home WDBVXC0040HWT",
        "GIA": 5590000,
        "HINHANH": "Ổ Cứng Desktop  Cloud/WD-MyCloud-2017-01-280x315.jpg",
        "MOTA": "Thông số kĩ thuật Nhà sản xuất Western Digital Model My Cloud Home Chuẩn giao tiếp Gigabit Lan 10/100/1000 Ethernet port Dung lượng 4TB Chuẩn giao tiếp USB mở rộng USB 3.0 Chia sẻ trực tuyến qua Internet Có Số ổ cứng Single Drive Phần mềm hỗ trợ trên thiết bị di động MyCloud (có sẵn trên Appstore, Google Play,…) Phần mềm hỗ trợ trên máy tính WD Discovery (Hỗ trợ trên Windows. Bạn có thể dowload tại ĐÂY) Bảo hành 24 tháng Ổ cứng mạng HDD Western Digital My Cloud Home Chia sẻ dữ liệu trên Cloud theo cách riêng của bạn Ổ cứng mạng HDD Western Digital My Cloud Home là thiết bị lưu trữ hoàn toàn mới thuộc dòng sản phẩm My Cloud Home của Western Digital. Bạn chỉ cần cắm trực tiếp vào bộ định tuyến Wi-Fi ở nhà là có thể dễ dàng lưu trữ, sắp xếp, kiểm soát, chia sẻ toàn bộ dữ liệu của bạn một cách tập trung ở bất kỳ nơi đâu, chỉ cần có Internet. MyCloud Home – Lưu trữ dữ liệu tập trung Ổ cứng mạng HDD Western Digital My Cloud Home giúp bạn có nhiều không gian lưu trữ để lưu giữ ảnh, video và dữ liệu của bạn từ điện thoại, máy tính bảng, máy tính cá nhân và thiết bị lưu trữ bên ngoài của bạn ở một nơi và bạn có thể truy cập bất kỳ lúc nào ở bất kỳ nơi đâu, chỉ cần có Internet. Truy cập dữ liệu từ di động – On The Go Bạn có thể sử dụng ứng dụng dành cho điện thoại di động “My Cloud“, ứng dụng dành cho máy tính để bàn “WD Discovery” hoặc truy cập trực tiếp trên trang chủ “MyCloud.com” để upload, truy cập và chia sẻ những hình ảnh và Video của bạn ở bất cứ nơi nào bạn có kết nối internet. Cực kỳ nhanh chóng và dễ dàng. Tự động sao lưu hình ảnh và Video trên điện thoại của bạn Cổng USB hỗ trợ USB giúp mở rộng bộ nhớ thêm cho ổ cứng Desktop Sync Tính năng Desktop Sync giúp bạn lưu giữ các thư mục yêu thích của bạn trên máy tính PC Windows và máy Mac đồng thời liên tục đồng bộ dữ liệu với thiết bị My Cloud Home, vừa giúp backup dữ liệu vừa cho phép bạn truy cập dữ liệu cực kỳ linh động. Streaming Video cực kỳ mượt Ổ cứng mạng HDD Western Digital My Cloud Home có thể Streaming các Video cá nhân của bạn ở mọi nơi, tính năng được hỗ trợ trên phần mềm “My Cloud” của thiết bị di dộng, “WD Discovery” trên máy tính hoặc trên trang chủ MyCloud.com. Tính năng nổi bật: Dễ dàng tìm kiếm nội dung: chức năng tìm kiếm được tích hợp giúp bạn tìm nhanh ảnh, video, phim và tài liệu trên My Cloud Home hoặc trên MyCloud.com. Khả năng phân quyền truy cập cho từng người dùng: bạn có thể cho phép rất nhiều người dùng sử dụng chung My Cloud Home, mỗi người sẽ có tài khoản cá nhân riêng. Dựa vào tài khoản riêng bạn có thể thiết lập không gian riêng tư cho từng người mà chỉ có họ mới có thể truy cập vào thư mục bạn đã chỉ định. Họ có thể quản lý, truy cập và chia sẻ nội dung của họ theo ý muốn. Rất an toàn. Đồng bộ dữ liệu từ các dịch vụ Cloud khác: My Cloud Home giúp bạn lưu trữ mọi thứ ở một nơi, bao gồm các dịch vụ lưu trữ Cloud khác như: Dropbox, Box, Google Drive ™, Facebook,… Tất cả sẽ được tự động tải về và lưu trữ tập trung tại một nơi. Tự động Backup máy tính cá nhân và máy MacOS: My Cloud Home có dung lượng rất lớn và được cắm trực tiếp vào mạng nội bộ trong nhà hoặc cơ quan làm việc của bạn. Nó không chỉ hỗ trợ lưu dữ liệu bình thường mà còn có chức năng lưu trữ Backup cả hệ thống máy tính cho bạn. Hoạt động cực kỳ mượt mà với phần mềm Windows Backup và Time Machine. Bảo vệ bằng mật khẩu: Giúp bảo vệ tất cả dữ liệu của bạn bằng mật khẩu để tránh bị truy cập trái phép, hỗ trợ cả Passcode và Touch ID trên Smartphone. Thương hiệu Western Digital",
        "NHASANXUAT": "Western Digital",
        "MODEL": "My Cloud Home",
        "CHUANGIAOTIEP": "USB mở rộng USB 3.0",
        "DUNGLUONG": "4TB",
        "BAOHANH": "24 tháng"
    },
    {
        "TEN": "Ổ cứng để bàn HDD 6TB Western Digital My Book WDBBGB0060HBK-SEN",
        "GIA": 7050000,
        "HINHANH": "Ổ Cứng Desktop  Cloud/WD-MyBook-2017-01-280x315.jpg",
        "MOTA": "Thông số kĩ thuật Nhà sản xuất Western Digital Model My Book Chuẩn giao tiếp USB 3.0 Dung lượng 6 TB Chia sẻ trực tuyến qua Internet Không Số ổ cứng Single Drive Phần mềm hỗ trợ trên máy tính WD Discovery (Hỗ trợ trên Windows. Bạn có thể dowload tại ĐÂY) Bảo hành 36 tháng Ổ cứng để bàn HDD Western Digital My Book – Tự động sao lưu dữ liệu Cuộc sống của chúng ta luôn bận rộn và tạo ra hàng tấn nội dung kĩ thuật số hàng ngày, và bạn luôn có một nỗi lo lắng đối với việc lưu trữ khối lượng dữ liệu lớn. Ổ cứng để bàn HDD Western Digital My Book có dung lượng lưu trữ cực lớn để bạn có thể tự tin sao lưu các dữ liệu của mình. Mở rộng không gian lưu trữ ảnh, video, nhạc và tài liệu của bạn. Complete Backup, Tương thích Time Machine Được trang bị phần mềm WD Backup cho Windows và Apple Time Machine tương thích cho Mac, ổ cứng để bàn HDD Western Digital My Book có thể sao lưu ảnh, video, nhạc và tài liệu của bạn. Ổ cứng máy tính để bàn My Book cũng hoạt động tốt với phần mềm Acronis True Image WD Edition để lên kế hoạch sao lưu toàn bộ hệ thống. Bảo vệ mật khẩu bằng Hardware Encryption Với mã hóa phần cứng AES 256-bit được tích hợp với phần mềm Bảo mật của WD, bạn có thể đặt mật khẩu cá nhân của riêng mình để giúp giữ cho dữ liệu của bạn an toàn và riêng tư. Dễ dàng sử dụng Ổ cứng để bàn HDD Western Digital My Book với chuẩn giao tiếp USB 3.0 chỉ cần cắm và sử dụng, luông sẵn sàng để bạn lưu lại những kỷ niệm và sao lưu tất cả dữ liệu. Phần mềm WD Backup và WD Security giúp bảo vệ dữ liệu của bạn. Ổ cứng để bàn HDD Western Digital My Book cũng tương thích hoàn toàn với Apple Time Machine. Thiết kế nhỏ gọn Với thiết kế nhỏ gọn và cực kỳ thời trang của ổ cứng để bàn HDD Western Digital My Book mang lại sự tinh tế và sang trọng cho khu vực làm việc. Với dung lượng lưu trữ tối đa 8TB, bạn có thể thoải mái lưu trữ thế giới kỹ thuật số của bạn. Dung lượng cực lớn Với dung lượng từ 3TB lên tới 8TB, sẽ có rất nhiều chỗ để bạn có thể lưu trữ số lượng lớn các ảnh, video và âm nhạc bạn yêu thích cộng với các tài liệu quan trọng của bạn. Western Digital – Chất lượng hàng đầu thế giới Hàng triệu người trên thế giới hiện đang tin tưởng và lưu trữ dữ liệu của họ vào ổ cứng để bàn HDD Western Digital My Book. Được thiết kế để đáp ứng các yêu cầu khắt khe của WD đối với độ bền, khả năng chịu sốc và độ tin cậy lâu dài, ổ cứng để bàn HDD Western Digital My Book cực kỳ đáng tin cậy với chế độ bảo hành lên đến 3 năm. Thương hiệu Western Digital",
        "NHASANXUAT": "Western Digital",
        "MODEL": "My Book",
        "CHUANGIAOTIEP": "USB 3.0",
        "DUNGLUONG": "6 TB",
        "BAOHANH": "36 tháng"
    },
    {
        "TEN": "Ổ cứng mạng HDD 6TB Western Digital My Cloud Home WDBVXC0060HWT",
        "GIA": 8590000,
        "HINHANH": "Ổ Cứng Desktop  Cloud/WD-MyCloud-2017-01-280x315.jpg",
        "MOTA": "Thông số kĩ thuật Nhà sản xuất Western Digital Model My Cloud Home Chuẩn giao tiếp Gigabit Lan 10/100/1000 Ethernet port Dung lượng 6TB Chuẩn giao tiếp USB mở rộng USB 3.0 Chia sẻ trực tuyến qua Internet Có Số ổ cứng Single Drive Phần mềm hỗ trợ trên thiết bị di động MyCloud (có sẵn trên Appstore, Google Play,…) Phần mềm hỗ trợ trên máy tính WD Discovery (Hỗ trợ trên Windows. Bạn có thể dowload tại ĐÂY) Bảo hành 24 tháng Ổ cứng mạng HDD Western Digital My Cloud Home Chia sẻ dữ liệu trên Cloud theo cách riêng của bạn Ổ cứng mạng HDD Western Digital My Cloud Home là thiết bị lưu trữ hoàn toàn mới thuộc dòng sản phẩm My Cloud Home của Western Digital. Bạn chỉ cần cắm trực tiếp vào bộ định tuyến Wi-Fi ở nhà là có thể dễ dàng lưu trữ, sắp xếp, kiểm soát, chia sẻ toàn bộ dữ liệu của bạn một cách tập trung ở bất kỳ nơi đâu, chỉ cần có Internet. MyCloud Home – Lưu trữ dữ liệu tập trung Ổ cứng mạng HDD Western Digital My Cloud Home giúp bạn có nhiều không gian lưu trữ để lưu giữ ảnh, video và dữ liệu của bạn từ điện thoại, máy tính bảng, máy tính cá nhân và thiết bị lưu trữ bên ngoài của bạn ở một nơi và bạn có thể truy cập bất kỳ lúc nào ở bất kỳ nơi đâu, chỉ cần có Internet. Truy cập dữ liệu từ di động – On The Go Bạn có thể sử dụng ứng dụng dành cho điện thoại di động “My Cloud“, ứng dụng dành cho máy tính để bàn “WD Discovery” hoặc truy cập trực tiếp trên trang chủ “MyCloud.com” để upload, truy cập và chia sẻ những hình ảnh và Video của bạn ở bất cứ nơi nào bạn có kết nối internet. Cực kỳ nhanh chóng và dễ dàng. Tự động sao lưu hình ảnh và Video trên điện thoại của bạn Cổng USB hỗ trợ USB giúp mở rộng bộ nhớ thêm cho ổ cứng Desktop Sync Tính năng Desktop Sync giúp bạn lưu giữ các thư mục yêu thích của bạn trên máy tính PC Windows và máy Mac đồng thời liên tục đồng bộ dữ liệu với thiết bị My Cloud Home, vừa giúp backup dữ liệu vừa cho phép bạn truy cập dữ liệu cực kỳ linh động. Streaming Video cực kỳ mượt Ổ cứng mạng HDD Western Digital My Cloud Home có thể Streaming các Video cá nhân của bạn ở mọi nơi, tính năng được hỗ trợ trên phần mềm “My Cloud” của thiết bị di dộng, “WD Discovery” trên máy tính hoặc trên trang chủ MyCloud.com. Tính năng nổi bật: Dễ dàng tìm kiếm nội dung: chức năng tìm kiếm được tích hợp giúp bạn tìm nhanh ảnh, video, phim và tài liệu trên My Cloud Home hoặc trên MyCloud.com. Khả năng phân quyền truy cập cho từng người dùng: bạn có thể cho phép rất nhiều người dùng sử dụng chung My Cloud Home, mỗi người sẽ có tài khoản cá nhân riêng. Dựa vào tài khoản riêng bạn có thể thiết lập không gian riêng tư cho từng người mà chỉ có họ mới có thể truy cập vào thư mục bạn đã chỉ định. Họ có thể quản lý, truy cập và chia sẻ nội dung của họ theo ý muốn. Rất an toàn. Đồng bộ dữ liệu từ các dịch vụ Cloud khác: My Cloud Home giúp bạn lưu trữ mọi thứ ở một nơi, bao gồm các dịch vụ lưu trữ Cloud khác như: Dropbox, Box, Google Drive ™, Facebook,… Tất cả sẽ được tự động tải về và lưu trữ tập trung tại một nơi. Tự động Backup máy tính cá nhân và máy MacOS: My Cloud Home có dung lượng rất lớn và được cắm trực tiếp vào mạng nội bộ trong nhà hoặc cơ quan làm việc của bạn. Nó không chỉ hỗ trợ lưu dữ liệu bình thường mà còn có chức năng lưu trữ Backup cả hệ thống máy tính cho bạn. Hoạt động cực kỳ mượt mà với phần mềm Windows Backup và Time Machine. Bảo vệ bằng mật khẩu: Giúp bảo vệ tất cả dữ liệu của bạn bằng mật khẩu để tránh bị truy cập trái phép, hỗ trợ cả Passcode và Touch ID trên Smartphone. Thương hiệu Western Digital",
        "NHASANXUAT": "Western Digital",
        "MODEL": "My Cloud Home",
        "CHUANGIAOTIEP": "USB mở rộng USB 3.0",
        "DUNGLUONG": "6TB",
        "BAOHANH": "24 tháng"
    },
    {
        "TEN": "Ổ cứng để bàn HDD 8TB Western Digital My Book WDBBGB0080HBK-SEN",
        "GIA": 9050000,
        "HINHANH": "Ổ Cứng Desktop  Cloud/WD-MyBook-2017-01-280x315.jpg",
        "MOTA": "Thông số kĩ thuật Nhà sản xuất Western Digital Model My Book Chuẩn giao tiếp USB 3.0 Dung lượng 8 TB Chia sẻ trực tuyến qua Internet Không Số ổ cứng Single Drive Phần mềm hỗ trợ trên máy tính WD Discovery (Hỗ trợ trên Windows. Bạn có thể dowload tại ĐÂY) Bảo hành 36 tháng Ổ cứng để bàn HDD Western Digital My Book – Tự động sao lưu dữ liệu Cuộc sống của chúng ta luôn bận rộn và tạo ra hàng tấn nội dung kĩ thuật số hàng ngày, và bạn luôn có một nỗi lo lắng đối với việc lưu trữ khối lượng dữ liệu lớn. Ổ cứng để bàn HDD Western Digital My Book có dung lượng lưu trữ cực lớn để bạn có thể tự tin sao lưu các dữ liệu của mình. Mở rộng không gian lưu trữ ảnh, video, nhạc và tài liệu của bạn. Complete Backup, Tương thích Time Machine Được trang bị phần mềm WD Backup cho Windows và Apple Time Machine tương thích cho Mac, ổ cứng để bàn HDD Western Digital My Book có thể sao lưu ảnh, video, nhạc và tài liệu của bạn. Ổ cứng máy tính để bàn My Book cũng hoạt động tốt với phần mềm Acronis True Image WD Edition để lên kế hoạch sao lưu toàn bộ hệ thống. Bảo vệ mật khẩu bằng Hardware Encryption Với mã hóa phần cứng AES 256-bit được tích hợp với phần mềm Bảo mật của WD, bạn có thể đặt mật khẩu cá nhân của riêng mình để giúp giữ cho dữ liệu của bạn an toàn và riêng tư. Dễ dàng sử dụng Ổ cứng để bàn HDD Western Digital My Book với chuẩn giao tiếp USB 3.0 chỉ cần cắm và sử dụng, luông sẵn sàng để bạn lưu lại những kỷ niệm và sao lưu tất cả dữ liệu. Phần mềm WD Backup và WD Security giúp bảo vệ dữ liệu của bạn. Ổ cứng để bàn HDD Western Digital My Book cũng tương thích hoàn toàn với Apple Time Machine. Thiết kế nhỏ gọn Với thiết kế nhỏ gọn và cực kỳ thời trang của ổ cứng để bàn HDD Western Digital My Book mang lại sự tinh tế và sang trọng cho khu vực làm việc. Với dung lượng lưu trữ tối đa 8TB, bạn có thể thoải mái lưu trữ thế giới kỹ thuật số của bạn. Dung lượng cực lớn Với dung lượng từ 3TB lên tới 8TB, sẽ có rất nhiều chỗ để bạn có thể lưu trữ số lượng lớn các ảnh, video và âm nhạc bạn yêu thích cộng với các tài liệu quan trọng của bạn. Western Digital – Chất lượng hàng đầu thế giới Hàng triệu người trên thế giới hiện đang tin tưởng và lưu trữ dữ liệu của họ vào ổ cứng để bàn HDD Western Digital My Book. Được thiết kế để đáp ứng các yêu cầu khắt khe của WD đối với độ bền, khả năng chịu sốc và độ tin cậy lâu dài, ổ cứng để bàn HDD Western Digital My Book cực kỳ đáng tin cậy với chế độ bảo hành lên đến 3 năm. Thương hiệu Western Digital",
        "NHASANXUAT": "Western Digital",
        "MODEL": "My Book",
        "CHUANGIAOTIEP": "USB 3.0",
        "DUNGLUONG": "8 TB",
        "BAOHANH": "36 tháng"
    },
    {
        "TEN": "Ổ cứng mạng HDD 8TB Western Digital My Cloud Home WDBVXC0080HWT",
        "GIA": 9980000,
        "HINHANH": "Ổ Cứng Desktop  Cloud/WD-MyCloud-2017-01-280x315.jpg",
        "MOTA": "Thông số kĩ thuật Nhà sản xuất Western Digital Model My Cloud Home Chuẩn giao tiếp Gigabit Lan 10/100/1000 Ethernet port Dung lượng 8TB Chuẩn giao tiếp USB mở rộng USB 3.0 Chia sẻ trực tuyến qua Internet Có Số ổ cứng Single Drive Phần mềm hỗ trợ trên thiết bị di động MyCloud (có sẵn trên Appstore, Google Play,…) Phần mềm hỗ trợ trên máy tính WD Discovery (Hỗ trợ trên Windows. Bạn có thể dowload tại ĐÂY) Bảo hành 24 tháng Ổ cứng mạng HDD Western Digital My Cloud Home Chia sẻ dữ liệu trên Cloud theo cách riêng của bạn Ổ cứng mạng HDD Western Digital My Cloud Home là thiết bị lưu trữ hoàn toàn mới thuộc dòng sản phẩm My Cloud Home của Western Digital. Bạn chỉ cần cắm trực tiếp vào bộ định tuyến Wi-Fi ở nhà là có thể dễ dàng lưu trữ, sắp xếp, kiểm soát, chia sẻ toàn bộ dữ liệu của bạn một cách tập trung ở bất kỳ nơi đâu, chỉ cần có Internet. MyCloud Home – Lưu trữ dữ liệu tập trung Ổ cứng mạng HDD Western Digital My Cloud Home giúp bạn có nhiều không gian lưu trữ để lưu giữ ảnh, video và dữ liệu của bạn từ điện thoại, máy tính bảng, máy tính cá nhân và thiết bị lưu trữ bên ngoài của bạn ở một nơi và bạn có thể truy cập bất kỳ lúc nào ở bất kỳ nơi đâu, chỉ cần có Internet. Truy cập dữ liệu từ di động – On The Go Bạn có thể sử dụng ứng dụng dành cho điện thoại di động “My Cloud“, ứng dụng dành cho máy tính để bàn “WD Discovery” hoặc truy cập trực tiếp trên trang chủ “MyCloud.com” để upload, truy cập và chia sẻ những hình ảnh và Video của bạn ở bất cứ nơi nào bạn có kết nối internet. Cực kỳ nhanh chóng và dễ dàng. Tự động sao lưu hình ảnh và Video trên điện thoại của bạn Cổng USB hỗ trợ USB giúp mở rộng bộ nhớ thêm cho ổ cứng Desktop Sync Tính năng Desktop Sync giúp bạn lưu giữ các thư mục yêu thích của bạn trên máy tính PC Windows và máy Mac đồng thời liên tục đồng bộ dữ liệu với thiết bị My Cloud Home, vừa giúp backup dữ liệu vừa cho phép bạn truy cập dữ liệu cực kỳ linh động. Streaming Video cực kỳ mượt Ổ cứng mạng HDD Western Digital My Cloud Home có thể Streaming các Video cá nhân của bạn ở mọi nơi, tính năng được hỗ trợ trên phần mềm “My Cloud” của thiết bị di dộng, “WD Discovery” trên máy tính hoặc trên trang chủ MyCloud.com. Tính năng nổi bật: Dễ dàng tìm kiếm nội dung: chức năng tìm kiếm được tích hợp giúp bạn tìm nhanh ảnh, video, phim và tài liệu trên My Cloud Home hoặc trên MyCloud.com. Khả năng phân quyền truy cập cho từng người dùng: bạn có thể cho phép rất nhiều người dùng sử dụng chung My Cloud Home, mỗi người sẽ có tài khoản cá nhân riêng. Dựa vào tài khoản riêng bạn có thể thiết lập không gian riêng tư cho từng người mà chỉ có họ mới có thể truy cập vào thư mục bạn đã chỉ định. Họ có thể quản lý, truy cập và chia sẻ nội dung của họ theo ý muốn. Rất an toàn. Đồng bộ dữ liệu từ các dịch vụ Cloud khác: My Cloud Home giúp bạn lưu trữ mọi thứ ở một nơi, bao gồm các dịch vụ lưu trữ Cloud khác như: Dropbox, Box, Google Drive ™, Facebook,… Tất cả sẽ được tự động tải về và lưu trữ tập trung tại một nơi. Tự động Backup máy tính cá nhân và máy MacOS: My Cloud Home có dung lượng rất lớn và được cắm trực tiếp vào mạng nội bộ trong nhà hoặc cơ quan làm việc của bạn. Nó không chỉ hỗ trợ lưu dữ liệu bình thường mà còn có chức năng lưu trữ Backup cả hệ thống máy tính cho bạn. Hoạt động cực kỳ mượt mà với phần mềm Windows Backup và Time Machine. Bảo vệ bằng mật khẩu: Giúp bảo vệ tất cả dữ liệu của bạn bằng mật khẩu để tránh bị truy cập trái phép, hỗ trợ cả Passcode và Touch ID trên Smartphone. Thương hiệu Western Digital",
        "NHASANXUAT": "Western Digital",
        "MODEL": "My Cloud Home",
        "CHUANGIAOTIEP": "USB mở rộng USB 3.0",
        "DUNGLUONG": "8TB",
        "BAOHANH": "24 tháng"
    }
]