[
    {
        "TEN": "HDD 2TB Seagate BarraCuda SATA III 6Gb/s 128MB Cache 2.5-Inch ST2000LM015",
        "GIA": 2450000,
        "HINHANH": "HDD/BarraCuda-2TB-01-280x315.jpg",
        "MOTA": "Thông số kĩ thuật Nhà sản xuất Seagate (USA) Model BarraCuda ST2000LM015 Chuẩn giao tiếp Sata III Kích thước 2.5 inch 7mm Dung lượng 2 TB Tốc độ ~ 120 MB/s Bộ nhớ Cache 128 MB Bảo hành 24 tháng Product of Thailand Ổ cứng HDD Seagate BarraCuda 2.5-Inch Linh hoạt – Tốc độ cao – Đáng tin cậy Dòng ổ cứng HDD BarraCuda của Seagate luôn dẫn đầu trong ngành công nghiệp lưu trữ cho máy tính để bàn và máy tính Laptop. Với dung lượng lên đến 5TB đối với chuẩn 2.5″, dòng sản phẩm BarraCuda là một lựa chọn tuyệt vời cho việc nâng cấp máy tính của bạn. BarraCuda kết hợp công nghệ lưu trữ hàng đầu với tốc độ quay 5,400 vòng / phút cho hiệu năng và thời gian tải nhanh khi chơi game hoặc thực hiện tải công việc nặng nề. Ổ cứng HDD Seagate BarraCuda 2.5-Inch cũng được hỗ trợ bảo hành 2 năm tại Seagate Việt Nam. Công nghệ Multi-Tier Caching Technology Tất cả các ổ đĩa cứng trong gia đình BarraCuda đều được trang bị Công nghệ Multi-Tier Caching Technology (MTC). MTC giúp tăng cường hiệu năng cho máy tính của bạn, vì vậy bạn có thể load ứng dụng và các tập tin nhanh hơn bao giờ hết. Bằng cách áp dụng các Intelligent Layers của NAND Flash, DRAM và công nghệ bộ nhớ Cache MLC, BarraCuda mang lại hiệu suất đọc và ghi được cải thiện bằng cách tối ưu hóa luồng dữ liệu. Nhiều dung lượng cho bạn lựa chọn Với dung lượng từ 500GB đến 5TB, dòng ổ cứng HDD BarraCuda luôn dẫn đầu thị trường với nhiều lựa chọn lưu trữ rộng nhất có sẵn để phù hợp với từng nhu cầu của bạn. thiết kế kích thước 2,5-inch giúp người dùng có thể nâng cấp máy tính xách tay Laptop, Desktop hoặc làm ổ cứng di động lưu trữ bên ngoài. Được tin dùng khắp thế giới Dòng ổ cứng đáng tin cậy của BarraCuda của Seagate đã được tin dùng khắp thế giới trong hơn 20 năm qua và được công nhận chất lượng bởi khách hàng toàn cầu. Thương hiệu Seagate Dạng ổ cứng 2.5 Inches Dung lượng ổ cứng 2TB – 4TB Chuẩn giao tiếp SATA III 6Gb/s",
        "NHASANXUAT": "Seagate (USA)",
        "MODEL": "BarraCuda ST2000LM015",
        "CHUANGIAOTIEP": "Sata III",
        "DUNGLUONG": "2 TB",
        "BAOHANH": "24 tháng"
    }
]