[{"TEN":"USB 2.0 Adata C906 8GB","GIA":102000,"HINHANH":"USB/Adata-906-08-01-280x315.jpg","MOTA":"Thông số kĩ thuật Nhà sản xuất ADATA Model C906 Chuẩn giao tiếp USB 2.0 Dung lượng 8GB Tốc độ đọc ~ 20 MB/s Tốc độ ghi ~ 10 MB/s Bảo hành 24 tháng USB ADATA Classic Series C906 Thiết kế cổ điển, dung lượng cực cao USB ADATA Classic Series C906 được thiết kế theo phong cách cổ điển làm cho nó không chỉ là một thiết bị lưu trữ mà còn là một phụ kiện thời trang nói lên cá tính của bạn. Với trọng lượng chỉ 9 gram và độ dài chỉ khoảng 5,8 cm, USB ADATA Classic Series C906 là một thiết bị lưu trữ USB cực kỳ nhỏ gọn, mang đến tính di động cho tất cả các dữ liệu của bạn. Được thiết kế với các góc cạnh được bo tròn và một bề mặt bóng mang lại cái nhìn bắt mắt, USB ADATA Classic Series C906 cũng được thiết kế nắp đậy chống bụi và đầu giữ nắp phía sau của thiết bị để ngăn ngừa mất nắp. Dung lượng cực khủng Với dung lượng từ 4GB đến 32GB, USB ADATA Classic Series C906 được thiết kế để phù hợp với từng nhu cầu của khách hàng. Khả năng lưu trữ âm nhạc, hình ảnh, Multimedia của bạn và các tập tin cá nhân cùng với khả năng di chuyển dữ liệu tốc độ cao USB 2.0 làm cho USB ADATA Classic Series C906 trở thành một sự lựa chọn hoàn hảo của bạn. Thương hiệu Adata Cổng kết nối USB 2.0","NHASANXUAT":"ADATA","MODEL":"C906","CHUANGIAOTIEP":"USB 2.0","DUNGLUONG":"8GB","BAOHANH":"24 tháng"},{"TEN":"USB 3.0 Kingston DataTraverler 100 G3 16GB 100MB/s","GIA":115000,"HINHANH":"USB/DT-100-G3-16-01-280x315.jpg","MOTA":"Thông số kĩ thuật Nhà sản xuất Kingston (USA) Model DT 100 G3 Chuẩn giao tiếp USB 3.0 (Tương thích ngược 2.0) Dung lượng 16 GB Tốc độ đọc 100 MB/s Tốc độ ghi 10 MB/s Bảo hành 60 tháng Là công nghệ giao tiếp phổ biến nhất thế giới hiện nay, USB xuất hiện trong hầu hết các thiết bị, từ máy tính bảng cho tới máy in và smartphone. So với USB 2.0 tiêu chuẩn hiện nay, chuẩn USB 3.0 nâng khả năng truyền tải dữ liệu lên cao gấp 10 lần. Kingston DataTraverler 100 G3 là thiết bị tận dụng các cổng USB 3.0 ở các máy tính xách tay và máy tính để bàn mới; cho phép bạn nhanh chóng chuyển đổi tất cả dữ liệu của mình, từ văn bản, các bài báo cáo đến các file nhạc, hình ảnh… Sản phẩm còn nổi bật bởi thiết kế đơn giản, gam màu sang trọng cùng khả năng tương thích ngược với các hệ thống USB 2.0, mang đến nhiều tiện ích cho người dùng. Sản phẩm được bảo hành 60 tháng. TÍNH NĂNG NỔI BẬT Thiết bị lưu trữ đạt chuẩn USB 3.0 hiện đại, hiệu quả Là dòng sản phẩm USB 3.0, Kingston DataTraverler 100G3 cho tốc độ truyền tải nhanh chóng, ấn tượng; sử dụng cơ chế ngắt (interrupt) thay vì truy vấn lần lượt (polling) khi một thiết bị được cắm vào (giúp hạn chế lãng phí thời gian hay năng lượng trên một thiết bị nhàn rỗi, từ đó tiết kiệm pin hơn); điện áp cung cấp qua cổng USB 3.0, khi thiết bị cần hoạt động, không những đủ cho các thanh nhớ flash USB mà còn đủ cho các ổ đĩa gắn ngoài… Tương thích ngược với các thiết bị hỗ trợ USB 2.0 USB 3.0 Kingston DataTraverler 100G3 hỗ trợ khả năng tương thích ngược với các chuẩn trước đó, như 2.0, đạt tốc độ vượt trội so với những USB chuẩn 2.0 truyền thống. Dung lượng lưu trữ thoải mái Dòng sản phẩm Kingston DateTraverler 100G3 có dung lượng lưu trữ lên đến 64GB, thỏa mãn mọi như cầu học tập và làm việc của bạn. Hỗ trợ nhiều hệ điều hành thông dụng USB 3.0 Kingston DataTraverler 100G3 64GB sử dụng được cho nhiều hệ điều hành (cả chuẩn 3.0 lẫn 2.0): Linux, Mac OS X, Windows 7, Windows 8, Windows Vista, Windows XP. Thương hiệu Kingston Cổng kết nối USB 3.0","NHASANXUAT":"Kingston (USA)","MODEL":"DT 100 G3","CHUANGIAOTIEP":"USB 3.0 (Tương thích ngược 2.0)","DUNGLUONG":"16 GB","BAOHANH":"60 tháng"},{"TEN":"USB 2.0 PNY Monkey Tail Attache 16GB","GIA":115000,"HINHANH":"USB/Monkey-Tail-Attache-16-02-280x315.jpg","MOTA":"Thông số kĩ thuật Nhà sản xuất PNY (USA) Model PFMKY016 Chuẩn giao tiếp USB 2.0 Dung lượng 16 GB Tốc độ đọc 32 MB/s Tốc độ ghi 8 MB/s Chất liệu Nhựa dẻo Kích thước 61.47 x 28.35 x 7.16 mm Bảo hành 24 tháng USB 2.0 PNY Monkey Tail Attache Phiên bản hạn chế Được thiết kế và sản xuất bằng vật liệu nhựa dẻo, giúp sản phẩm USB 2.0 PNY Monkey Tail Attache linh hoạt, vui nhộn và cực kỳ bền bỉ khi bạn có thể kéo dài chiếc đuôi khỉ ra và nó dễ dàng trở lại hình dạng ban đầu, bạn có thể thoải mái móc sản phẩm vào balo, chìa khóa hay bất cứ chỗ nào có thể móc được. USB 2.0 PNY Monkey Tail Attache chống nước, chống sock, chống trầy xước và tương thích với bất kỳ thiết bị nào có hỗ trợ cổng USB Type-A. Thương hiệu PNY Cổng kết nối USB 2.0","NHASANXUAT":"PNY (USA)","MODEL":"PFMKY016","CHUANGIAOTIEP":"USB 2.0","DUNGLUONG":"16 GB","BAOHANH":"24 tháng"},{"TEN":"USB 3.0 SanDisk Ultra Flair CZ73 16GB","GIA":160000,"HINHANH":"USB/Sandisk-Ultra-Flair-CZ73-10-280x315.jpg","MOTA":"Thông số kĩ thuật Nhà sản xuất Sandisk Model CZ73 Chuẩn giao tiếp USB 3.0 ; 2.0 Dung lượng 16 GB Tốc độ đọc ~130 MB/s Tốc độ ghi ~15 MB/s Bảo hành 60 tháng USB SanDisk Ultra Flair CZ73 USB 3.0 Flash Drive Với tốc độ chuyển dữ liệu nhanh gấp 15 lần so với chuẩn USB 2.0, USB SanDisk Ultra Flair USB 3.0 Flash Drive được thiết kế để di chuyển các tập tin của bạn thật nhanh chóng, vì vậy nó sẽ tiết kiệm cho bạn rất nhiều thời gian. Vỏ bọc được làm bằng kim loại bền và rất phong cách giúp giữ các tập tin quan trọng của bạn an toàn. Bên cạnh đó phần mềm SanDisk SecureAccess đi kèm cho phép bạn dễ dàng thêm các mật khẩu được mã hóa cho các tập tin quan trọng. Chuẩn giao tiếp High-Speed USB 3.0 – Cho tốc độ lên đến 150MB/s Với công nghệ tốc độ cao USB 3.0, SanDisk Ultra Flair USB 3.0 Flash Drive mang đến tốc độ lên đến 150MB/s, cho phép bạn chuyển một bộ phim độ dài đầy đủ chỉ ít hơn 30 giây. Di chuyển và sao lưu tất cả các tập tin bạn cần trên USB mà không cần lo lắng về việc đầy bộ nhớ với dung lượng lên đến 32GB. Tất cả các sản phẩm của SanDisk sản xuất với tiêu chuẩn cao nhất và được thử nghiệm chặt chẽ trước khi xuất xưởng. Bạn có thể tự tin vào chất lượng, hiệu suất vượt trội và độ tin cậy của tất cả các sản phẩm SanDisk. Tốc độ đọc ghi cực nhanh Với tốc độ lên tới 150MB/s, USB SanDisk Ultra Flair CZ73 USB 3.0 Flash Drive nhanh gấp 15 lần so với các ổ USB 2.0 thông thường. Bạn có thể di chuyển một bộ phim có độ dài đầy đủ trong chưa đến 30 giây. Tiết kiệm tối đa thời gian cho bạn. Vỏ kim loại – cực đẹp và chắc chắn USB SanDisk Ultra Flair CZ73 USB 3.0 Flash Drive có vỏ bọc bằng kim loại cực bền giúp bảo vệ thiết bị khỏi những ngoại lực tác động bên ngoài. Thiết kế nhỏ gọn giúp bạn dễ dàng bỏ vào túi, ví và mang theo các dữ liệu của bạn đế bất cứ đâu. Phần mềm bảo mật SanDisk SecureAccess đi kèm Phần mềm bảo mật SanDisk SecureAccess đi kèm sẽ giúp bạn tạo một thư mục riêng trên ổ đĩa của bạn và mã hóa nó bằng thuật toán AES 128-bit kèm theo mật khẩu bảo vệ giúp bạn dễ dàng bảo vệ các tệp quan trọng. Chỉ cần chép dữ liệu quan trọng vào thư mục đã được chỉ định, dữ liệu của bạn sẽ được bảo vệ an toàn. Phục hồi dữ liệu dễ dàng với phần mềm RescuePRO Deluxe Phần mềm phục hồi dữ liệu RescuePRO Deluxe đi kèm sẽ giúp bạn dễ dàng khôi phục các tệp đã bị xóa chỉ với một cú Click chuột. Bạn có thể tải phần mềm tại ĐÂY Tương thích chuẩn giao tiếp USB 3.0 và 2.0 USB SanDisk Ultra Flair CZ73 USB 3.0 Flash Drive tương thích ngược với chuẩn giao tiếp USB 2.0 đời trước, vì vậy bạn có thể cắm nó vào bất kỳ cổng USB 2.0 hoặc 3.0 trên bất cứ máy tính nào. Thoải mái lưu trữ dữ liệu Biểu đồ ở bên cạnh sẽ cho bạn biết số lượng ảnh, video, nhạc và các tệp dữ liệu bạn có thể lưu trữ trong USB SanDisk Ultra Flair CZ73 USB 3.0 Flash Drive. Thương hiệu Sandisk Cổng kết nối USB 3.0","NHASANXUAT":"Sandisk","MODEL":"CZ73","CHUANGIAOTIEP":"USB 3.0 ; 2.0","DUNGLUONG":"16 GB","BAOHANH":"60 tháng"},{"TEN":"USB 3.0 SanDisk Ultra Fit CZ43 16GB","GIA":170000,"HINHANH":"USB/Sandisk-CZ43-16-01-280x315.jpg","MOTA":"Thông số kĩ thuật Nhà sản xuất Sandisk (USA) Model SDCZ43 Chuẩn giao tiếp USB 3.0 ; 2.0 Dung lượng 16 GB Tốc độ đọc ~ 135 MB/s Tốc độ ghi ~ 15 MB/s Bảo hành 60 tháng Di chuyển, lưu trữ và chia sẻ tập tin nhanh hơn mười lần với USB 3.0 Sandisk Ultra Fit CZ43 Với tốc độ đọc lên đến 130 MB/s và tốc độ ghi nhanh hơn gấp 10 lần so với chuẩn USB 2.0, USB SanDisk Ultra Fit USB 3.0 CZ43 Flash Drive cho phép bạn di chuyển, lưu trữ và chia sẻ thông tin yêu thích của bạn một cách nhanh chóng. Với dung lượng lên đến 128GB, mở rộng tối đa không gian lưu trữ cho thiết bị của bạn một cách nhanh chóng hoặc di chuyển các tập tin giữa các máy tính xách tay, máy tính bảng, máy chơi game, TV, hệ thống âm thanh xe hơi, hoặc thiết bị USB khác. Bạn thậm chí có thể chuyển một bộ phim độ dài đầy đủ chỉ trong 40 giây. Ngoài ra, USB SanDisk Ultra Fit USB 3.0 CZ43 Flash Drive tương thích ngượcvới cổng USB 2.0. Nhỏ gọn, thiết kế Stay-Put và dung lượng lưu trữ cực khủng USB SanDisk Ultra Fit USB 3.0 CZ43 Flash Drive được thiết kế cực nhỏ, vừa khít vào cổng USB của thiết bị và được thiết kế để có thể cắm liên tục mà không cần phải tháo ra, vì vậy bạn không phải lo lắng về việc bị rơi hoặc bị nứt vỡ. Và với dung lượng lên đến 128GB, bạn sẽ có rất nhiều không gian cho tất cả các hình ảnh, video, âm nhạc, và các trò chơi. Mật khẩu bảo vệ tập tin cá nhân của bạn Với phần mềm SanDisk SecureAccess, bạn có thể bảo vệ tập tin cá nhân của bạn trong một thư mục được bảo vệ bằng mật khẩu trong khi vẫn giữ các tập tin khác sẵn bình thường để chia sẻ. Với mã hóa 128-bit, bảo vệ tuyệt đối các tập tin nhạy cảm của bạn, ngay cả khi bạn chia sẻ nó với bạn bè. Phục hồi dữ liệu bị hỏng hoặc bị xóa với RescuePRO USB SanDisk Ultra Fit USB 3.0 CZ43 Flash Drive đi kèm với phần mềm RescuePRO Deluxe bản quyền một năm để phục hồi dữ liệu. Với phần mềm RescuePRO Deluxe, bạn rất dễ dàng để khôi phục lại hình ảnh hoặc video bị xóa hoặc bị mất và lưu chúng vào máy tính của bạn, thậm chí nếu các tập tin đã bị xóa vài tháng trước đây. Thương hiệu Sandisk Cổng kết nối USB 3.0","NHASANXUAT":"Sandisk (USA)","MODEL":"SDCZ43","CHUANGIAOTIEP":"USB 3.0 ; 2.0","DUNGLUONG":"16 GB","BAOHANH":"60 tháng"},{"TEN":"USB 3.0 SanDisk Ultra SDCZ48 16GB 100MB/s","GIA":175000,"HINHANH":"USB/Sandisk-CZ48-01-280x315.jpg","MOTA":"Thông số kĩ thuật Nhà sản xuất Sandisk (USA) Model SDCZ48 Chuẩn giao tiếp USB 3.0 ; 2.0 Dung lượng 16 GB Tốc độ đọc 100 MB/s Tốc độ ghi 20 MB/s Bảo hành 60 tháng Di chuyển Movie Full-length chưa đến 40 giây USB SanDisk Ultra USB 3.0 Flash Drive đươc trang bị tốc độ chuyển dữ liệu nhanh hơn và khả năng lưu trữ rất cao trong thiết kế rất nhỏ gọn. Tiết kiệm thời gian với tốc độ di chuyển các dữ liệu nhanh hơn gấp 10 lần so với chuẩn USB 2.0. Khả năng lưu trữ lên đến 256GB, USB SanDisk Ultra USB 3.0 Flash Drive đáp ứng mọi nhu cầu lưu trữ của bạn. Khả năng lưu trữ cực lớn Với dung lượng lên đến 256 GB, bạn có thể lưu trữ rất nhiều nội dung dữ liệu vào USB SanDisk Ultra USB 3.0 Flash Drive và mang đến bất kì nơi đâu. Hãy tận hưởng tốc độ cực cao của USB 3.0 USB SanDisk Ultra USB 3.0 Flash Drive có khả năng truyền tải file lên đến 100 MB/s, vì vậy bạn có thể di chuyển một bộ phim với độ dài đầy đủ chỉ chưa đầy 40 giây. Giữ các tập tin của bạn an toàn với SanDisk SecureAccess Software Tập tin của bạn có thể được bảo vệ rất an toàn ngay cả khi bạn chia sẻ USB với những người khác. Phần mềm SanDisk SecureAccess (đi kèm) cho phép bạn thiết lập mật khẩu một thư mục trên ổ đĩa của bạn và bảo vệ các tập tin của bạn với mã hóa 128-bit AES. Dung lượng cực khủng Với dung lượng lên đến 256GB, USB SanDisk Ultra USB 3.0 Flash Drive máng đến cho bạn rất nhiều không gian để giữ tất cả các tập tin yêu thích của bạn, từ các bức ảnh có độ phân giải cao, MP3 và phim, đến các bài thuyết trình, các tập tin đồ họa và tài liệu quan trọng khác. Tiết kiệm thời gian tối đa USB SanDisk Ultra USB 3.0 Flash Drive truyền tải và lưu trữ tập tin lớn lên nhanh hơn so với chuẩn USB 2.0 ổ đĩa gấp mười lần. Thương hiệu Sandisk Cổng kết nối USB 3.0","NHASANXUAT":"Sandisk (USA)","MODEL":"SDCZ48","CHUANGIAOTIEP":"USB 3.0 ; 2.0","DUNGLUONG":"16 GB","BAOHANH":"60 tháng"},{"TEN":"USB 3.0 Kingston DataTraverler 100 G3 32GB 100MB/s","GIA":230000,"HINHANH":"USB/DT-100-G3-32-01-280x315.jpg","MOTA":"Thông số kĩ thuật Nhà sản xuất Kingston (USA) Model DT 100 G3 Chuẩn giao tiếp USB 3.0 (Tương thích ngược 2.0) Dung lượng 32 GB Tốc độ đọc 100 MB/s Tốc độ ghi 10 MB/s Bảo hành 60 tháng Là công nghệ giao tiếp phổ biến nhất thế giới hiện nay, USB xuất hiện trong hầu hết các thiết bị, từ máy tính bảng cho tới máy in và smartphone. So với USB 2.0 tiêu chuẩn hiện nay, chuẩn USB 3.0 nâng khả năng truyền tải dữ liệu lên cao gấp 10 lần. Kingston DataTraverler 100 G3 là thiết bị tận dụng các cổng USB 3.0 ở các máy tính xách tay và máy tính để bàn mới; cho phép bạn nhanh chóng chuyển đổi tất cả dữ liệu của mình, từ văn bản, các bài báo cáo đến các file nhạc, hình ảnh… Sản phẩm còn nổi bật bởi thiết kế đơn giản, gam màu sang trọng cùng khả năng tương thích ngược với các hệ thống USB 2.0, mang đến nhiều tiện ích cho người dùng. Sản phẩm được bảo hành 60 tháng. TÍNH NĂNG NỔI BẬT Thiết bị lưu trữ đạt chuẩn USB 3.0 hiện đại, hiệu quả Là dòng sản phẩm USB 3.0, Kingston DataTraverler 100G3 cho tốc độ truyền tải nhanh chóng, ấn tượng; sử dụng cơ chế ngắt (interrupt) thay vì truy vấn lần lượt (polling) khi một thiết bị được cắm vào (giúp hạn chế lãng phí thời gian hay năng lượng trên một thiết bị nhàn rỗi, từ đó tiết kiệm pin hơn); điện áp cung cấp qua cổng USB 3.0, khi thiết bị cần hoạt động, không những đủ cho các thanh nhớ flash USB mà còn đủ cho các ổ đĩa gắn ngoài… Tương thích ngược với các thiết bị hỗ trợ USB 2.0 USB 3.0 Kingston DataTraverler 100G3 hỗ trợ khả năng tương thích ngược với các chuẩn trước đó, như 2.0, đạt tốc độ vượt trội so với những USB chuẩn 2.0 truyền thống. Dung lượng lưu trữ thoải mái Dòng sản phẩm Kingston DateTraverler 100G3 có dung lượng lưu trữ lên đến 64GB, thỏa mãn mọi như cầu học tập và làm việc của bạn. Hỗ trợ nhiều hệ điều hành thông dụng USB 3.0 Kingston DataTraverler 100G3 64GB sử dụng được cho nhiều hệ điều hành (cả chuẩn 3.0 lẫn 2.0): Linux, Mac OS X, Windows 7, Windows 8, Windows Vista, Windows XP. Thương hiệu Kingston Cổng kết nối USB 3.0","NHASANXUAT":"Kingston (USA)","MODEL":"DT 100 G3","CHUANGIAOTIEP":"USB 3.0 (Tương thích ngược 2.0)","DUNGLUONG":"32 GB","BAOHANH":"60 tháng"},{"TEN":"USB OTG 3.0 Kingston MicroDuo 3.0 16GB","GIA":240000,"HINHANH":"USB/USB-OTG-Kingston-MicroDuo-16GB-280x315.jpg","MOTA":"Thông số kĩ thuật Nhà sản xuất Kingston (USA) Model DT MicroDuo Chuẩn giao tiếp – USB 3.0 – MicroUSSB Dung lượng 16 GB Tương thích Các thiết bị Android dùng cổng MicroUSB Bảo hành 60 tháng USB Kingston microDuo 3.0 USB OTG Kingston microDuo 3.0 cung cấp thêm dung lượng lưu trữ trong một thiết bị nhỏ gọn và tiện lợi cho máy tính bảng và điện thoại thông minh hỗ trợ tính năng USB OTG (On-The-Go). Chuẩn USB OTG cho phép các thiết bị di động kết nối trực tiếp với các thiết bị USB được hỗ trợ. USB Kingston DataTraveler microDuo cho phép sử dụng cổng microUSB, thường được dùng để sạc các thiết bị, làm cổng mở rộng để bổ sung dung lượng lưu trữ. Lý tưởng để lưu trữ các tập tin lớn trong khi di chuyển, USB Kingston microDuo tự động nhận và không cần cài driver. Bổ sung dung lượng lưu trữ cho điện thoại thông minh và máy tính bảng USB OTG của Kingston cung cấp thêm dung lượng lưu trữ cho các thiết bị di động Android OTG. Người dung có thể sao lưu tập tin, ảnh, video và hơn thế nữa, cũng như chia sẻ với các thiết bị di động khác hoặc thậm chí là máy tính một cách dễ dàng hơn so với việc sử dụng các dịch vụ đám mây trực tuyến. Hoạt động như USB thông thường Sử dụng USB Kingston DataTraveler microDuo một cách bình thường như USB. Đây là cách thuận tiện để chia sẻ các tập tin lớn giữa các thiết bị di động mà không cần sử dụng đến các dịch vụ đám mây trực tuyến hoặc bất kì hết nối nào khác. Thiết kế siêu nhỏ gọn DataTravelermicroDuo có thiết kế nhỏ và nhẹ, vì thế sản phẩm rất dễ dàng mang đi bất cứ đâu và không chiếm chỗ của các ổ hoặc thiết bị khác mà nó được cắm vào. Nắp xoay giúp bảo vệ đầu kết nối microUSB khỏi hư hại. Chuẩn giao tiếp USB 3.0 Chuẩn giao tiếp USB 3.0 với tốc độ đọc lên đến 70MB/s, tốc độ ghi 15MB/s giúp tăng tốc quá trình truyền dữ liệu. Bạn sẽ không phải mất quá nhiều thời gian khi sao chép nhạc, video clip và hình ảnh. – Tương thích với nhiều loại điện thoại thông minh và máy tính bảng – Tương thích với điện thoại và máy tính bảng dùng Androi 4.0 +. – Xem thêm danh sách thiết bị tương thích tại đây. Thương hiệu Kingston Cổng kết nối USB 3.0, Micro-USB","NHASANXUAT":"Kingston (USA)","MODEL":"DT MicroDuo","CHUANGIAOTIEP":"– USB 3.0 – MicroUSSB","DUNGLUONG":"16 GB","BAOHANH":"60 tháng"},{"TEN":"USB 3.0 SanDisk Ultra Flair CZ73 32GB 150MB/s","GIA":250000,"HINHANH":"USB/Sandisk-Ultra-Flair-CZ73-10-280x315.jpg","MOTA":"Thông số kĩ thuật Nhà sản xuất Sandisk Model CZ73 Chuẩn giao tiếp USB 3.0 ; 2.0 Dung lượng 32 GB Tốc độ đọc ~150 MB/s Tốc độ ghi ~25 MB/s Bảo hành 60 tháng USB SanDisk Ultra Flair CZ73 USB 3.0 Flash Drive Với tốc độ chuyển dữ liệu nhanh gấp 15 lần so với chuẩn USB 2.0, USB SanDisk Ultra Flair USB 3.0 Flash Drive được thiết kế để di chuyển các tập tin của bạn thật nhanh chóng, vì vậy nó sẽ tiết kiệm cho bạn rất nhiều thời gian. Vỏ bọc được làm bằng kim loại bền và rất phong cách giúp giữ các tập tin quan trọng của bạn an toàn. Bên cạnh đó phần mềm SanDisk SecureAccess đi kèm cho phép bạn dễ dàng thêm các mật khẩu được mã hóa cho các tập tin quan trọng. Chuẩn giao tiếp High-Speed USB 3.0 – Cho tốc độ lên đến 150MB/s Với công nghệ tốc độ cao USB 3.0, SanDisk Ultra Flair USB 3.0 Flash Drive mang đến tốc độ lên đến 150MB/s, cho phép bạn chuyển một bộ phim độ dài đầy đủ chỉ ít hơn 30 giây. Di chuyển và sao lưu tất cả các tập tin bạn cần trên USB mà không cần lo lắng về việc đầy bộ nhớ với dung lượng lên đến 32GB. Tất cả các sản phẩm của SanDisk sản xuất với tiêu chuẩn cao nhất và được thử nghiệm chặt chẽ trước khi xuất xưởng. Bạn có thể tự tin vào chất lượng, hiệu suất vượt trội và độ tin cậy của tất cả các sản phẩm SanDisk. Tốc độ đọc ghi cực nhanh Với tốc độ lên tới 150MB/s, USB SanDisk Ultra Flair CZ73 USB 3.0 Flash Drive nhanh gấp 15 lần so với các ổ USB 2.0 thông thường. Bạn có thể di chuyển một bộ phim có độ dài đầy đủ trong chưa đến 30 giây. Tiết kiệm tối đa thời gian cho bạn. Vỏ kim loại – cực đẹp và chắc chắn USB SanDisk Ultra Flair CZ73 USB 3.0 Flash Drive có vỏ bọc bằng kim loại cực bền giúp bảo vệ thiết bị khỏi những ngoại lực tác động bên ngoài. Thiết kế nhỏ gọn giúp bạn dễ dàng bỏ vào túi, ví và mang theo các dữ liệu của bạn đế bất cứ đâu. Phần mềm bảo mật SanDisk SecureAccess đi kèm Phần mềm bảo mật SanDisk SecureAccess đi kèm sẽ giúp bạn tạo một thư mục riêng trên ổ đĩa của bạn và mã hóa nó bằng thuật toán AES 128-bit kèm theo mật khẩu bảo vệ giúp bạn dễ dàng bảo vệ các tệp quan trọng. Chỉ cần chép dữ liệu quan trọng vào thư mục đã được chỉ định, dữ liệu của bạn sẽ được bảo vệ an toàn. Phục hồi dữ liệu dễ dàng với phần mềm RescuePRO Deluxe Phần mềm phục hồi dữ liệu RescuePRO Deluxe đi kèm sẽ giúp bạn dễ dàng khôi phục các tệp đã bị xóa chỉ với một cú Click chuột. Bạn có thể tải phần mềm tại ĐÂY Tương thích chuẩn giao tiếp USB 3.0 và 2.0 USB SanDisk Ultra Flair CZ73 USB 3.0 Flash Drive tương thích ngược với chuẩn giao tiếp USB 2.0 đời trước, vì vậy bạn có thể cắm nó vào bất kỳ cổng USB 2.0 hoặc 3.0 trên bất cứ máy tính nào. Thoải mái lưu trữ dữ liệu Biểu đồ ở bên cạnh sẽ cho bạn biết số lượng ảnh, video, nhạc và các tệp dữ liệu bạn có thể lưu trữ trong USB SanDisk Ultra Flair CZ73 USB 3.0 Flash Drive. Thương hiệu Lexar Cổng kết nối USB 3.0","NHASANXUAT":"Sandisk","MODEL":"CZ73","CHUANGIAOTIEP":"USB 3.0 ; 2.0","DUNGLUONG":"32 GB","BAOHANH":"60 tháng"},{"TEN":"USB 3.0 SanDisk Ultra Fit CZ43 32GB","GIA":260000,"HINHANH":"USB/Sandisk-CZ43-32-01-280x315.jpg","MOTA":"Thông số kĩ thuật Nhà sản xuất Sandisk (USA) Model SDCZ43 Chuẩn giao tiếp USB 3.0 ; 2.0 Dung lượng 32 GB Tốc độ đọc ~ 135 MB/s Tốc độ ghi ~ 15 MB/s Bảo hành 60 tháng Di chuyển, lưu trữ và chia sẻ tập tin nhanh hơn mười lần với USB 3.0 Sandisk Ultra Fit CZ43 Với tốc độ đọc lên đến 130 MB/s và tốc độ ghi nhanh hơn gấp 10 lần so với chuẩn USB 2.0, USB SanDisk Ultra Fit USB 3.0 CZ43 Flash Drive cho phép bạn di chuyển, lưu trữ và chia sẻ thông tin yêu thích của bạn một cách nhanh chóng. Với dung lượng lên đến 128GB, mở rộng tối đa không gian lưu trữ cho thiết bị của bạn một cách nhanh chóng hoặc di chuyển các tập tin giữa các máy tính xách tay, máy tính bảng, máy chơi game, TV, hệ thống âm thanh xe hơi, hoặc thiết bị USB khác. Bạn thậm chí có thể chuyển một bộ phim độ dài đầy đủ chỉ trong 40 giây. Ngoài ra, USB SanDisk Ultra Fit USB 3.0 CZ43 Flash Drive tương thích ngượcvới cổng USB 2.0. Nhỏ gọn, thiết kế Stay-Put và dung lượng lưu trữ cực khủng USB SanDisk Ultra Fit USB 3.0 CZ43 Flash Drive được thiết kế cực nhỏ, vừa khít vào cổng USB của thiết bị và được thiết kế để có thể cắm liên tục mà không cần phải tháo ra, vì vậy bạn không phải lo lắng về việc bị rơi hoặc bị nứt vỡ. Và với dung lượng lên đến 128GB, bạn sẽ có rất nhiều không gian cho tất cả các hình ảnh, video, âm nhạc, và các trò chơi. Mật khẩu bảo vệ tập tin cá nhân của bạn Với phần mềm SanDisk SecureAccess, bạn có thể bảo vệ tập tin cá nhân của bạn trong một thư mục được bảo vệ bằng mật khẩu trong khi vẫn giữ các tập tin khác sẵn bình thường để chia sẻ. Với mã hóa 128-bit, bảo vệ tuyệt đối các tập tin nhạy cảm của bạn, ngay cả khi bạn chia sẻ nó với bạn bè. Phục hồi dữ liệu bị hỏng hoặc bị xóa với RescuePRO USB SanDisk Ultra Fit USB 3.0 CZ43 Flash Drive đi kèm với phần mềm RescuePRO Deluxe bản quyền một năm để phục hồi dữ liệu. Với phần mềm RescuePRO Deluxe, bạn rất dễ dàng để khôi phục lại hình ảnh hoặc video bị xóa hoặc bị mất và lưu chúng vào máy tính của bạn, thậm chí nếu các tập tin đã bị xóa vài tháng trước đây. Thương hiệu Sandisk Cổng kết nối USB 3.0","NHASANXUAT":"Sandisk (USA)","MODEL":"SDCZ43","CHUANGIAOTIEP":"USB 3.0 ; 2.0","DUNGLUONG":"32 GB","BAOHANH":"60 tháng"},{"TEN":"USB 3.1 Kingston DataTraveler DT50 32GB","GIA":260000,"HINHANH":"USB/DT50-32-01-280x315.jpg","MOTA":"Thông số kĩ thuật Nhà sản xuất Kingston (USA) Model DT50/32GBFR Chuẩn giao tiếp USB 3.1 / 3.0 / 2.0 Dung lượng 32 GB Tốc độ đọc ~110 MB/s Tốc độ ghi ~15 MB/s Bảo hành 60 tháng USB 3.1 Kingston DataTraveler DT50 USB 3.1 Kingston DataTraveler DT50 là một USB có trọng lượng rất nhẹ và có nhiều dung lượng từ 8GB đến 128GB. Kích thước nhỏ gọn, thiết kế không có nắp và vỏ bọc bằng kim loại giúp bạn không phải lo về vấn đề mất nắp. Chuẩn giao tiếp tốc độ siêu cao USB 3.1 Gen 1 (USB 3.0) giúp bạn di chuyển dữ liệu cực nhanh và tiết kiệm thời gian. tương thích với các cổng USB 2.0 hiện có.USB 3.1 Kingston DataTraveler DT50 được hỗ trợ bởi một bảo hành năm năm, hỗ trợ kỹ thuật miễn phí và nổi tiếng của Kingston. Kích thước nhỏ gọn USB 3.1 Kingston DataTraveler DT50 được thiết kế nhỏ gọn giúp bạn dễ mang theo bên mình. Vỏ kim loại USB 3.1 Kingston DataTraveler DT50 có vỏ được làm bằng kim loại nguyên khối giúp chống va đập, chống sốc, bảo vệ mọi thứ bên trong thân USB. Và thiết kế không nắp giúp hạn chế vấn đề mất nắp khi sử dụng. Chuẩn giao tiếp USB 3.1 Gen 1 (USB 3.0) tốc độ cao USB 3.1 Kingston DataTraveler DT50 với chuẩn giao tiếp USB 3.1 Gen 1 mới nhất cho tốc độ truyền tải cực cao. Nhiều dung lượng cho bạn lựa chọn Với dung lượng từ 16GB đến 128GB cho bạn rất nhiều sự lựa chọn phù hợp nhu cầu của bạn. Cổng kết nối USB 3.1 Thương hiệu Kingston","NHASANXUAT":"Kingston (USA)","MODEL":"DT50/32GBFR","CHUANGIAOTIEP":"USB 3.1 / 3.0 / 2.0","DUNGLUONG":"32 GB","BAOHANH":"60 tháng"},{"TEN":"USB 3.0 SanDisk Ultra SDCZ48 32GB 100MB/s","GIA":270000,"HINHANH":"USB/Sandisk-CZ48-01-280x315.jpg","MOTA":"Thông số kĩ thuật Nhà sản xuất Sandisk (USA) Model SDCZ48 Chuẩn giao tiếp USB 3.0 ; 2.0 Dung lượng 32 GB Tốc độ đọc 100 MB/s Tốc độ ghi 25 MB/s Bảo hành 60 tháng Di chuyển Movie Full-length chưa đến 40 giây USB SanDisk Ultra USB 3.0 Flash Drive đươc trang bị tốc độ chuyển dữ liệu nhanh hơn và khả năng lưu trữ rất cao trong thiết kế rất nhỏ gọn. Tiết kiệm thời gian với tốc độ di chuyển các dữ liệu nhanh hơn gấp 10 lần so với chuẩn USB 2.0. Khả năng lưu trữ lên đến 256GB, USB SanDisk Ultra USB 3.0 Flash Drive đáp ứng mọi nhu cầu lưu trữ của bạn. Khả năng lưu trữ cực lớn Với dung lượng lên đến 256 GB, bạn có thể lưu trữ rất nhiều nội dung dữ liệu vào USB SanDisk Ultra USB 3.0 Flash Drive và mang đến bất kì nơi đâu. Hãy tận hưởng tốc độ cực cao của USB 3.0 USB SanDisk Ultra USB 3.0 Flash Drive có khả năng truyền tải file lên đến 100 MB/s, vì vậy bạn có thể di chuyển một bộ phim với độ dài đầy đủ chỉ chưa đầy 40 giây. Giữ các tập tin của bạn an toàn với SanDisk SecureAccess Software Tập tin của bạn có thể được bảo vệ rất an toàn ngay cả khi bạn chia sẻ USB với những người khác. Phần mềm SanDisk SecureAccess (đi kèm) cho phép bạn thiết lập mật khẩu một thư mục trên ổ đĩa của bạn và bảo vệ các tập tin của bạn với mã hóa 128-bit AES. Dung lượng cực khủng Với dung lượng lên đến 256GB, USB SanDisk Ultra USB 3.0 Flash Drive máng đến cho bạn rất nhiều không gian để giữ tất cả các tập tin yêu thích của bạn, từ các bức ảnh có độ phân giải cao, MP3 và phim, đến các bài thuyết trình, các tập tin đồ họa và tài liệu quan trọng khác. Tiết kiệm thời gian tối đa USB SanDisk Ultra USB 3.0 Flash Drive truyền tải và lưu trữ tập tin lớn lên nhanh hơn so với chuẩn USB 2.0 ổ đĩa gấp mười lần. Thương hiệu Sandisk Cổng kết nối USB 3.0","NHASANXUAT":"Sandisk (USA)","MODEL":"SDCZ48","CHUANGIAOTIEP":"USB 3.0 ; 2.0","DUNGLUONG":"32 GB","BAOHANH":"60 tháng"},{"TEN":"USB 3.1 Kingston Zodiac Monkey King 2016 32GB Limited Edition","GIA":270000,"HINHANH":"USB/USB-3.1-Kingston-Zodiac-Monkey-King-2016-32GB-280x315.jpg","MOTA":"Thông số kĩ thuật Nhà sản xuất Kingston (USA) Model DTCNY16/32GB Chuẩn giao tiếp USB 3.1 ; 3.0 ; 2.0 Dung lượng 32 GB Tốc độ đọc ~100 MB/s Tốc độ ghi ~10 – 15 MB/s Chất liệu Nhôm nguyên khối Kích thước 2 x 0.9 x6.7 cm Bảo hành 60 tháng USB 3.1 Kingston Zodiac Monkey 2016 32GB Phiên bản hạn chế USB 3.1 Kingston Zodiac Monkey 2016 32GB là phiên bản hạn chế đặc biệt dành cho tết Bính Thân 2016 tại thị trường châu Á. Với thiết kế độc đáo hình đầu chú khỉ tạo nên biểu tượng may mắn ngay đầu năm mới. Sản phẩm được chứa trong một hộp kim loại rất sang trọng, thích hợp dùng làm quà tặng hoặc lưu niệm. Với số lượng sản xuất hạn chế, đây là chiếc USB mà bạn cần sở hữu ngay trong dịp tết Bính Thân.Khả năng tương thích USB 3.1 Kingston Monkey 2016 có chuẩn giao tiếp 3.1 tốc độ cao, đảm bảo hiệu năng và tốc độ cần thiết của một USB cao cấp. Đồng thời vẫn tương thích với các cổng USB 3.0, 2.0, 1.1. USB 3.1 là sự kế thừa cho chuẩn USB 3.0, có thể nhận diện bằng cổng kết nối màu xanh. USB 3.1 tăng gấp đôi tốc độ truyền tải lên 10Gbps nó hoàn toàn tương thích với các thiết bị cũ.Bảo hành USB 3.1 Kingston Zodiac Monkey 2016 được bảo hành 5 năm. Thương hiệu Kingston Cổng kết nối USB 3.1","NHASANXUAT":"Kingston (USA)","MODEL":"DTCNY16/32GB","CHUANGIAOTIEP":"USB 3.1 ; 3.0 ; 2.0","DUNGLUONG":"32 GB","BAOHANH":"60 tháng"},{"TEN":"USB 3.0 Samsung BAR 32GB","GIA":350000,"HINHANH":"USB/MUF-02-280x315.jpg","MOTA":"Thông số kĩ thuật Hãng sản xuất Samsung Model BAR-32BA Chuẩn giao tiếp USB 3.0 ; 2.0 Dung lượng 32 GB Tốc độ đọc ~130 MB/s Tốc độ ghi ~25 MB/s Bảo hành 24 tháng USB Samsung BAR 3.0 USB Samsung BAR 3.0 là một giải pháp lý tưởng cho những nhu cầu về tốc độ khi di chuyển các tập tin giữa các máy tính. không những có tốc độ cao, USB Samsung BAR 3.0 còn có kiểu dáng đẹp, thiết kế siêu nhỏ gọn. Ngoài ra USB Samsung BAR 3.0 còn có thể chống nước, chống sốc, chống nhiệt độ cao, chống từ trường, và chống tia X-Rays. USB Samsung BAR 3.0 có vỏ kim loại chất lượng cao giúp tăng độ bền, và được thiết kế rất tiện lợi, chống trượt. Bạn có thể hoàn toàn tin vào hiệu suất và độ tin cậy của thương hiệu bộ nhớ Samsung nổi tiếng khắp thế giới. Thiết kế kim loại cứng cáp USB Samsung BAR 3.0 được thiết kế rất tinh tế với kiểu dáng đẹp, một sự kết hợp hoàn hảo giữa hình thức bên ngoài và hiệu suất bên trong. Những đường nét sắc cạnh cũng như những vị trí được bo tròn một cách hợp lý, ngoài ra USB Samsung BAR 3.0 còn được thiết kế 1 lỗ vòng tròn cho phép bạn có thể móc vào chùm chìa khóa rất tiện lợi và không sợ bị mất. Độ chịu đựng cao Samsung nổi tiếng với khả năng bảo vệ dữ liệu của bạn rất an toàn. USB Samsung BAR 3.0 sử dụng công nghệ NAND flash với chế độ bảo hành 2 năm, và khả năng chịu đựng những môi trường khắc nghiệt rất cao: chống nước, chống sốc, chống nhiệt độ cao, chống từ trường, chống tia X-Ray. Đó chính là chất lượng mà bạn đã mong đợi từ thương hiệu Samsung nổi tiếng thế giới. Hiệu suất siêu cao Với nhu cầu và sự phát triển của công nghệ lưu trữ, Samsung ra mắt thế hệ USB chuẩn giao tiếp tốc độ cao USB 3.0 mới nhất cho tốc độ truyền dữ liệu siêu nhanh và khả năng tương thích ngược với chuẩn USB 2.0. Thương hiệu Samsung Cổng kết nối USB 3.0","MODEL":"BAR-32BA","CHUANGIAOTIEP":"USB 3.0 ; 2.0","DUNGLUONG":"32 GB","BAOHANH":"24 tháng"},{"TEN":"USB 3.0 SanDisk Ultra Fit CZ43 64GB","GIA":460000,"HINHANH":"USB/Sandisk-CZ43-64-01-280x315.jpg","MOTA":"Thông số kĩ thuật Nhà sản xuất Sandisk (USA) Model SDCZ43 Chuẩn giao tiếp USB 3.0 ; 2.0 Dung lượng 64 GB Tốc độ đọc ~ 135 MB/s Tốc độ ghi ~ 15 MB/s Bảo hành 60 tháng Di chuyển, lưu trữ và chia sẻ tập tin nhanh hơn mười lần với USB 3.0 Sandisk Ultra Fit CZ43 Với tốc độ đọc lên đến 130 MB/s và tốc độ ghi nhanh hơn gấp 10 lần so với chuẩn USB 2.0, USB SanDisk Ultra Fit USB 3.0 CZ43 Flash Drive cho phép bạn di chuyển, lưu trữ và chia sẻ thông tin yêu thích của bạn một cách nhanh chóng. Với dung lượng lên đến 128GB, mở rộng tối đa không gian lưu trữ cho thiết bị của bạn một cách nhanh chóng hoặc di chuyển các tập tin giữa các máy tính xách tay, máy tính bảng, máy chơi game, TV, hệ thống âm thanh xe hơi, hoặc thiết bị USB khác. Bạn thậm chí có thể chuyển một bộ phim độ dài đầy đủ chỉ trong 40 giây. Ngoài ra, USB SanDisk Ultra Fit USB 3.0 CZ43 Flash Drive tương thích ngượcvới cổng USB 2.0. Nhỏ gọn, thiết kế Stay-Put và dung lượng lưu trữ cực khủng USB SanDisk Ultra Fit USB 3.0 CZ43 Flash Drive được thiết kế cực nhỏ, vừa khít vào cổng USB của thiết bị và được thiết kế để có thể cắm liên tục mà không cần phải tháo ra, vì vậy bạn không phải lo lắng về việc bị rơi hoặc bị nứt vỡ. Và với dung lượng lên đến 128GB, bạn sẽ có rất nhiều không gian cho tất cả các hình ảnh, video, âm nhạc, và các trò chơi. Mật khẩu bảo vệ tập tin cá nhân của bạn Với phần mềm SanDisk SecureAccess, bạn có thể bảo vệ tập tin cá nhân của bạn trong một thư mục được bảo vệ bằng mật khẩu trong khi vẫn giữ các tập tin khác sẵn bình thường để chia sẻ. Với mã hóa 128-bit, bảo vệ tuyệt đối các tập tin nhạy cảm của bạn, ngay cả khi bạn chia sẻ nó với bạn bè. Phục hồi dữ liệu bị hỏng hoặc bị xóa với RescuePRO USB SanDisk Ultra Fit USB 3.0 CZ43 Flash Drive đi kèm với phần mềm RescuePRO Deluxe bản quyền một năm để phục hồi dữ liệu. Với phần mềm RescuePRO Deluxe, bạn rất dễ dàng để khôi phục lại hình ảnh hoặc video bị xóa hoặc bị mất và lưu chúng vào máy tính của bạn, thậm chí nếu các tập tin đã bị xóa vài tháng trước đây. Thương hiệu Sandisk Cổng kết nối USB 3.0","NHASANXUAT":"Sandisk (USA)","MODEL":"SDCZ43","CHUANGIAOTIEP":"USB 3.0 ; 2.0","DUNGLUONG":"64 GB","BAOHANH":"60 tháng"},{"TEN":"USB 3.0 SanDisk Ultra Flair CZ73 64GB 150MB/s","GIA":470000,"HINHANH":"USB/Sandisk-Ultra-Flair-CZ73-10-280x315.jpg","MOTA":"Thông số kĩ thuật Nhà sản xuất Sandisk Model CZ73 Chuẩn giao tiếp USB 3.0 ; 2.0 Dung lượng 64 GB Tốc độ đọc ~150 MB/s Tốc độ ghi ~25 MB/s Bảo hành 60 tháng USB SanDisk Ultra Flair CZ73 USB 3.0 Flash Drive Với tốc độ chuyển dữ liệu nhanh gấp 15 lần so với chuẩn USB 2.0, USB SanDisk Ultra Flair USB 3.0 Flash Drive được thiết kế để di chuyển các tập tin của bạn thật nhanh chóng, vì vậy nó sẽ tiết kiệm cho bạn rất nhiều thời gian. Vỏ bọc được làm bằng kim loại bền và rất phong cách giúp giữ các tập tin quan trọng của bạn an toàn. Bên cạnh đó phần mềm SanDisk SecureAccess đi kèm cho phép bạn dễ dàng thêm các mật khẩu được mã hóa cho các tập tin quan trọng. Chuẩn giao tiếp High-Speed USB 3.0 – Cho tốc độ lên đến 150MB/s Với công nghệ tốc độ cao USB 3.0, SanDisk Ultra Flair USB 3.0 Flash Drive mang đến tốc độ lên đến 150MB/s, cho phép bạn chuyển một bộ phim độ dài đầy đủ chỉ ít hơn 30 giây. Di chuyển và sao lưu tất cả các tập tin bạn cần trên USB mà không cần lo lắng về việc đầy bộ nhớ với dung lượng lên đến 32GB. Tất cả các sản phẩm của SanDisk sản xuất với tiêu chuẩn cao nhất và được thử nghiệm chặt chẽ trước khi xuất xưởng. Bạn có thể tự tin vào chất lượng, hiệu suất vượt trội và độ tin cậy của tất cả các sản phẩm SanDisk. Tốc độ đọc ghi cực nhanh Với tốc độ lên tới 150MB/s, USB SanDisk Ultra Flair CZ73 USB 3.0 Flash Drive nhanh gấp 15 lần so với các ổ USB 2.0 thông thường. Bạn có thể di chuyển một bộ phim có độ dài đầy đủ trong chưa đến 30 giây. Tiết kiệm tối đa thời gian cho bạn. Vỏ kim loại – cực đẹp và chắc chắn USB SanDisk Ultra Flair CZ73 USB 3.0 Flash Drive có vỏ bọc bằng kim loại cực bền giúp bảo vệ thiết bị khỏi những ngoại lực tác động bên ngoài. Thiết kế nhỏ gọn giúp bạn dễ dàng bỏ vào túi, ví và mang theo các dữ liệu của bạn đế bất cứ đâu. Phần mềm bảo mật SanDisk SecureAccess đi kèm Phần mềm bảo mật SanDisk SecureAccess đi kèm sẽ giúp bạn tạo một thư mục riêng trên ổ đĩa của bạn và mã hóa nó bằng thuật toán AES 128-bit kèm theo mật khẩu bảo vệ giúp bạn dễ dàng bảo vệ các tệp quan trọng. Chỉ cần chép dữ liệu quan trọng vào thư mục đã được chỉ định, dữ liệu của bạn sẽ được bảo vệ an toàn. Phục hồi dữ liệu dễ dàng với phần mềm RescuePRO Deluxe Phần mềm phục hồi dữ liệu RescuePRO Deluxe đi kèm sẽ giúp bạn dễ dàng khôi phục các tệp đã bị xóa chỉ với một cú Click chuột. Bạn có thể tải phần mềm tại ĐÂY Tương thích chuẩn giao tiếp USB 3.0 và 2.0 USB SanDisk Ultra Flair CZ73 USB 3.0 Flash Drive tương thích ngược với chuẩn giao tiếp USB 2.0 đời trước, vì vậy bạn có thể cắm nó vào bất kỳ cổng USB 2.0 hoặc 3.0 trên bất cứ máy tính nào. Thoải mái lưu trữ dữ liệu Biểu đồ ở bên cạnh sẽ cho bạn biết số lượng ảnh, video, nhạc và các tệp dữ liệu bạn có thể lưu trữ trong USB SanDisk Ultra Flair CZ73 USB 3.0 Flash Drive. Thương hiệu Sandisk Cổng kết nối USB 3.0","NHASANXUAT":"Sandisk","MODEL":"CZ73","CHUANGIAOTIEP":"USB 3.0 ; 2.0","DUNGLUONG":"64 GB","BAOHANH":"60 tháng"},{"TEN":"USB Sandisk Ultra OTG Type-C CZ450 64GB","GIA":500000,"HINHANH":"USB/CZ450-03-280x315.jpg","MOTA":"Thông số kĩ thuật Nhà sản xuất Sandisk (USA) Model SDCZ450-064G-G46 Hỗ trợ Smartphone, Macbook, Laptop có hỗ trợ cổng Type-C Chuẩn giao tiếp USB Type-CTM Dung lượng 64 GB Tốc độ 150MB/s Bảo hành 24 tháng USB SanDisk Ultra OTG Type-CTM CZ450 USB SanDisk Ultra OTG Type-CTM CZ450 được thiết kế cho điện thoại thông minh, máy tính bảng và máy tính có cổng USB chuẩn Type-C. Với hiệu suất USB 3.1 cho tốc độ lên đến 150MB/s, giúp bạn nhanh chóng chuyển hình ảnh, video, bài hát, và các tập tin khác. Thêm vào đó, ứng dụng đi kèm SanDisk Memory Zone cho Android (có sẵn trên Google Play) giúp bạn dễ dàng quản lý và sắp xếp dữ liệu của bạn. Tất cả các sản phẩm của SanDisk được sản xuất với tiêu chuẩn cao nhất và đã được thử nghiệm chặt chẽ. Bạn có thể tự tin vào chất lượng, hiệu suất vượt trội và độ tin cậy của tất cả các sản phẩm SanDisk. Chuẩn USB Type-C mới nhất USB SanDisk Ultra OTG Type-CTM CZ450 được thiết kế với độ dày siêu mỏng đặc biệt dành riêng cho các thiết bị có cổng USB Type-C. Hỗ trợ cắm đảo chiều rất tiện lợi khi sử dụng. Giải phóng không gian lưu trữ trên thiết bị di động của bạn USB SanDisk Ultra OTG Type-CTM CZ450 giúp bạn nhanh chóng giải phóng không gian lưu trữ trên thiết bị di động của bạn khi đầy bộ nhớ. USB 3.1 tốc độ cao USB SanDisk Ultra OTG Type-CTM CZ450 cung cấp tốc độ cao của chuẩn USB 3.1 với tốc độ lên đến 150MB/s, cho phép bạn nhanh chóng chuyển đổi hoặc chia sẻ hình ảnh, video, bài hát, và các tập tin khác giữa nhiều thiết bị. Tương thích cổng USB Type-C USB SanDisk Ultra OTG Type-CTM CZ450 tương thích với điện thoại thông minh, máy tính bảng, máy tính cá nhân và máy tính Mac có cổng USB Type-C. Đầu kết nối Type-C được thiết kế có thể trượt vào để bảo vệ khi không sử dụng. Ứng dụng đi kèm SanDisk Memory Zone Có sẵn trên cửa hàng Google Play, ứng dụng đi kèm SanDisk Memory Zone cho phép bạn xem, truy cập và sao lưu tất cả các tập tin từ bộ nhớ của điện thoại của bạn. Nó cũng có thể tự động di chuyển tập tin từ thiết bị của bạn vào ổ đĩa của bạn để giải phóng không gian lưu trữ. Nhiều dung lượng cho bạn lựa chọn USB SanDisk Ultra OTG Type-CTM CZ450 có dung lượng từ 16GB đến 128GB để đáp ứng tất cả các nhu cầu lưu trữ của bạn. Cổng kết nối USB Type-C Thương hiệu Sandisk","NHASANXUAT":"Sandisk (USA)","MODEL":"SDCZ450-064G-G46","CHUANGIAOTIEP":"USB Type-CTM","DUNGLUONG":"64 GB","BAOHANH":"24 tháng"},{"TEN":"USB 3.0 SanDisk Ultra SDCZ48 64GB 100MB/s","GIA":540000,"HINHANH":"USB/Sandisk-CZ48-01-280x315.jpg","MOTA":"Thông số kĩ thuật Nhà sản xuất Sandisk (USA) Model SDCZ48 Chuẩn giao tiếp USB 3.0 ; 2.0 Dung lượng 64 GB Tốc độ đọc 100 MB/s Tốc độ ghi 25 MB/s Bảo hành 60 tháng Di chuyển Movie Full-length chưa đến 40 giây USB SanDisk Ultra USB 3.0 Flash Drive đươc trang bị tốc độ chuyển dữ liệu nhanh hơn và khả năng lưu trữ rất cao trong thiết kế rất nhỏ gọn. Tiết kiệm thời gian với tốc độ di chuyển các dữ liệu nhanh hơn gấp 10 lần so với chuẩn USB 2.0. Khả năng lưu trữ lên đến 256GB, USB SanDisk Ultra USB 3.0 Flash Drive đáp ứng mọi nhu cầu lưu trữ của bạn. Khả năng lưu trữ cực lớn Với dung lượng lên đến 256 GB, bạn có thể lưu trữ rất nhiều nội dung dữ liệu vào USB SanDisk Ultra USB 3.0 Flash Drive và mang đến bất kì nơi đâu. Hãy tận hưởng tốc độ cực cao của USB 3.0 USB SanDisk Ultra USB 3.0 Flash Drive có khả năng truyền tải file lên đến 100 MB/s, vì vậy bạn có thể di chuyển một bộ phim với độ dài đầy đủ chỉ chưa đầy 40 giây. Giữ các tập tin của bạn an toàn với SanDisk SecureAccess Software Tập tin của bạn có thể được bảo vệ rất an toàn ngay cả khi bạn chia sẻ USB với những người khác. Phần mềm SanDisk SecureAccess (đi kèm) cho phép bạn thiết lập mật khẩu một thư mục trên ổ đĩa của bạn và bảo vệ các tập tin của bạn với mã hóa 128-bit AES. Dung lượng cực khủng Với dung lượng lên đến 256GB, USB SanDisk Ultra USB 3.0 Flash Drive máng đến cho bạn rất nhiều không gian để giữ tất cả các tập tin yêu thích của bạn, từ các bức ảnh có độ phân giải cao, MP3 và phim, đến các bài thuyết trình, các tập tin đồ họa và tài liệu quan trọng khác. Tiết kiệm thời gian tối đa USB SanDisk Ultra USB 3.0 Flash Drive truyền tải và lưu trữ tập tin lớn lên nhanh hơn so với chuẩn USB 2.0 ổ đĩa gấp mười lần. Thương hiệu Sandisk Cổng kết nối USB 3.0","NHASANXUAT":"Sandisk (USA)","MODEL":"SDCZ48","CHUANGIAOTIEP":"USB 3.0 ; 2.0","DUNGLUONG":"64 GB","BAOHANH":"60 tháng"},{"TEN":"USB 3.0 Samsung BAR 64GB","GIA":550000,"HINHANH":"USB/MUF-02-280x315.jpg","MOTA":"Thông số kĩ thuật Hãng sản xuất Samsung Model BAR-64BA Chuẩn giao tiếp USB 3.0 ; 2.0 Dung lượng 64 GB Tốc độ đọc ~130 MB/s Tốc độ ghi ~25 MB/s Bảo hành 24 tháng USB Samsung BAR 3.0 USB Samsung BAR 3.0 là một giải pháp lý tưởng cho những nhu cầu về tốc độ khi di chuyển các tập tin giữa các máy tính. không những có tốc độ cao, USB Samsung BAR 3.0 còn có kiểu dáng đẹp, thiết kế siêu nhỏ gọn. Ngoài ra USB Samsung BAR 3.0 còn có thể chống nước, chống sốc, chống nhiệt độ cao, chống từ trường, và chống tia X-Rays. USB Samsung BAR 3.0 có vỏ kim loại chất lượng cao giúp tăng độ bền, và được thiết kế rất tiện lợi, chống trượt. Bạn có thể hoàn toàn tin vào hiệu suất và độ tin cậy của thương hiệu bộ nhớ Samsung nổi tiếng khắp thế giới. Thiết kế kim loại cứng cáp USB Samsung BAR 3.0 được thiết kế rất tinh tế với kiểu dáng đẹp, một sự kết hợp hoàn hảo giữa hình thức bên ngoài và hiệu suất bên trong. Những đường nét sắc cạnh cũng như những vị trí được bo tròn một cách hợp lý, ngoài ra USB Samsung BAR 3.0 còn được thiết kế 1 lỗ vòng tròn cho phép bạn có thể móc vào chùm chìa khóa rất tiện lợi và không sợ bị mất. Độ chịu đựng cao Samsung nổi tiếng với khả năng bảo vệ dữ liệu của bạn rất an toàn. USB Samsung BAR 3.0 sử dụng công nghệ NAND flash với chế độ bảo hành 2 năm, và khả năng chịu đựng những môi trường khắc nghiệt rất cao: chống nước, chống sốc, chống nhiệt độ cao, chống từ trường, chống tia X-Ray. Đó chính là chất lượng mà bạn đã mong đợi từ thương hiệu Samsung nổi tiếng thế giới. Hiệu suất siêu cao Với nhu cầu và sự phát triển của công nghệ lưu trữ, Samsung ra mắt thế hệ USB chuẩn giao tiếp tốc độ cao USB 3.0 mới nhất cho tốc độ truyền dữ liệu siêu nhanh và khả năng tương thích ngược với chuẩn USB 2.0. Thương hiệu Samsung Cổng kết nối USB 3.0","MODEL":"BAR-64BA","CHUANGIAOTIEP":"USB 3.0 ; 2.0","DUNGLUONG":"64 GB","BAOHANH":"24 tháng"},{"TEN":"USB 3.1 Kingston Zodiac Puppy 2018 32GB Limited Edition","GIA":550000,"HINHANH":"USB/Zodiac-Puppy-2018-01-280x315.jpg","MOTA":"Thông số kĩ thuật Nhà sản xuất Kingston (USA) Model DTCNY18/32GB Chuẩn giao tiếp USB 3.1 ; 3.0 ; 2.0 Dung lượng 32 GB Tốc độ đọc ~110 MB/s Tốc độ ghi ~15 MB/s Chất liệu Nhôm nguyên khối Kích thước 20 x 37 x 12 mm Bảo hành 60 tháng USB 3.1 Kingston Zodiac Puppy 2018 32GB Phiên bản hạn chế USB 3.1 Kingston Zodiac Puppy 2018 32GB là phiên bản hạn chế đặc biệt dành cho tết Mậu Tuất 2018 tại thị trường châu Á. Với thiết kế độc đáo hình chú chó tạo nên biểu tượng may mắn ngay đầu năm mới. Sản phẩm được chứa trong một hộp kim loại rất sang trọng, thích hợp dùng làm quà tặng hoặc lưu niệm. Với số lượng sản xuất hạn chế, đây là chiếc USB mà bạn cần sở hữu ngay trong dịp tết Mậu Tuất. USB 3.1 Kingston Zodiac Puppy 2018 có chuẩn giao tiếp 3.1 tốc độ cao, đảm bảo hiệu năng và tốc độ cần thiết của một USB cao cấp. Đồng thời vẫn tương thích với các cổng USB 3.0, 2.0, 1.1. USB 3.1 là sự kế thừa cho chuẩn USB 3.0, có thể nhận diện bằng cổng kết nối màu xanh. USB 3.1 tăng gấp đôi tốc độ truyền tải lên 10Gbps nó hoàn toàn tương thích với các thiết bị cũ. USB 3.1 Kingston Zodiac Puppy 2018 được bảo hành 5 năm. Thương hiệu Kingston Cổng kết nối USB 3.1","NHASANXUAT":"Kingston (USA)","MODEL":"DTCNY18/32GB","CHUANGIAOTIEP":"USB 3.1 ; 3.0 ; 2.0","DUNGLUONG":"32 GB","BAOHANH":"60 tháng"},{"TEN":"USB 3.0 Kingston DataTraverler 100 G3 64 GB 100MB/s","GIA":560000,"HINHANH":"USB/DT-100-G3-64-01-280x315.jpg","MOTA":"Thông số kĩ thuật Nhà sản xuất Kingston (USA) Model DT 100 G3 Chuẩn giao tiếp USB 3.0 (Tương thích ngược 2.0) Dung lượng 64 GB Tốc độ đọc 100 MB/s Tốc độ ghi 10 MB/s Bảo hành 60 tháng Là công nghệ giao tiếp phổ biến nhất thế giới hiện nay, USB xuất hiện trong hầu hết các thiết bị, từ máy tính bảng cho tới máy in và smartphone. So với USB 2.0 tiêu chuẩn hiện nay, chuẩn USB 3.0 nâng khả năng truyền tải dữ liệu lên cao gấp 10 lần. Kingston DataTraverler 100 G3 là thiết bị tận dụng các cổng USB 3.0 ở các máy tính xách tay và máy tính để bàn mới; cho phép bạn nhanh chóng chuyển đổi tất cả dữ liệu của mình, từ văn bản, các bài báo cáo đến các file nhạc, hình ảnh… Sản phẩm còn nổi bật bởi thiết kế đơn giản, gam màu sang trọng cùng khả năng tương thích ngược với các hệ thống USB 2.0, mang đến nhiều tiện ích cho người dùng. Sản phẩm được bảo hành 60 tháng. TÍNH NĂNG NỔI BẬT Thiết bị lưu trữ đạt chuẩn USB 3.0 hiện đại, hiệu quả Là dòng sản phẩm USB 3.0, Kingston DataTraverler 100G3 cho tốc độ truyền tải nhanh chóng, ấn tượng; sử dụng cơ chế ngắt (interrupt) thay vì truy vấn lần lượt (polling) khi một thiết bị được cắm vào (giúp hạn chế lãng phí thời gian hay năng lượng trên một thiết bị nhàn rỗi, từ đó tiết kiệm pin hơn); điện áp cung cấp qua cổng USB 3.0, khi thiết bị cần hoạt động, không những đủ cho các thanh nhớ flash USB mà còn đủ cho các ổ đĩa gắn ngoài… Tương thích ngược với các thiết bị hỗ trợ USB 2.0 USB 3.0 Kingston DataTraverler 100G3 hỗ trợ khả năng tương thích ngược với các chuẩn trước đó, như 2.0, đạt tốc độ vượt trội so với những USB chuẩn 2.0 truyền thống. Dung lượng lưu trữ thoải mái Dòng sản phẩm Kingston DateTraverler 100G3 có dung lượng lưu trữ lên đến 64GB, thỏa mãn mọi như cầu học tập và làm việc của bạn. Hỗ trợ nhiều hệ điều hành thông dụng USB 3.0 Kingston DataTraverler 100G3 64GB sử dụng được cho nhiều hệ điều hành (cả chuẩn 3.0 lẫn 2.0): Linux, Mac OS X, Windows 7, Windows 8, Windows Vista, Windows XP. Thương hiệu Kingston Cổng kết nối USB 3.0","NHASANXUAT":"Kingston (USA)","MODEL":"DT 100 G3","CHUANGIAOTIEP":"USB 3.0 (Tương thích ngược 2.0)","DUNGLUONG":"64 GB","BAOHANH":"60 tháng"},{"TEN":"USB 3.0 SanDisk Ultra Fit CZ43 128GB","GIA":820000,"HINHANH":"USB/Sandisk-CZ43-128-01-280x315.jpg","MOTA":"Thông số kĩ thuật Nhà sản xuất Sandisk (USA) Model SDCZ43 Chuẩn giao tiếp USB 3.0 ; 2.0 Dung lượng 128 GB Tốc độ đọc ~ 135 MB/s Tốc độ ghi ~ 15 MB/s Bảo hành 60 tháng Di chuyển, lưu trữ và chia sẻ tập tin nhanh hơn mười lần với USB 3.0 Sandisk Ultra Fit CZ43 Với tốc độ đọc lên đến 130 MB/s và tốc độ ghi nhanh hơn gấp 10 lần so với chuẩn USB 2.0, USB SanDisk Ultra Fit USB 3.0 CZ43 Flash Drive cho phép bạn di chuyển, lưu trữ và chia sẻ thông tin yêu thích của bạn một cách nhanh chóng. Với dung lượng lên đến 128GB, mở rộng tối đa không gian lưu trữ cho thiết bị của bạn một cách nhanh chóng hoặc di chuyển các tập tin giữa các máy tính xách tay, máy tính bảng, máy chơi game, TV, hệ thống âm thanh xe hơi, hoặc thiết bị USB khác. Bạn thậm chí có thể chuyển một bộ phim độ dài đầy đủ chỉ trong 40 giây. Ngoài ra, USB SanDisk Ultra Fit USB 3.0 CZ43 Flash Drive tương thích ngượcvới cổng USB 2.0. Nhỏ gọn, thiết kế Stay-Put và dung lượng lưu trữ cực khủng USB SanDisk Ultra Fit USB 3.0 CZ43 Flash Drive được thiết kế cực nhỏ, vừa khít vào cổng USB của thiết bị và được thiết kế để có thể cắm liên tục mà không cần phải tháo ra, vì vậy bạn không phải lo lắng về việc bị rơi hoặc bị nứt vỡ. Và với dung lượng lên đến 128GB, bạn sẽ có rất nhiều không gian cho tất cả các hình ảnh, video, âm nhạc, và các trò chơi. Mật khẩu bảo vệ tập tin cá nhân của bạn Với phần mềm SanDisk SecureAccess, bạn có thể bảo vệ tập tin cá nhân của bạn trong một thư mục được bảo vệ bằng mật khẩu trong khi vẫn giữ các tập tin khác sẵn bình thường để chia sẻ. Với mã hóa 128-bit, bảo vệ tuyệt đối các tập tin nhạy cảm của bạn, ngay cả khi bạn chia sẻ nó với bạn bè. Phục hồi dữ liệu bị hỏng hoặc bị xóa với RescuePRO USB SanDisk Ultra Fit USB 3.0 CZ43 Flash Drive đi kèm với phần mềm RescuePRO Deluxe bản quyền một năm để phục hồi dữ liệu. Với phần mềm RescuePRO Deluxe, bạn rất dễ dàng để khôi phục lại hình ảnh hoặc video bị xóa hoặc bị mất và lưu chúng vào máy tính của bạn, thậm chí nếu các tập tin đã bị xóa vài tháng trước đây. Thương hiệu Sandisk Cổng kết nối USB 3.0","NHASANXUAT":"Sandisk (USA)","MODEL":"SDCZ43","CHUANGIAOTIEP":"USB 3.0 ; 2.0","DUNGLUONG":"128 GB","BAOHANH":"60 tháng"},{"TEN":"USB 3.0 SanDisk Ultra Flair CZ73 128GB","GIA":850000,"HINHANH":"USB/Sandisk-Ultra-Flair-CZ73-10-280x315.jpg","MOTA":"Thông số kĩ thuật Nhà sản xuất Sandisk Model CZ73 Chuẩn giao tiếp USB 3.0 ; 2.0 Dung lượng 128 GB Tốc độ đọc ~150 MB/s Tốc độ ghi ~25 MB/s Bảo hành 60 tháng USB SanDisk Ultra Flair CZ73 USB 3.0 Flash Drive Với tốc độ chuyển dữ liệu nhanh gấp 15 lần so với chuẩn USB 2.0, USB SanDisk Ultra Flair USB 3.0 Flash Drive được thiết kế để di chuyển các tập tin của bạn thật nhanh chóng, vì vậy nó sẽ tiết kiệm cho bạn rất nhiều thời gian. Vỏ bọc được làm bằng kim loại bền và rất phong cách giúp giữ các tập tin quan trọng của bạn an toàn. Bên cạnh đó phần mềm SanDisk SecureAccess đi kèm cho phép bạn dễ dàng thêm các mật khẩu được mã hóa cho các tập tin quan trọng. Chuẩn giao tiếp High-Speed USB 3.0 – Cho tốc độ lên đến 150MB/s Với công nghệ tốc độ cao USB 3.0, SanDisk Ultra Flair USB 3.0 Flash Drive mang đến tốc độ lên đến 150MB/s, cho phép bạn chuyển một bộ phim độ dài đầy đủ chỉ ít hơn 30 giây. Di chuyển và sao lưu tất cả các tập tin bạn cần trên USB mà không cần lo lắng về việc đầy bộ nhớ với dung lượng lên đến 32GB. Tất cả các sản phẩm của SanDisk sản xuất với tiêu chuẩn cao nhất và được thử nghiệm chặt chẽ trước khi xuất xưởng. Bạn có thể tự tin vào chất lượng, hiệu suất vượt trội và độ tin cậy của tất cả các sản phẩm SanDisk. Tốc độ đọc ghi cực nhanh Với tốc độ lên tới 150MB/s, USB SanDisk Ultra Flair CZ73 USB 3.0 Flash Drive nhanh gấp 15 lần so với các ổ USB 2.0 thông thường. Bạn có thể di chuyển một bộ phim có độ dài đầy đủ trong chưa đến 30 giây. Tiết kiệm tối đa thời gian cho bạn. Vỏ kim loại – cực đẹp và chắc chắn USB SanDisk Ultra Flair CZ73 USB 3.0 Flash Drive có vỏ bọc bằng kim loại cực bền giúp bảo vệ thiết bị khỏi những ngoại lực tác động bên ngoài. Thiết kế nhỏ gọn giúp bạn dễ dàng bỏ vào túi, ví và mang theo các dữ liệu của bạn đế bất cứ đâu. Phần mềm bảo mật SanDisk SecureAccess đi kèm Phần mềm bảo mật SanDisk SecureAccess đi kèm sẽ giúp bạn tạo một thư mục riêng trên ổ đĩa của bạn và mã hóa nó bằng thuật toán AES 128-bit kèm theo mật khẩu bảo vệ giúp bạn dễ dàng bảo vệ các tệp quan trọng. Chỉ cần chép dữ liệu quan trọng vào thư mục đã được chỉ định, dữ liệu của bạn sẽ được bảo vệ an toàn. Phục hồi dữ liệu dễ dàng với phần mềm RescuePRO Deluxe Phần mềm phục hồi dữ liệu RescuePRO Deluxe đi kèm sẽ giúp bạn dễ dàng khôi phục các tệp đã bị xóa chỉ với một cú Click chuột. Bạn có thể tải phần mềm tại ĐÂY Tương thích chuẩn giao tiếp USB 3.0 và 2.0 USB SanDisk Ultra Flair CZ73 USB 3.0 Flash Drive tương thích ngược với chuẩn giao tiếp USB 2.0 đời trước, vì vậy bạn có thể cắm nó vào bất kỳ cổng USB 2.0 hoặc 3.0 trên bất cứ máy tính nào. Thoải mái lưu trữ dữ liệu Biểu đồ ở bên cạnh sẽ cho bạn biết số lượng ảnh, video, nhạc và các tệp dữ liệu bạn có thể lưu trữ trong USB SanDisk Ultra Flair CZ73 USB 3.0 Flash Drive. Thương hiệu Sandisk Cổng kết nối USB 3.0","NHASANXUAT":"Sandisk","MODEL":"CZ73","CHUANGIAOTIEP":"USB 3.0 ; 2.0","DUNGLUONG":"128 GB","BAOHANH":"60 tháng"},{"TEN":"USB 3.1 SanDisk Extreme Go CZ800 64GB","GIA":890000,"HINHANH":"USB/CZ800-01-280x315.jpg","MOTA":"Thông số kĩ thuật Nhà sản xuất Sandisk Model SDCZ800-064G Chuẩn giao tiếp – USB 3.1 Gen 1 – USB 3.0 – USB 2.0 Dung lượng 64 GB Tốc độc đọc 200 MB/s Tốc độ ghi 150 MB/s Bảo hành 60 tháng USB 3.1 SanDisk Extreme Go CZ800 Với tốc độ ghi lên đến 150MB/s, USB 3.1 SanDisk Extreme Go CZ800 cho phép bạn sao chép và di chuyển dữ liệu cực kỳ nhanh chóng, tốc độ nhanh hơn 35X so với chuẩn USB 2.0. Thiết kế dạng trượt có thể thu vào được giúp bảo vệ đầu nối khi không sử dụng, và phần mềm SanDisk SecureAccess đi kèm cung cấp các chức năng bảo vệ mật khẩu các dữ liệu cá nhân của bạn được an toàn. Tất cả các sản phẩm của SanDisk sản xuất với tiêu chuẩn cao nhất và được thử nghiệm chặt chẽ trước khi xuất xưởng. Bạn có thể tự tin vào chất lượng, hiệu suất vượt trội và độ tin cậy của tất cả các sản phẩm SanDisk. Tốc độ đọc ghi cực nhanh Với tốc độ ghi lên tới 200MB/s và 150MB/s, USB 3.1 SanDisk Extreme Go CZ800 nhanh gấp 35 lần so với các ổ USB 2.0 thông thường. Chuyển một bộ phim có độ dài đầy đủ trong vài giây hoặc 1.000 tấm ảnh trong vòng chưa đầy 60 giây. Tiết kiệm tối đa thời gian cho bạn. Thiết kế dạng trượt USB 3.1 SanDisk Extreme Go CZ800 dạng trượt giúp đầu giao tiếp USB có thể thu vào để giữ an toàn khi không sử dụng. Phần mềm bảo mật SanDisk SecureAccess đi kèm Phần mềm bảo mật SanDisk SecureAccess đi kèm sẽ giúp bạn tạo một thư mục riêng trên ổ đĩa của bạn và mã hóa nó bằng thuật toán AES 128-bit kèm theo mật khẩu bảo vệ giúp bạn dễ dàng bảo vệ các tệp quan trọng. Chỉ cần chép dữ liệu quan trọng vào thư mục đã được chỉ định, dữ liệu của bạn sẽ được bảo vệ an toàn. Phục hồi dữ liệu dễ dàng với phần mềm RescuePRO Deluxe Phần mềm phục hồi dữ liệu RescuePRO Deluxe đi kèm sẽ giúp bạn dễ dàng khôi phục các tệp đã bị xóa chỉ với một cú Click chuột. Bạn có thể tải phần mềm tại ĐÂY Tương thích chuẩn giao tiếp USB 3.0 và 2.0 USB 3.1 SanDisk Extreme Go CZ800 tương thích ngược với chuẩn giao tiếp USB 2.0 đời trước, vì vậy bạn có thể cắm nó vào bất kỳ cổng USB 2.0 hoặc 3.0 trên bất cứ máy tính nào. Thoải mái lưu trữ dữ liệu Biểu đồ ở bên cạnh sẽ cho bạn biết số lượng ảnh, video, nhạc và các tệp dữ liệu bạn có thể lưu trữ trong USB 3.1 SanDisk Extreme Go CZ800. Thương hiệu Sandisk Cổng kết nối USB 3.1","NHASANXUAT":"Sandisk","MODEL":"SDCZ800-064G","CHUANGIAOTIEP":"– USB 3.1 Gen 1 – USB 3.0 – USB 2.0","DUNGLUONG":"64 GB","BAOHANH":"60 tháng"}]