[{"TEN":"Cáp ổ cứng di động 3.0 Seagate FreeAgent GoFlex 50cm","GIA":50000,"HINHANH":"Ổ Cứng Di Động/seagate-freeagent-goflex-01-280x315.jpg","MOTA":"Thông số kĩ thuật Hãng sản xuất Seagate Độ dài 50cm Chuẩn giao tiếp USB 3.0 Băng thông truyền tải 5Gbps Bảo hành Không bảo hành","CHUANGIAOTIEP":"USB 3.0","BAOHANH":"Không bảo hành"},{"TEN":"Bao da ổ cứng di động Western Digital","GIA":90000,"HINHANH":"Ổ Cứng Di Động/Bao-da-o-cung-di-dong-Western-Digital-280x315.jpg","MOTA":""},{"TEN":"Túi Vải Bảo Vệ Ổ Cứng 2.5 và Box 2.5","GIA":90000,"HINHANH":"Ổ Cứng Di Động/Tui-chong-sock-01-280x315.jpg","MOTA":""},{"TEN":"Hộp bảo vệ ổ cứng di động Western Digital","GIA":90000,"HINHANH":"Ổ Cứng Di Động/Hop-bao-ve-o-cung-WD-01-280x315.jpg","MOTA":""},{"TEN":"Ổ cứng di động Maxtor M3 USB 3.0 1TB STSHX-M101TCBM","GIA":1270000,"HINHANH":"Ổ Cứng Di Động/Maxtor-M3-Gift-280x315.jpg","MOTA":"Thông số kĩ thuật Nhà sản xuất Maxtor (Seagate) Model M3 STSHX-M101TCBM Chuẩn giao tiếp USB 3.0 5Gbps Dung lượng 1TB Hệ điều hành hỗ trợ Windows, MacOS, Linux,… Tốc độ ghi ~120 MB/s Chất liệu Nhựa Bảo hành 36 tháng Ổ cứng di động Maxtor M3 USB 3.0 Sự trở lại của một huyền thoại Ổ cứng di động Maxtor M3 USB 3.0 mang đến khả năng lưu trữ và bảo vệ dữ liệu. Giúp bạn dễ dàng mang đi bất cứ nơi nào và có dung lượng cực lớn lên đến 4TB. Thiết kế vỏ nhựa chống trượt màu đen có khả năng chịu lực, bền chắc đáp ứng được những yêu cầu sử dụng hàng ngày của bạn. Cùng với chuẩn giao tiếp SuperSpeed USB 3.0 sẽ tiết kiệm cho bạn rất nhiều thời gian khi di chuyển hoặc copy dữ liệu từ máy tính. Thiết kế tinh tế – cổ điển Ổ cứng di động Maxtor M3 USB 3.0 được thiết kế hình dáng cực kì đơn giản với vỏ bằng nhựa cứng chống va đập, bảo vệ những linh kiện bên trong. Bề mặt khắc nổi 3D bắt mắt và có khả năng chống vân tay, chống trượt, chống trầy xước. Các góc cạnh được bo tròn giúp bạn dễ thao tác cầm nắm trên tay. Đèn Led hiển thị giúp bạn theo dõi tình trạng hoạt động của ổ cứng. Chuẩn giao tiếp SuperSpeed USB 3.0 Ổ cứng di động Maxtor M3 USB 3.0 được trang bị chuẩn giao tiếp tốc độ cao USB 3.0 giúp bạn dễ dàng và nhanh chóng di chuyển hoặc copy dữ liệu giữa các thiết bị, bạn sẽ tiết kiệm rất nhiều thời gian quý báu và làm được nhiều việc hơn. Phần mềm quản lý – bảo vệ dữ liệu của bạn Ổ cứng di động Maxtor M3 USB 3.0 đi kèm với hướng dẫn sử dụng bằng tiếng Việt và phần mềm Drive Manager được chép sẵn trong ổ cứng hoặc bạn có thể tải về trực tiếp tại trang chủ của Seagate (Click here to Download), giúp bạn theo dõi, quản lý và bảo mật dữ liệu của bạn với những tính năng đi kèm như: AutoBackup, SafetyKey, SerectZone,… Bảo hành chính hãng 3 năm Ổ cứng di động Maxtor M3 USB 3.0 có chế độ hỗ trợ kĩ thuật và bảo hành 3 năm chính hãng tại MemoryZone và Seagate Việt Nam Thương hiệu Maxtor Cổng kết nối USB 3.0","NHASANXUAT":"Maxtor (Seagate)","MODEL":"M3 STSHX-M101TCBM","CHUANGIAOTIEP":"USB 3.0 5Gbps","DUNGLUONG":"1TB","BAOHANH":"36 tháng"},{"TEN":"Ổ cứng di động chống Sock Apacer AC630 USB 3.1 1TB","GIA":1350000,"HINHANH":"Ổ Cứng Di Động/AC630-01-280x315.jpg","MOTA":"Thông số kĩ thuật Nhà sản xuất Apacer Model AC630 Series Dung lượng 1 TB Màu sắc Đen viền cam Cổng giao tiếp USB 3.0 5 Gbps (Tương thích USB 2.0, 1.1 and 1.0) Chất liệu Vỏ nhựa, bọc viền Silicon chống Sock Hệ điều hành hỗ trợ Windows, MacOS, Linux,… Phụ kiện đi kèm Cable USB 3.0 Kích thước 143.3 x 92.9 x 20.1 mm Đèn Led tín hiệu Nguồn, trạng thái đọc/ghi Bảo hành 36 tháng Ổ cứng di động chống Sock Apacer AC630 USB 3.1 Gen 1 Khả năng chống sock tuyệt hảo Ổ cứng di động chống Sock Apacer AC630 được thiết kế và trang bị một khung bằng cao su nguyên tấm bao bọc từ bên trong lẫn bên ngoài tạo thành một lớp đệm cực dày có thể chịu lực tác động trực tiếp, giảm thiểu ảnh hưởng khi truy cập dữ liệu khi bạn đang di chuyển, mang đến cho bạn sự linh động khi bạn có thể di động, hoạt động với hiệu suất và độ tin cậy rất cao. Cho phép bạn truy cập dữ liệu trong sự an toàn về bảo mật và dáng vẻ thể thao. Sự di động linh hoạt của sản phẩm và thiết kế năng động thể thao, phù hợp với các yêu cầu cho những người đam mê hoạt động ngoài trời. Military-Grade – Đạt tiêu chuẩn của quân đội Ổ cứng di động chống Sock Apacer AC630 đạt tiêu chuẩn quân đội MIL-STD-810G 516.6 Procedure IV (Transit Drop Test), có thể rơi từ độ cao 1.22m mà không làm mất dữ liệu. Khả năng chống nước tiêu chuẩn IP55 Ổ cứng di động chống Sock Apacer AC630 đảm bảo bảo vệ toàn diện chống lại bụi và nước, bảo vệ tuyệt đối các linh kiện bên trong. Thiết kế dây Cable xung quanh độc đáo Ổ cứng di động chống Sock Apacer AC630 được thiết kế các rãnh xung quanh thiết bị để giữ cáp USB, rất gọn gàng và tiện lợi khi không phải bận tâm về vấn đề mất cable. Tốc độ siêu cao USB 3.1 Gen 1 Giao diện USB 3.1 Gen 1 làm cho quá trình sao lưu dữ liệu trở nên nhanh chóng, dễ dàng xử lý một triệu hình ảnh, nửa triệu bài hát MP3 hoặc 833 giờ video Full HD. Thương hiệu Apacer Cổng kết nối USB 3.0","NHASANXUAT":"Apacer","MODEL":"AC630 Series","DUNGLUONG":"1 TB","BAOHANH":"36 tháng"},{"TEN":"Ổ cứng di động 1TB chống Sock Apacer AC631 Military-Grade USB 3.1 Gen 1","GIA":1350000,"HINHANH":"Ổ Cứng Di Động/AC631-01-280x315.jpg","MOTA":"Thông số kĩ thuật Nhà sản xuất Apacer Model AC631 Series Dung lượng 1 TB Màu sắc Đen viền Xanh Cổng giao tiếp USB 3.1 Gen 1 5Gbps (Tương thích USB 2.0, 1.1 and 1.0) Chất liệu Vỏ nhựa, bọc viền Silicon chống Sock Hệ điều hành hỗ trợ Windows, MacOS, Linux,… Phụ kiện đi kèm Cable USB 3.0 Kích thước 153.3 x 93 x 21 mm Đèn Led tín hiệu Nguồn, trạng thái đọc/ghi Bảo hành 36 tháng Ổ cứng di động chống Sock chuẩn quân đội Apacer AC631 USB 3.1 Gen 1 Khả năng chống Sock tuyệt hảo Ổ cứng di động chống Sock Apacer AC631 được thiết kế và trang bị một khung bằng cao su nguyên tấm bao bọc từ bên trong lẫn bên ngoài tạo thành một lớp đệm cực dày có thể chịu lực tác động trực tiếp, bề mặt bằng nhựa cứng kết hợp những đường vân 3D giúp giảm thiểu những tác động bên ngoài có thể ảnh hưởng đế việc truy cập dữ liệu khi bạn đang di chuyển, mang đến cho bạn sự linh động khi bạn có thể di động, hoạt động với hiệu suất và độ tin cậy rất cao. Cho phép bạn truy cập dữ liệu trong sự an toàn về bảo mật và dáng vẻ thể thao. Sự di động linh hoạt của sản phẩm và thiết kế năng động thể thao, phù hợp với các yêu cầu cho những người đam mê hoạt động ngoài trời. Military-Grade – Đạt tiêu chuẩn của quân đội Ổ cứng di động chống Sock Apacer AC631 đạt tiêu chuẩn của quân đội về chống Sock MIL-STD-810G 516.6 Procedure IV (Transit Drop Test), có thể rơi từ độ cao 1.22m mà không làm mất dữ liệu. Khả năng chống nước tiêu chuẩn IP55 Ổ cứng di động chống Sock Apacer AC631 đảm bảo bảo vệ toàn diện chống lại bụi và nước, bảo vệ tuyệt đối các linh kiện bên trong. Bề mặt chống trầy – Chống vân tay Bề mặt của ổ cứng di động chống Sock Apacer AC631 được thiết kế những đường vân 3D không chỉ tạo cảm giác thể thao, mà còn chống trầy xước hoặc dấu vân tay. Giảm ma sát chống gây hư hại cho các linh kiện bên trong. Thiết kế dây Cable xung quanh độc đáo Ổ cứng di động chống Sock Apacer AC631 được thiết kế các rãnh xung quanh thiết bị để giữ cáp USB, rất gọn gàng và tiện lợi khi không phải bận tâm về vấn đề mất cable. Durable USB Type-A Female Connector Ổ cứng di động chống Sock Apacer AC631 hỗ trợ chuẩn kết nối USB Type-A Female trên ổ với độ bền lên đến 10.000 lần cắm và rút liên tục, đảm bảo an toàn cho người sử dụng. Tốc độ siêu cao USB 3.1 Gen 1 Giao diện USB 3.1 Gen 1 làm cho quá trình sao lưu dữ liệu trở nên nhanh chóng, dễ dàng xử lý một triệu hình ảnh, nửa triệu bài hát MP3 hoặc 833 giờ video Full HD. Thương hiệu Apacer Cổng kết nối USB 3.0","NHASANXUAT":"Apacer","MODEL":"AC631 Series","DUNGLUONG":"1 TB","BAOHANH":"36 tháng"},{"TEN":"Ổ cứng di động chống Sock Silicon Power Armor A60 1TB","GIA":1490000,"HINHANH":"Ổ Cứng Di Động/A60-02-280x315.jpg","MOTA":"Thông số kĩ thuật Nhà sản xuất Silicon Power Model Armor A60 Chuẩn giao tiếp USB 3.0 Dung lượng 1TB Hệ điều hành hỗ trợ Windows, MacOS, Linux,… Tốc độ truyền tải Lến đến 5Gb/s Bảo hành 3 Năm Ổ cứng di động Silicon Power Armor A60 Ổ cứng di động Silicon Power Armor A60 đạt tiêu chuẩn chống thấm nước IPX4 giúp bảo vệ ổ cứng cực tốt. Cho bạn sự yên tâm khi sử dụng ở nhiều môi trường khắc nghiệt nhất. Đảm bảo an toàn cho dữ liệu của bạn. Chống sốc và chống thấm nước Ổ cứng di động Silicon Power Armor A60 được thiết kế với vỏ cao su siêu bền và hệ thống chống sốc bên trong, tạo nên một lớp đệm hoàn hảo giúp bảo vệ chống lại sự va đập, bụi bặm và nước. Thiết kế cáp bọc xung quanh Thiết kế khe gắn cáp xung quanh ổ cứng rất gọn gàng giúp bạn dễ dàng mang theo bên mình và chống mất cáp. Chống trơn trượt, chống trầy xước Ổ cứng di động Silicon Power Armor A60 với thiết kế kết cấu bề mặt đặc biệt có thể chống trơn trượt khi cầm trên tay, chống dấu vân tay và chống trầy xước.  Chuẩn giao tiếp tốc độ cao SuperSpeed USB 3.1 Với chuẩn giao tiếp tốc độ mới nhất SuperSpeed USB 3.1 Gen1 (USB3.0) cải thiện tối đa tốc độ đọc ghi. Giúp tiết kiệm thời gian quý báu của bạn để bạn có thể làm được nhiều việc hơn. Thương hiệu SiliconPower Cổng kết nối USB 3.0","NHASANXUAT":"Silicon Power","MODEL":"Armor A60","CHUANGIAOTIEP":"USB 3.0","DUNGLUONG":"1TB","BAOHANH":"3 Năm"},{"TEN":"Ổ cứng di động Western Digital My Passport 1TB (New 2017)","GIA":1520000,"HINHANH":"Ổ Cứng Di Động/MyPassport-Gift1-280x315.jpg","MOTA":"Thông số kĩ thuật Nhà sản xuất Western Digital Model My Passport Chuẩn giao tiếp USB 3.0 Dung lượng 1 TB Hệ điều hành hỗ trợ Windows, MacOS, Linux,… Màu sắc Đen, trắng, đỏ, xanh, cam, vàng Chất liệu Vỏ nhựa cao cấp Bảo hành 3 năm Ổ cứng di động Western Digital My Passport Ổ cứng di động Western Digital My Passport với danh tiếng khắp thế giới về độ tin cậy cho bạn sự yên tâm khi lưu trữ các dữ liệu quan trọng của bạn. Thiết kế mới với nhiều màu sắc theo từng phong cách của bạn, kích thước nhỏ gọn giúp bạn có thể dễ dàng mang nội dung quý giá của bạn ở khắp mọi nơi bạn muốn. Đặc điểm nổi bật: – Tự động sao lưu với phần mềm WD Backup Software đi kèm – Hỗ trợ bảo vệ bằng mật khẩu bảo vệ với mã hóa phần cứng – Dễ dàng sử dụng – Nhiều màu sắc cho bạn lựa chọn – Chất lượng cực tốt với tiêu chuẩn của WD – Dung lượng tối đa lên đến 4TB – Chuẩn giao tiếp USB 3.0; tương thích ngược USB 2.0 Tự động sao lưu với WD Backup Software Được trang bị với phần mềm sao lưu WD Backup Software đi kèm, do đó bạn có thể tự động sao lưu ảnh, video, âm nhạc và tài liệu. Bạn cũng có thể đặt lịch để ổ cứng sẽ tự động sao lưu theo thời gian bạn đã chọn. Bảo vệ dữ liệu bằng mật khẩu Với 256-bit mã hóa phần cứng AES được tích hợp với phần mềm WD Security giúp giữ cho dữ liệu của bạn được riêng tư và an toàn. Dễ dàng khôi phục mật khẩu nhanh chóng trong trường hợp bạn quên mật khẩu. Dễ dàng sử dụng Ổ cứng di động Western Digital My Passport rất dễ dàng sử dụng, chỉ cần bạn cắm vào máy tính và không cần bài bất kì phần mềm hoặc driver nào cả. Ngoài ra, ổ cứng di động Western Digital My Passport đi kèm với tất cả các phần mềm bạn cần để giúp bảo vệ tất cả dữ liệu của bạn, bao gồm cả WD Backup Software và phần mềm WD Security. Thiết kế cổ điển Kiểu dáng đẹp, thiết kế sống động của ổ cứng di động Western Digital My Passport với Logo của hãng được in chìm, nhiều màu sắc đẹp, do đó bạn có thể lựa chọn phù hợp theo phong cách cá nhân, của riêng bạn. Dung lượng cực lớn Với dung lượng lên đến 4TB, bạn có thể mang theo tất cả những gì bạn cần, các hình ảnh, âm nhạc và video mà bạn yêu thích đến bất cứ nơi nào bạn đi… WD – Chất lượng hàng đầu thế giới WD với qui trình sản xuất đòi hỏi các yêu cầu về độ bền, khả năng chống sốc và độ tin cậy lâu dài. Và ổ cứng di động Western Digital My Passport có chế độ bảo hành 2 năm cho bạn sự yên tâm nhất khi sử dụng. Thương hiệu Western Digital Cổng kết nối USB 3.0","NHASANXUAT":"Western Digital","MODEL":"My Passport","CHUANGIAOTIEP":"USB 3.0","DUNGLUONG":"1 TB","BAOHANH":"3 năm"},{"TEN":"Ổ cứng di động Transcend StoreJet Slim 25M3S 1TB","GIA":1520000,"HINHANH":"Ổ Cứng Di Động/25M3S-02-280x315.jpg","MOTA":"Thông số kĩ thuật Nhà sản xuất Transcend Model StoreJet 25M3S TS1TSJ25M3S Chuẩn giao tiếp USB 3.0 Dung lượng 1TB (Xám viền xanh) Hệ điều hành hỗ trợ Windows, MacOS, Linux,… Tốc độ truyền tải Lến đến 5Gb/s Bảo hành 24 tháng Transcend StoreJet 25M3S TS1TSJ25M3S Với mong muốn đem đến cho những đối tượng có đam mê về tốc độ truyền tải nhanh, khả năng lưu trữ lớn và hệ thống bảo vệ sốc ba lớp độc đáo, ổ cứng di động USB 3.0 StoreJet 25M3S là một thiết bị lưu trữ lý tưởng nhất để sao lưu dữ liệu, lưu trữ và di chuyển tập tin. Thiết kế 2018 mới nhất với bề rộng hẹp hơn và bề dày mỏng hơn mẫu cũ, sẽ giúp bạn tiết kiệm được không gian và dễ dàng mang đến bất kì nơi nào bạn muốn. Tốc độ siêu cao Ổ cứng di động USB 3.0 StoreJet 25M3S được trang bị cổng SuperSpeed USB thế hệ 3.0 mang đến tốc độ truyền gấp 3 lần so với USB 2.0. Nhờ có băng thông được cải tiến của USB 3.0, StoreJet 25M3S giúp bạn chia sẻ dữ liệu dễ dàng hơn và nhanh hơn bao giờ hết với tốc độ truyền thực tế lên đến 100MB/s. Chống Sock đạt tiêu chuẩn quân đội Nhỏ gọn, bền và đáng tin cậy, ổ cứng di động USB 3.0 StoreJet 25M3S bên ngoài trông khá gồ ghề vì được bảo vệ bởi một hệ thống bảo vệ sốc ba lớp tiên tiến chống lại được các môi trường sử dụng khắc nghiệt nhất. Vỏ ngoài được làm bằng chất liệu Silicone chống tác động mạnh, bên trong được gia cố bởi một vỏ cứng và một hệ thống cố định ổ cứng bên trong – tất cả được thiết kế để giảm lực tác động và giảm Sock tối đa. Auto – Backup Ổ cứng di động USB 3.0 StoreJet 25M3S được trang bị một nút tự động sao lưu One-Touch cực kỳ thuận tiện cho việc sao lưu dữ liệu và đồng bộ hóa ngay lập tức khi được sử dụng với phần mềm Transcend Elite. Ngoài ra, ổ cứng di động USB 3.0 StoreJet 25M3S hỗ trợ tất cả các hệ điều hành Microsoft Windows 8/7 / Vista / XP, Mac OS X, và các hệ thống Linux, và tương thích ngược với các cổng USB 2.0. Phần mềm quản lý dữ liệu Transcend Elite Ổ cứng di động USB 3.0 StoreJet 25M3S đi kèm với phầm mềm Transcend Elite, một công cụ quản lý dữ liệu độc quyền giúp bạn quản lý dữ liệu và tăng năng suất, hiệu năng của ổ đĩa. Với phần mềm này, bạn có thể dễ dàng thực hiện sao lưu, nén tập tin với mã hóa 256-bit AES Encryption, và sử dụng ổ đĩa cứng như là một chìa khóa kỹ thuật số BitLocker cho máy tính của bạn. RecoveRX – Phầm mềm cứu dữ liệu đi kèm Ngoài phần mềm quả lý ổ đĩa thì ổ cứng di động USB 3.0 StoreJet 25M3S được trang bị thêm phần mềm cứu dữ liệu miễn phí sẽ giúp bạn dễ dàng phục hồi những dữ liệu bị xóa nhầm. Thương hiệu Transcend Cổng kết nối USB 3.0","NHASANXUAT":"Transcend","MODEL":"StoreJet 25M3S TS1TSJ25M3S","CHUANGIAOTIEP":"USB 3.0","DUNGLUONG":"1TB (Xám viền xanh)","BAOHANH":"24 tháng"},{"TEN":"Ổ cứng di động Seagate Backup Plus Slim 1TB","GIA":1550000,"HINHANH":"Ổ Cứng Di Động/Seagate-Backup-Plus-Slim-Gift-280x315.jpg","MOTA":"Thông số kĩ thuật Nhà sản xuất Seagate Model Backup Plus Slim (Siêu mỏng) Chuẩn giao tiếp USB 3.0 5Gbps Dung lượng 1 TB Hệ điều hành hỗ trợ Windows, MacOS, Linux,… Tốc độ truyền tải ~120 MB/s Bảo hành 36 tháng Ổ cứng di động Siêu Mỏng Seagate Backup Plus Slim Backup dữ liệu của bạn – Bất cứ lúc nào, bất cứ nơi đâu Ổ cứng di động Seagate Backup Plus Slim được thiết siêu mỏng và rất đơn giản, chỉ với một cú Click là bạn đã có thể bảo vệ và chia sẻ toàn bộ cuộc sống số của bạn. Ổ cứng di động Seagate Backup Plus Slim rất mỏng và có dung lượng lên đến 4TB – rất hoàn hảo, sẽ cùng bạn đi bất kì nơi đâu. – Kiểu dáng đẹp, cứng rắn, thiết kế kim loại nhôm thời trang cho tính di động ở khắp mọi nơi – Sử dụng ứng dụng Seagate Mobile Backup sao lưu trực tiếp từ các thiết bị di động của bạn – Chia sẻ nội dung của bạn giữa các máy tính và máy Mac Dễ dàng quản lý dữ liệu yêu thích của bạn ở bất cứ nơi nào Tất cả hình ảnh, phim và video có thể được sao lưu bằng cách sử dụng phần mềm Dashboard Seagate, bao gồm cả những gì mà bạn đã chia sẻ trên Facebook, Flickr và YouTube. Chỉ cần một cú Click hoặc bạn có thể lên một kế hoạch sao lưu tự động để bảo vệ các tập tin của bạn trên ổ cứng di động Seagate Backup Plus Slim, rất thuận tiện. Plug-and-Play – Tốc độ kết nối cực cao Với chuẩn giao tiếp tốc độ cao USB 3.0 và hỗ trợ kết nối 2.0, cùng với chức năng Plug-and-Play trên PC hoặc Laptop của bạn mà không cần nguồn phụ, sẽ tiết kiệm cho bạn rất nhiều thời gian và mang đến cho bạn sự tiện lợi. Chia sẻ qua Lyve! Ổ cứng di động Seagate Backup Plus Slim có thể chuyển đổi thành một thiết bị sao lưu Lyve, bảo vệ tất cả những dữ liệu của bạn từ tất cả các thiết bị của bạn. Ứng dụng Lyve trên máy tính và các thiết bị di động của bạn sẽ tìm thấy tất cả các hình ảnh và video từ các thiết bị khác nhau và tạo ra một Single. Bạn có thể tạo bộ sưu tập, sắp xếp và quản lý chúng và dễ dàng xem từ điện thoại thông minh hoặc máy tính bảng của bạn. Cùng với tính năng Lyve’s Moments Past, sẽ luôn tự động hiện những kỉ niệm đẹp của bạn mà bạn đã lưu trong thời gian trước. Sản phẩm bao gồm: – Seagate Backup Plus Slim Portable Drive – Seagate Dashboard backup software – 200GB dung lượng lưu trữ OneDrive trong 2 năm miễn phi (Phải được kích hoạt trước 30-06-2017) – 18-inch USB 3.0 cable, Plug-and-Play – Quick start guide Thương hiệu Seagate Cổng kết nối USB 3.0","NHASANXUAT":"Seagate","MODEL":"Backup Plus Slim (Siêu mỏng)","CHUANGIAOTIEP":"USB 3.0 5Gbps","DUNGLUONG":"1 TB","BAOHANH":"36 tháng"},{"TEN":"Ổ cứng di động USB 3.0 ADATA HD710 1TB Dashdrive Durable","GIA":1550000,"HINHANH":"Ổ Cứng Di Động/ADATA-HD710M-02-280x315.jpg","MOTA":"Thông số kĩ thuật Nhà sản xuất ADATA Model HD710 Series Dung lượng 1 TB Màu sắc Xanh, Vàng, Đen, Xanh quân đội (Camouflage) Cổng giao tiếp USB 3.0 5 Gbps (Tương thích USB 2.0, 1.1 and 1.0) Chất liệu Vỏ nhựa, bọc Silicon Hệ điều hành hỗ trợ Windows, MacOS, Linux,… Phụ kiện đi kèm Cable USB 3.0 Kích thước 132 x 99 x 22 Đèn Led tín hiệu Nguồn, trạng thái đọc/ghi Bảo hành 36 tháng Ổ cứng di động USB 3.0 ADATA Dashdrive Durable HD710 Ổ cứng di động USB 3.0 ADATA Dashdrive Durable HD710 mang đến cho bạn sự linh động khi có thể di động, hoạt động với hiệu suất và độ tin cậy rất cao. Cho phép bạn truy cập dữ liệu trong sự an toàn về bảo mật và dáng vẻ thể thao. Ổ cứng di động USB 3.0 ADATA Dashdrive Durable HD710 có vỏ bọc silicone độc đáo, và ổ đĩa bên trong được thiết kế theo tiêu chuẩn quân đội, có thể chống shock, chống bụi (IP68) và chống thấm nước với cổng kết nối USB 3.0 siêu nhanh. Sự di động linh hoạt của nó và thiết kế năng động thể thao, phù hợp với các yêu cầu cho những người đam mê hoạt động ngoài trời, với nhiều lựa chọn màu sắc bao gồm màu xanh, vàng, và đen và màu xanh quân đội Camouflage. Khả năng chống bụi, chống nước theo tiêu chuẩn IP68 Ổ cứng di động USB 3.0 ADATA Dashdrive Durable HD710 đã được thử nghiệm nghiêm ngặt theo tiêu chuẩn quân đội IP68, khả năng chống nước tuyệt vời và bảo vệ khỏi bụi. Nhờ thiết kế cực bền của nó, Ổ cứng di động USB 3.0 ADATA Dashdrive Durable HD710 có thể hoạt động bình thường ngay cả trong một môi trường đầy bụi bặm hoặc sau khi bị ngâm nước với độ sâu lên đến 2 mét trong 120 phút. Chống sốc tiêu chuẩn quân đội Ổ cứng di động USB 3.0 ADATA Dashdrive Durable HD710 đã vượt qua những thử nghiệm với tiêu chuẩn quân sự MIL-STD-810G 516,6 rất nghiêm ngặt. Ổ cứng di động USB 3.0 ADATA Dashdrive Durable HD710 có khả năng chịu đựng các điều kiện khắc nghiệt mà vẫn giữ an toàn cho dữ liệu của bạn với tốc độ truy xuất rất nhanh. Thiết kế dây Cable xung quanh độc đáo Ổ cứng di động USB 3.0 ADATA Dashdrive Durable HD710 được thiết kế các rãnh xung quanh thiết bị để giữ cáp USB, rất gọn gàng và tiện lợi khi không phải bận tâm về vấn đề mất cable. Đèn LED tín hiệu Ổ cứng di động USB 3.0 ADATA Dashdrive Durable HD710 bên trong được trang bị một HDD 2,5″ với đèn LED hiển thị màu xanh cho phép bạn kiểm tra tình trạng nguồn, đọc, ghi của thiết bị Thương hiệu Adata Cổng kết nối USB 3.0","NHASANXUAT":"ADATA","MODEL":"HD710 Series","DUNGLUONG":"1 TB","BAOHANH":"36 tháng"},{"TEN":"Ổ cứng di động 3.0 Toshiba Canvio Alumy 1TB","GIA":1590000,"HINHANH":"Ổ Cứng Di Động/CanvioAlumy-Gift-280x315.jpg","MOTA":"Thông số kĩ thuật Nhà sản xuất Toshiba Model Canvio Alumy Chuẩn giao tiếp USB 3.0 Dung lượng 1 TB Hệ điều hành hỗ trợ Windows, MacOS, Linux,… Màu sắc Gold, Silver, Black, Metallic Blue, Metallic Red Chất liệu Vỏ nhôm cao cấp Tốc độ 115 MB/s Bảo hành 36 tháng Ổ cứng di động Toshiba Canvio Alumy Thiết kế chắc chắn – dễ dàng lưu trữ Ổ cứng di động Toshiba Canvio Alumy giúp bạn lưu trữ dữ liệu quan trọng một cách an toàn, truy cập nhanh chóng và dễ dàng thông qua SuperSpeed USB 3.0. Với vỏ nhôm trang nhã – màu Gold, Silver, Black, Metallic Blue hoặc Metallic Red – phù hợp với mọi sở thích và phong cách thời trang của bạn. Hơn thế nữa, phần mềm sao lưu NTI® Backup Now EZ™ dễ sử dụng cho phép bạn thực hiện sao lưu tự động lên tới 2,5 TB dữ liệu. Tốc độ SuperSpeed USB 3.0 Được trang bị chuẩn giao tiếp mới nhất USB 3.0, giúp bạn di chuyển dữ liệu cực nhanh và tiết kiệm nhiều thời gian hơn. Ngoài ra, sản phẩm cũng tương thích với công nghệ USB 2.0 giúp bạn kết nối với các thế hệ máy tính cũ. Thiết kế vỏ nhôm chắc chắn Với vỏ bọc được thiết kế bằng nhôm chắc chắn, ổ cứng di động Toshiba Canvio Alumy được thiết kế rất thời trang và đáp ứng khả năng bảo vệ an toàn cho dữ liệu của bạn. Với bộ cảm biến sốc và công nghệ chống sock, ổ cứng di động Toshiba Canvio Alumy sẽ giữ cho dữ liệu của bạn an toàn trước những va chạm và vết bẩn khi sử dụng. Bảo vệ dữ liệu an toàn Ổ cứng di động Toshiba Canvio Alumy được đi kèm với phầm mềm backup dữ liệu NTI® Backup Now EZ™ giúp bạn hệ thống và quản lý tập tin và sao lưu toàn bộ dữ liệu của bạn. Dễ dàng di chuyển dữ liệu Với ổ cứng di động Toshiba Canvio Alumy, bạn có thể tự động chuyển dữ liệu bằng chức năng sao lưu tự động. Ngoài ra, bạn có thể tự chọn các dữ liệu sao lưu một cách dễ dàng bằng cách kéo và thả các tập tin, sắp xếp lại dữ liệu chỉ trong vài giây. Nhiều màu sắc thời trang Ổ cứng di động Toshiba Canvio Alumy được thiết kế năm màu sắc khác nhau: màu Gold, Silver, Black, Metallic Blue hoặc Metallic Red sẽ đáp ứng mọi phong cách của bạn. Các phiên bản Silver, Black và Gold lý tưởng cho một kiểu dáng đẹp, thanh lịch, trong khi phiên bản Metallic Blue hoặc Metallic Red trông sôi động và sang trọng. Toshiba – Thương hiệu bộ nhớ hàng đầu thế giới Toshiba – tập đoàn điện tử công nghệ cao đa quốc gia, với sản lượng chiếm 25% tổng số lượng thiết bị bộ nhớ được bán ra trên toàn thế giới (thống kê 2016), cho thấy các sản phẩm của Toshiba luôn được khách hàng ở mọi nơi tin tưởng và ưa chuộng. Và điều đặc biệt nhất đó là Toshiba tự sản xuất linh kiện cho chính mình, đảm bảo độ tương thích giữ các linh kiện, tiết kiệm năng lượng tối đa mà vẫn cho hiệu suất cao, và giá thành cực kì thấp. Thương hiệu Toshiba Cổng kết nối USB 3.0","NHASANXUAT":"Toshiba","MODEL":"Canvio Alumy","CHUANGIAOTIEP":"USB 3.0","DUNGLUONG":"1 TB","BAOHANH":"36 tháng"},{"TEN":"Ổ cứng di động 1TB Western Digital My Passport Ultra 2017","GIA":1790000,"HINHANH":"Ổ Cứng Di Động/WD-PU-2017-00-280x315.jpg","MOTA":"Thông số kĩ thuật Nhà sản xuất Western Digital Model My Passport Ultra Chuẩn giao tiếp USB 3.0 Dung lượng 1 TB Hệ điều hành hỗ trợ Windows, MacOS, Linux,… Màu sắc White-Gold ; Black-Gray Chất liệu Vỏ nhôm, nhựa cao cấp Bảo hành 3 năm Ổ cứng di động 4TB Western Digital My Passport Ultra 2017 Phong cách sáng tạo – Tự động sao lưu Ổ cứng di động Western Digital My Passport Ultra 2017 với tốc độ và độ tin cậy cực cao, giúp bạn lưu trữ dữ liệu và mang chúng đến bất kỳ nơi đâu, thiết kế tuyệt đẹp khi kết hợp phong cách kim loại mạnh mẽ bọc phần dưới và sự mềm mại của chất liệu nhựa ở phần trên rất tinh tế. Với rất nhiều không gian lưu trữ lên đến 4tb, phần mềm WD Backup và bảo vệ mật khẩu đi kèm sẽ giúp bảo vệ dữ liệu của bạn được an toàn. Dễ dàng sử dụng, chỉ cần cắm vào và sử dụng. Brilliant Design Ổ cứng di động Western Digital My Passport Ultra 2017 được thiết kế vỏ bọc nhôm nửa dưới và nhựa mờ phần trên, một sự kết hợp độc đáo đem đến sự tinh tế nhất mà chưa thiết bị nào được thiết kế như vậy, cùng với kích thước cực kì nhỏ gọn giúp bạn dễ dàng mang theo bên mình đến bất cứ nơi đâu. Social Media và Cloud Storage Phần mềm WD Discovery đi kèm giúp bạn kết nối với các phương tiện truyền thông xã hội phổ biến và các dịch vụ lưu trữ đám mây như Facebook, Instagram, Dropbox và Google Drive. Bạn sẽ dễ dàng backup dữ liệu về ổ cứng di động Western Digital My Passport Ultra 2017. Tự động sao lưu Ổ cứng di động Western Digital My Passport Ultra 2017 được trang bị phần mềm WD Backup để giúp đảm bảo ảnh, video, nhạc và tài liệu của bạn không bị mất. Bạn có thể đặt lịch tự động Backup dữ liệu từ máy tính vào ổ đĩa. Bảo vệ mật khẩu bằng mã hóa phần cứng Ổ cứng di động Western Digital My Passport Ultra 2017đi kèm với mã hóa phần cứng AES 256-bit với phần mềm WD Security được tích hợp để giúp giữ an toàn cho dữ liệu cá nhân của bạn. Bạn chỉ cần đặt một mật khẩu cá nhân để kích hoạt mã hóa phần cứng và bảo vệ dữ liệu. Độ tin cậy cao nhất Được sản xuất với độ tin cậy tuyệt vời của WD, bạn có thể tin tưởng ổ cứng di động Western Digital My Passport Ultra 2017 sẽ luôn bảo vệ ảnh, video và các tài liệu quan trọng của bạn được an toàn với chế độ hỗ trợ bảo hành phần cứng trong 3 năm. Dễ dàng sử dụng Chỉ cần cắm Ổ cứng di động Western Digital My Passport Ultra 2017 và sử dụng, bạn không cần cài bất kì phần mềm nào khác. Thương hiệu Western Digital Cổng kết nối USB 3.0","NHASANXUAT":"Western Digital","MODEL":"My Passport Ultra","CHUANGIAOTIEP":"USB 3.0","DUNGLUONG":"1 TB","BAOHANH":"3 năm"},{"TEN":"Ổ cứng di động chống Sock Apacer AC630 USB 3.1 2TB","GIA":2150000,"HINHANH":"Ổ Cứng Di Động/AC630-01-280x315.jpg","MOTA":"Thông số kĩ thuật Nhà sản xuất Apacer Model AC630 Series Dung lượng 2 TB Màu sắc Đen viền cam Cổng giao tiếp USB 3.0 5 Gbps (Tương thích USB 2.0, 1.1 and 1.0) Chất liệu Vỏ nhựa, bọc viền Silicon chống Sock Hệ điều hành hỗ trợ Windows, MacOS, Linux,… Phụ kiện đi kèm Cable USB 3.0 Kích thước 143.3 x 92.9 x 20.1 mm Đèn Led tín hiệu Nguồn, trạng thái đọc/ghi Bảo hành 36 tháng Ổ cứng di động chống Sock Apacer AC630 USB 3.1 Gen 1 Khả năng chống sock tuyệt hảo Ổ cứng di động chống Sock Apacer AC630 được thiết kế và trang bị một khung bằng cao su nguyên tấm bao bọc từ bên trong lẫn bên ngoài tạo thành một lớp đệm cực dày có thể chịu lực tác động trực tiếp, giảm thiểu ảnh hưởng khi truy cập dữ liệu khi bạn đang di chuyển, mang đến cho bạn sự linh động khi bạn có thể di động, hoạt động với hiệu suất và độ tin cậy rất cao. Cho phép bạn truy cập dữ liệu trong sự an toàn về bảo mật và dáng vẻ thể thao. Sự di động linh hoạt của sản phẩm và thiết kế năng động thể thao, phù hợp với các yêu cầu cho những người đam mê hoạt động ngoài trời. Military-Grade – Đạt tiêu chuẩn của quân đội Ổ cứng di động chống Sock Apacer AC630 đạt tiêu chuẩn quân đội MIL-STD-810G 516.6 Procedure IV (Transit Drop Test), có thể rơi từ độ cao 1.22m mà không làm mất dữ liệu. Khả năng chống nước tiêu chuẩn IP55 Ổ cứng di động chống Sock Apacer AC630 đảm bảo bảo vệ toàn diện chống lại bụi và nước, bảo vệ tuyệt đối các linh kiện bên trong. Thiết kế dây Cable xung quanh độc đáo Ổ cứng di động chống Sock Apacer AC630 được thiết kế các rãnh xung quanh thiết bị để giữ cáp USB, rất gọn gàng và tiện lợi khi không phải bận tâm về vấn đề mất cable. Tốc độ siêu cao USB 3.1 Gen 1 Giao diện USB 3.1 Gen 1 làm cho quá trình sao lưu dữ liệu trở nên nhanh chóng, dễ dàng xử lý một triệu hình ảnh, nửa triệu bài hát MP3 hoặc 833 giờ video Full HD. Thương hiệu Apacer Cổng kết nối USB 3.0","NHASANXUAT":"Apacer","MODEL":"AC630 Series","DUNGLUONG":"2 TB","BAOHANH":"36 tháng"},{"TEN":"Ổ cứng di động 1TB LaCie Porsche Design Mobile Drive P’9227 USB 3.1 Type-C STFD1000400","GIA":2150000,"HINHANH":"Ổ Cứng Di Động/Porsche-P9227-01-280x315.jpg","MOTA":"Thông số kĩ thuật Nhà sản xuất LaCie Model STFD1000400 Chuẩn giao tiếp – USB 3.1 – USB Type-C Dung lượng 1TB Hệ điều hành hỗ trợ Windows, MacOS, Linux,… Tốc độ ~110 MB/s 5Gbps Chất liệu Nhôm Màu sắc Silver Kích thước 84 × 128 × 10 mm Siêu Mỏng Bảo hành 24 tháng Ổ cứng di động LaCie Porsche Design Mobile Drive Thiết kế bởi Porsche – Chất lượng của LaCie Trong sự hợp tác giữa Porsche và Lacie vào năm 2003, ổ cứng di động LaCie Porsche Design Mobile Drive chứa đựng mọi công nghệ tiên tiến nhất của LaCie với phong cách tinh tế từ Porsche Design. Thiết kế vỏ nhôm siêu mỏng Ổ cứng di động LaCie Porsche Design Mobile Drive là ổ cứng di động mỏng nhất hiện nay với độ dày chỉ 10mm (phiên bản 1TB, 2TB) và 21mm (phiên bản 4TB, 5TB) kết hợp cùng vỏ nhôm cực kỳ cứng cáp giúp bảo vệ những linh kiện bên trong cực tốt, mang phong cách thời trang sang trọng và lịch lãm của một doanh nhân. Nhiều dung lượng cho bạn lựa chọn Ổ cứng di động LaCie Porsche Design Mobile Drive có dung lượng 1Tb, 2TB, 4TB và 5TB. Cho bạn nhiều sự lựa chọn phù hợp với từng nhu cầu. Chuẩn giao tiếp USB Type-C tốc độ cao Giao tiếp USB Type-C Dễ dàng kết nối với cổng USB Type-C hỗ trợ đảo chiều. Kết nối mọi thiết bị Cáp USB Type-C to USB Type-A đi kèm giúp bạn kết nối mọi thiết bị. Tốc độ cực cao Với băng thông 5Gbps, bạn có thể di chuyển dữ liệu cực kỳ nhanh chóng. Được thiết kế cho Macbook® của bạn Ổ cứng di động LaCie Porsche Design Mobile Drive được thiết kế đặc biệt để phù hợp với phong cách của Apple, vỏ bọc nhôm phong cách tinh tế phù hợp với MacBook® mới của bạn. Ngoài ra, sản phẩm hỗ trợ tương thích với Time Machine® để bạn có thể Backup dữ liệu vào ổ đĩa bằng cách sử dụng phần mềm trong Mac. Thương hiệu Lacie Cổng kết nối USB 3.1, USB Type-C","NHASANXUAT":"LaCie","MODEL":"STFD1000400","CHUANGIAOTIEP":"– USB 3.1 – USB Type-C","DUNGLUONG":"1TB","BAOHANH":"24 tháng"},{"TEN":"Ổ cứng di động 2TB chống Sock Apacer AC631 Military-Grade USB 3.1 Gen 1","GIA":2150000,"HINHANH":"Ổ Cứng Di Động/AC631-01-280x315.jpg","MOTA":"Thông số kĩ thuật Nhà sản xuất Apacer Model AC631 Series Dung lượng 2 TB Màu sắc Đen viền Xanh Cổng giao tiếp USB 3.1 Gen 1 5Gbps (Tương thích USB 2.0, 1.1 and 1.0) Chất liệu Vỏ nhựa, bọc viền Silicon chống Sock Hệ điều hành hỗ trợ Windows, MacOS, Linux,… Phụ kiện đi kèm Cable USB 3.0 Kích thước 153.3 x 93 x 21 mm Đèn Led tín hiệu Nguồn, trạng thái đọc/ghi Bảo hành 36 tháng Ổ cứng di động chống Sock chuẩn quân đội Apacer AC631 USB 3.1 Gen 1 Khả năng chống Sock tuyệt hảo Ổ cứng di động chống Sock Apacer AC631 được thiết kế và trang bị một khung bằng cao su nguyên tấm bao bọc từ bên trong lẫn bên ngoài tạo thành một lớp đệm cực dày có thể chịu lực tác động trực tiếp, bề mặt bằng nhựa cứng kết hợp những đường vân 3D giúp giảm thiểu những tác động bên ngoài có thể ảnh hưởng đế việc truy cập dữ liệu khi bạn đang di chuyển, mang đến cho bạn sự linh động khi bạn có thể di động, hoạt động với hiệu suất và độ tin cậy rất cao. Cho phép bạn truy cập dữ liệu trong sự an toàn về bảo mật và dáng vẻ thể thao. Sự di động linh hoạt của sản phẩm và thiết kế năng động thể thao, phù hợp với các yêu cầu cho những người đam mê hoạt động ngoài trời. Military-Grade – Đạt tiêu chuẩn của quân đội Ổ cứng di động chống Sock Apacer AC631 đạt tiêu chuẩn của quân đội về chống Sock MIL-STD-810G 516.6 Procedure IV (Transit Drop Test), có thể rơi từ độ cao 1.22m mà không làm mất dữ liệu. Khả năng chống nước tiêu chuẩn IP55 Ổ cứng di động chống Sock Apacer AC631 đảm bảo bảo vệ toàn diện chống lại bụi và nước, bảo vệ tuyệt đối các linh kiện bên trong. Bề mặt chống trầy – Chống vân tay Bề mặt của ổ cứng di động chống Sock Apacer AC631 được thiết kế những đường vân 3D không chỉ tạo cảm giác thể thao, mà còn chống trầy xước hoặc dấu vân tay. Giảm ma sát chống gây hư hại cho các linh kiện bên trong. Thiết kế dây Cable xung quanh độc đáo Ổ cứng di động chống Sock Apacer AC631 được thiết kế các rãnh xung quanh thiết bị để giữ cáp USB, rất gọn gàng và tiện lợi khi không phải bận tâm về vấn đề mất cable. Durable USB Type-A Female Connector Ổ cứng di động chống Sock Apacer AC631 hỗ trợ chuẩn kết nối USB Type-A Female trên ổ với độ bền lên đến 10.000 lần cắm và rút liên tục, đảm bảo an toàn cho người sử dụng. Tốc độ siêu cao USB 3.1 Gen 1 Giao diện USB 3.1 Gen 1 làm cho quá trình sao lưu dữ liệu trở nên nhanh chóng, dễ dàng xử lý một triệu hình ảnh, nửa triệu bài hát MP3 hoặc 833 giờ video Full HD. Thương hiệu Apacer Cổng kết nối USB 3.0","NHASANXUAT":"Apacer","MODEL":"AC631 Series","DUNGLUONG":"2 TB","BAOHANH":"36 tháng"},{"TEN":"Ổ cứng di động USB 3.0 ADATA Dashdrive Durable HD710 2TB","GIA":2450000,"HINHANH":"Ổ Cứng Di Động/ADATA-HD710M-02-280x315.jpg","MOTA":"Thông số kĩ thuật Nhà sản xuất ADATA Model HD710 Series Dung lượng 2 TB Màu sắc Xanh, Vàng, Đen, Xanh quân đội (Camouflage) Cổng giao tiếp USB 3.0 5 Gbps (Tương thích USB 2.0, 1.1 and 1.0) Chất liệu Vỏ nhựa, bọc Silicon Hệ điều hành hỗ trợ Windows, MacOS, Linux,… Phụ kiện đi kèm Cable USB 3.0 Kích thước 132 x 99 x 22 Đèn Led tín hiệu Nguồn, trạng thái đọc/ghi Bảo hành 36 tháng Ổ cứng di động USB 3.0 ADATA Dashdrive Durable HD710 Ổ cứng di động USB 3.0 ADATA Dashdrive Durable HD710 mang đến cho bạn sự linh động khi có thể di động, hoạt động với hiệu suất và độ tin cậy rất cao. Cho phép bạn truy cập dữ liệu trong sự an toàn về bảo mật và dáng vẻ thể thao. Ổ cứng di động USB 3.0 ADATA Dashdrive Durable HD710 có vỏ bọc silicone độc đáo, và ổ đĩa bên trong được thiết kế theo tiêu chuẩn quân đội, có thể chống shock, chống bụi (IP68) và chống thấm nước với cổng kết nối USB 3.0 siêu nhanh. Sự di động linh hoạt của nó và thiết kế năng động thể thao, phù hợp với các yêu cầu cho những người đam mê hoạt động ngoài trời, với nhiều lựa chọn màu sắc bao gồm màu xanh, vàng, và đen và màu xanh quân đội Camouflage. Khả năng chống bụi, chống nước theo tiêu chuẩn IP68 Ổ cứng di động USB 3.0 ADATA Dashdrive Durable HD710 đã được thử nghiệm nghiêm ngặt theo tiêu chuẩn quân đội IP68, khả năng chống nước tuyệt vời và bảo vệ khỏi bụi. Nhờ thiết kế cực bền của nó, Ổ cứng di động USB 3.0 ADATA Dashdrive Durable HD710 có thể hoạt động bình thường ngay cả trong một môi trường đầy bụi bặm hoặc sau khi bị ngâm nước với độ sâu lên đến 2 mét trong 120 phút. Chống sốc tiêu chuẩn quân đội Ổ cứng di động USB 3.0 ADATA Dashdrive Durable HD710 đã vượt qua những thử nghiệm với tiêu chuẩn quân sự MIL-STD-810G 516,6 rất nghiêm ngặt. Ổ cứng di động USB 3.0 ADATA Dashdrive Durable HD710 có khả năng chịu đựng các điều kiện khắc nghiệt mà vẫn giữ an toàn cho dữ liệu của bạn với tốc độ truy xuất rất nhanh. Thiết kế dây Cable xung quanh độc đáo Ổ cứng di động USB 3.0 ADATA Dashdrive Durable HD710 được thiết kế các rãnh xung quanh thiết bị để giữ cáp USB, rất gọn gàng và tiện lợi khi không phải bận tâm về vấn đề mất cable. Đèn LED tín hiệu Ổ cứng di động USB 3.0 ADATA Dashdrive Durable HD710 bên trong được trang bị một HDD 2,5″ với đèn LED hiển thị màu xanh cho phép bạn kiểm tra tình trạng nguồn, đọc, ghi của thiết bị Thương hiệu Adata Cổng kết nối USB 3.0","NHASANXUAT":"ADATA","MODEL":"HD710 Series","DUNGLUONG":"2 TB","BAOHANH":"36 tháng"},{"TEN":"Ổ cứng di động Transcend StoreJet Slim 25M3S 2TB","GIA":2550000,"HINHANH":"Ổ Cứng Di Động/25M3S-02-280x315.jpg","MOTA":"Thông số kĩ thuật Nhà sản xuất Transcend Model StoreJet 25M3S TS2TSJ25M3S Chuẩn giao tiếp USB 3.0 Dung lượng 2TB (Xám viền xanh) Hệ điều hành hỗ trợ Windows, MacOS, Linux,… Tốc độ truyền tải Lến đến 5Gb/s Bảo hành 24 tháng Transcend StoreJet 25M3S TS2TSJ25M3S Với mong muốn đem đến cho những đối tượng có đam mê về tốc độ truyền tải nhanh, khả năng lưu trữ lớn và hệ thống bảo vệ sốc ba lớp độc đáo, ổ cứng di động USB 3.0 StoreJet 25M3S là một thiết bị lưu trữ lý tưởng nhất để sao lưu dữ liệu, lưu trữ và di chuyển tập tin. Thiết kế 2018 mới nhất với bề rộng hẹp hơn và bề dày mỏng hơn mẫu cũ, sẽ giúp bạn tiết kiệm được không gian và dễ dàng mang đến bất kì nơi nào bạn muốn. Tốc độ siêu cao Ổ cứng di động USB 3.0 StoreJet 25M3S được trang bị cổng SuperSpeed USB thế hệ 3.0 mang đến tốc độ truyền gấp 3 lần so với USB 2.0. Nhờ có băng thông được cải tiến của USB 3.0, StoreJet 25M3S giúp bạn chia sẻ dữ liệu dễ dàng hơn và nhanh hơn bao giờ hết với tốc độ truyền thực tế lên đến 100MB/s. Chống Sock đạt tiêu chuẩn quân đội Nhỏ gọn, bền và đáng tin cậy, ổ cứng di động USB 3.0 StoreJet 25M3S bên ngoài trông khá gồ ghề vì được bảo vệ bởi một hệ thống bảo vệ sốc ba lớp tiên tiến chống lại được các môi trường sử dụng khắc nghiệt nhất. Vỏ ngoài được làm bằng chất liệu Silicone chống tác động mạnh, bên trong được gia cố bởi một vỏ cứng và một hệ thống cố định ổ cứng bên trong – tất cả được thiết kế để giảm lực tác động và giảm Sock tối đa. Auto – Backup Ổ cứng di động USB 3.0 StoreJet 25M3S được trang bị một nút tự động sao lưu One-Touch cực kỳ thuận tiện cho việc sao lưu dữ liệu và đồng bộ hóa ngay lập tức khi được sử dụng với phần mềm Transcend Elite. Ngoài ra, ổ cứng di động USB 3.0 StoreJet 25M3S hỗ trợ tất cả các hệ điều hành Microsoft Windows 8/7 / Vista / XP, Mac OS X, và các hệ thống Linux, và tương thích ngược với các cổng USB 2.0. Phần mềm quản lý dữ liệu Transcend Elite Ổ cứng di động USB 3.0 StoreJet 25M3S đi kèm với phầm mềm Transcend Elite, một công cụ quản lý dữ liệu độc quyền giúp bạn quản lý dữ liệu và tăng năng suất, hiệu năng của ổ đĩa. Với phần mềm này, bạn có thể dễ dàng thực hiện sao lưu, nén tập tin với mã hóa 256-bit AES Encryption, và sử dụng ổ đĩa cứng như là một chìa khóa kỹ thuật số BitLocker cho máy tính của bạn. RecoveRX – Phầm mềm cứu dữ liệu đi kèm Ngoài phần mềm quả lý ổ đĩa thì ổ cứng di động USB 3.0 StoreJet 25M3S được trang bị thêm phần mềm cứu dữ liệu miễn phí sẽ giúp bạn dễ dàng phục hồi những dữ liệu bị xóa nhầm. Thương hiệu Transcend Cổng kết nối USB 3.0","NHASANXUAT":"Transcend","MODEL":"StoreJet 25M3S TS2TSJ25M3S","CHUANGIAOTIEP":"USB 3.0","DUNGLUONG":"2TB (Xám viền xanh)","BAOHANH":"24 tháng"},{"TEN":"Ổ cứng di động 3.0 Toshiba Canvio Alumy 2TB","GIA":2750000,"HINHANH":"Ổ Cứng Di Động/CanvioAlumy-Gift-280x315.jpg","MOTA":"Thông số kĩ thuật Nhà sản xuất Toshiba Model Canvio Alumy Chuẩn giao tiếp USB 3.0 Dung lượng 2 TB Hệ điều hành hỗ trợ Windows, MacOS, Linux,… Màu sắc Gold, Silver, Black, Metallic Blue, Metallic Red Chất liệu Vỏ nhôm cao cấp Tốc độ 115 MB/s Bảo hành 36 tháng Ổ cứng di động Toshiba Canvio Alumy Thiết kế chắc chắn – dễ dàng lưu trữ Ổ cứng di động Toshiba Canvio Alumy giúp bạn lưu trữ dữ liệu quan trọng một cách an toàn, truy cập nhanh chóng và dễ dàng thông qua SuperSpeed USB 3.0. Với vỏ nhôm trang nhã – màu Gold, Silver, Black, Metallic Blue hoặc Metallic Red – phù hợp với mọi sở thích và phong cách thời trang của bạn. Hơn thế nữa, phần mềm sao lưu NTI® Backup Now EZ™ dễ sử dụng cho phép bạn thực hiện sao lưu tự động lên tới 2,5 TB dữ liệu. Tốc độ SuperSpeed USB 3.0 Được trang bị chuẩn giao tiếp mới nhất USB 3.0, giúp bạn di chuyển dữ liệu cực nhanh và tiết kiệm nhiều thời gian hơn. Ngoài ra, sản phẩm cũng tương thích với công nghệ USB 2.0 giúp bạn kết nối với các thế hệ máy tính cũ. Thiết kế vỏ nhôm chắc chắn Với vỏ bọc được thiết kế bằng nhôm chắc chắn, ổ cứng di động Toshiba Canvio Alumy được thiết kế rất thời trang và đáp ứng khả năng bảo vệ an toàn cho dữ liệu của bạn. Với bộ cảm biến sốc và công nghệ chống sock, ổ cứng di động Toshiba Canvio Alumy sẽ giữ cho dữ liệu của bạn an toàn trước những va chạm và vết bẩn khi sử dụng. Bảo vệ dữ liệu an toàn Ổ cứng di động Toshiba Canvio Alumy được đi kèm với phầm mềm backup dữ liệu NTI® Backup Now EZ™ giúp bạn hệ thống và quản lý tập tin và sao lưu toàn bộ dữ liệu của bạn. Dễ dàng di chuyển dữ liệu Với ổ cứng di động Toshiba Canvio Alumy, bạn có thể tự động chuyển dữ liệu bằng chức năng sao lưu tự động. Ngoài ra, bạn có thể tự chọn các dữ liệu sao lưu một cách dễ dàng bằng cách kéo và thả các tập tin, sắp xếp lại dữ liệu chỉ trong vài giây. Nhiều màu sắc thời trang Ổ cứng di động Toshiba Canvio Alumy được thiết kế năm màu sắc khác nhau: màu Gold, Silver, Black, Metallic Blue hoặc Metallic Red sẽ đáp ứng mọi phong cách của bạn. Các phiên bản Silver, Black và Gold lý tưởng cho một kiểu dáng đẹp, thanh lịch, trong khi phiên bản Metallic Blue hoặc Metallic Red trông sôi động và sang trọng. Toshiba – Thương hiệu bộ nhớ hàng đầu thế giới Toshiba – tập đoàn điện tử công nghệ cao đa quốc gia, với sản lượng chiếm 25% tổng số lượng thiết bị bộ nhớ được bán ra trên toàn thế giới (thống kê 2016), cho thấy các sản phẩm của Toshiba luôn được khách hàng ở mọi nơi tin tưởng và ưa chuộng. Và điều đặc biệt nhất đó là Toshiba tự sản xuất linh kiện cho chính mình, đảm bảo độ tương thích giữ các linh kiện, tiết kiệm năng lượng tối đa mà vẫn cho hiệu suất cao, và giá thành cực kì thấp. Thương hiệu Toshiba Cổng kết nối USB 3.0","NHASANXUAT":"Toshiba","MODEL":"Canvio Alumy","CHUANGIAOTIEP":"USB 3.0","DUNGLUONG":"2 TB","BAOHANH":"36 tháng"},{"TEN":"Ổ cứng di động Seagate Backup Plus Slim 2TB","GIA":2990000,"HINHANH":"Ổ Cứng Di Động/Seagate-Backup-Plus-Slim-Gift-280x315.jpg","MOTA":"Thông số kĩ thuật Nhà sản xuất Seagate Model Backup Plus Slim (Siêu mỏng) Chuẩn giao tiếp USB 3.0 5Gbps Dung lượng 2 TB Hệ điều hành hỗ trợ Windows, MacOS, Linux,… Tốc độ truyền tải ~120 MB/s Bảo hành 36 tháng Ổ cứng di động Siêu Mỏng Seagate Backup Plus Slim Backup dữ liệu của bạn – Bất cứ lúc nào, bất cứ nơi đâu Ổ cứng di động Seagate Backup Plus Slim được thiết siêu mỏng và rất đơn giản, chỉ với một cú Click là bạn đã có thể bảo vệ và chia sẻ toàn bộ cuộc sống số của bạn. Ổ cứng di động Seagate Backup Plus Slim rất mỏng và có dung lượng lên đến 4TB – rất hoàn hảo, sẽ cùng bạn đi bất kì nơi đâu. – Kiểu dáng đẹp, cứng rắn, thiết kế kim loại nhôm thời trang cho tính di động ở khắp mọi nơi – Sử dụng ứng dụng Seagate Mobile Backup sao lưu trực tiếp từ các thiết bị di động của bạn – Chia sẻ nội dung của bạn giữa các máy tính và máy Mac Dễ dàng quản lý dữ liệu yêu thích của bạn ở bất cứ nơi nào Tất cả hình ảnh, phim và video có thể được sao lưu bằng cách sử dụng phần mềm Dashboard Seagate, bao gồm cả những gì mà bạn đã chia sẻ trên Facebook, Flickr và YouTube. Chỉ cần một cú Click hoặc bạn có thể lên một kế hoạch sao lưu tự động để bảo vệ các tập tin của bạn trên ổ cứng di động Seagate Backup Plus Slim, rất thuận tiện. Plug-and-Play – Tốc độ kết nối cực cao Với chuẩn giao tiếp tốc độ cao USB 3.0 và hỗ trợ kết nối 2.0, cùng với chức năng Plug-and-Play trên PC hoặc Laptop của bạn mà không cần nguồn phụ, sẽ tiết kiệm cho bạn rất nhiều thời gian và mang đến cho bạn sự tiện lợi. Chia sẻ qua Lyve! Ổ cứng di động Seagate Backup Plus Slim có thể chuyển đổi thành một thiết bị sao lưu Lyve, bảo vệ tất cả những dữ liệu của bạn từ tất cả các thiết bị của bạn. Ứng dụng Lyve trên máy tính và các thiết bị di động của bạn sẽ tìm thấy tất cả các hình ảnh và video từ các thiết bị khác nhau và tạo ra một Single. Bạn có thể tạo bộ sưu tập, sắp xếp và quản lý chúng và dễ dàng xem từ điện thoại thông minh hoặc máy tính bảng của bạn. Cùng với tính năng Lyve’s Moments Past, sẽ luôn tự động hiện những kỉ niệm đẹp của bạn mà bạn đã lưu trong thời gian trước. Sản phẩm bao gồm: – Seagate Backup Plus Slim Portable Drive – Seagate Dashboard backup software – 200GB dung lượng lưu trữ OneDrive trong 2 năm miễn phi (Phải được kích hoạt trước 30-06-2017) – 18-inch USB 3.0 cable, Plug-and-Play – Quick start guide Thương hiệu Seagate Cổng kết nối USB 3.0","NHASANXUAT":"Seagate","MODEL":"Backup Plus Slim (Siêu mỏng)","CHUANGIAOTIEP":"USB 3.0 5Gbps","DUNGLUONG":"2 TB","BAOHANH":"36 tháng"},{"TEN":"Ổ cứng di động Western Digital My Passport 2TB (New 2017)","GIA":2990000,"HINHANH":"Ổ Cứng Di Động/MyPassport-Gift1-280x315.jpg","MOTA":"Thông số kĩ thuật Nhà sản xuất Western Digital Model My Passport Chuẩn giao tiếp USB 3.0 Dung lượng 2 TB Hệ điều hành hỗ trợ Windows, MacOS, Linux,… Màu sắc Đen, trắng, đỏ, xanh, cam, vàng Chất liệu Vỏ nhựa cao cấp Bảo hành 3 năm Ổ cứng di động Western Digital My Passport Ổ cứng di động Western Digital My Passport với danh tiếng khắp thế giới về độ tin cậy cho bạn sự yên tâm khi lưu trữ các dữ liệu quan trọng của bạn. Thiết kế mới với nhiều màu sắc theo từng phong cách của bạn, kích thước nhỏ gọn giúp bạn có thể dễ dàng mang nội dung quý giá của bạn ở khắp mọi nơi bạn muốn. Đặc điểm nổi bật: – Tự động sao lưu với phần mềm WD Backup Software đi kèm – Hỗ trợ bảo vệ bằng mật khẩu bảo vệ với mã hóa phần cứng – Dễ dàng sử dụng – Nhiều màu sắc cho bạn lựa chọn – Chất lượng cực tốt với tiêu chuẩn của WD – Dung lượng tối đa lên đến 4TB – Chuẩn giao tiếp USB 3.0; tương thích ngược USB 2.0 Tự động sao lưu với WD Backup Software Được trang bị với phần mềm sao lưu WD Backup Software đi kèm, do đó bạn có thể tự động sao lưu ảnh, video, âm nhạc và tài liệu. Bạn cũng có thể đặt lịch để ổ cứng sẽ tự động sao lưu theo thời gian bạn đã chọn. Bảo vệ dữ liệu bằng mật khẩu Với 256-bit mã hóa phần cứng AES được tích hợp với phần mềm WD Security giúp giữ cho dữ liệu của bạn được riêng tư và an toàn. Dễ dàng khôi phục mật khẩu nhanh chóng trong trường hợp bạn quên mật khẩu. Dễ dàng sử dụng Ổ cứng di động Western Digital My Passport rất dễ dàng sử dụng, chỉ cần bạn cắm vào máy tính và không cần bài bất kì phần mềm hoặc driver nào cả. Ngoài ra, ổ cứng di động Western Digital My Passport đi kèm với tất cả các phần mềm bạn cần để giúp bảo vệ tất cả dữ liệu của bạn, bao gồm cả WD Backup Software và phần mềm WD Security. Thiết kế cổ điển Kiểu dáng đẹp, thiết kế sống động của ổ cứng di động Western Digital My Passport với Logo của hãng được in chìm, nhiều màu sắc đẹp, do đó bạn có thể lựa chọn phù hợp theo phong cách cá nhân, của riêng bạn. Dung lượng cực lớn Với dung lượng lên đến 4TB, bạn có thể mang theo tất cả những gì bạn cần, các hình ảnh, âm nhạc và video mà bạn yêu thích đến bất cứ nơi nào bạn đi… WD – Chất lượng hàng đầu thế giới WD với qui trình sản xuất đòi hỏi các yêu cầu về độ bền, khả năng chống sốc và độ tin cậy lâu dài. Và ổ cứng di động Western Digital My Passport có chế độ bảo hành 2 năm cho bạn sự yên tâm nhất khi sử dụng. Thương hiệu Western Digital Cổng kết nối USB 3.0","NHASANXUAT":"Western Digital","MODEL":"My Passport","CHUANGIAOTIEP":"USB 3.0","DUNGLUONG":"2 TB","BAOHANH":"3 năm"},{"TEN":"Ổ cứng di động 2TB Western Digital My Passport Ultra 2017","GIA":3090000,"HINHANH":"Ổ Cứng Di Động/WD-PU-2017-00-280x315.jpg","MOTA":"Thông số kĩ thuật Nhà sản xuất Western Digital Model My Passport Ultra Chuẩn giao tiếp USB 3.0 Dung lượng 2 TB Hệ điều hành hỗ trợ Windows, MacOS, Linux,… Màu sắc White-Gold ; Black-Gray Chất liệu Vỏ nhôm, nhựa cao cấp Bảo hành 3 năm Ổ cứng di động 4TB Western Digital My Passport Ultra 2017 Phong cách sáng tạo – Tự động sao lưu Ổ cứng di động Western Digital My Passport Ultra 2017 với tốc độ và độ tin cậy cực cao, giúp bạn lưu trữ dữ liệu và mang chúng đến bất kỳ nơi đâu, thiết kế tuyệt đẹp khi kết hợp phong cách kim loại mạnh mẽ bọc phần dưới và sự mềm mại của chất liệu nhựa ở phần trên rất tinh tế. Với rất nhiều không gian lưu trữ lên đến 4tb, phần mềm WD Backup và bảo vệ mật khẩu đi kèm sẽ giúp bảo vệ dữ liệu của bạn được an toàn. Dễ dàng sử dụng, chỉ cần cắm vào và sử dụng. Brilliant Design Ổ cứng di động Western Digital My Passport Ultra 2017 được thiết kế vỏ bọc nhôm nửa dưới và nhựa mờ phần trên, một sự kết hợp độc đáo đem đến sự tinh tế nhất mà chưa thiết bị nào được thiết kế như vậy, cùng với kích thước cực kì nhỏ gọn giúp bạn dễ dàng mang theo bên mình đến bất cứ nơi đâu. Social Media và Cloud Storage Phần mềm WD Discovery đi kèm giúp bạn kết nối với các phương tiện truyền thông xã hội phổ biến và các dịch vụ lưu trữ đám mây như Facebook, Instagram, Dropbox và Google Drive. Bạn sẽ dễ dàng backup dữ liệu về ổ cứng di động Western Digital My Passport Ultra 2017. Tự động sao lưu Ổ cứng di động Western Digital My Passport Ultra 2017 được trang bị phần mềm WD Backup để giúp đảm bảo ảnh, video, nhạc và tài liệu của bạn không bị mất. Bạn có thể đặt lịch tự động Backup dữ liệu từ máy tính vào ổ đĩa. Bảo vệ mật khẩu bằng mã hóa phần cứng Ổ cứng di động Western Digital My Passport Ultra 2017đi kèm với mã hóa phần cứng AES 256-bit với phần mềm WD Security được tích hợp để giúp giữ an toàn cho dữ liệu cá nhân của bạn. Bạn chỉ cần đặt một mật khẩu cá nhân để kích hoạt mã hóa phần cứng và bảo vệ dữ liệu. Độ tin cậy cao nhất Được sản xuất với độ tin cậy tuyệt vời của WD, bạn có thể tin tưởng ổ cứng di động Western Digital My Passport Ultra 2017 sẽ luôn bảo vệ ảnh, video và các tài liệu quan trọng của bạn được an toàn với chế độ hỗ trợ bảo hành phần cứng trong 3 năm. Dễ dàng sử dụng Chỉ cần cắm Ổ cứng di động Western Digital My Passport Ultra 2017 và sử dụng, bạn không cần cài bất kì phần mềm nào khác. Thương hiệu Western Digital Cổng kết nối USB 3.0","NHASANXUAT":"Western Digital","MODEL":"My Passport Ultra","CHUANGIAOTIEP":"USB 3.0","DUNGLUONG":"2 TB","BAOHANH":"3 năm"},{"TEN":"Ổ cứng di động 2TB LaCie Porsche Design Mobile Drive P’9227 USB 3.1 Type-C STFD2000400","GIA":3250000,"HINHANH":"Ổ Cứng Di Động/Porsche-P9227-01-280x315.jpg","MOTA":"Thông số kĩ thuật Nhà sản xuất LaCie Model STFD2000400 Chuẩn giao tiếp – USB 3.1 – USB Type-C Dung lượng 2TB Hệ điều hành hỗ trợ Windows, MacOS, Linux,… Tốc độ ~110 MB/s 5Gbps Chất liệu Nhôm Màu sắc Silver Kích thước 84 × 128 × 10 mm Siêu Mỏng Bảo hành 24 tháng Ổ cứng di động LaCie Porsche Design Mobile Drive Thiết kế bởi Porsche – Chất lượng của LaCie Trong sự hợp tác giữa Porsche và Lacie vào năm 2003, ổ cứng di động LaCie Porsche Design Mobile Drive chứa đựng mọi công nghệ tiên tiến nhất của LaCie với phong cách tinh tế từ Porsche Design. Thiết kế vỏ nhôm siêu mỏng Ổ cứng di động LaCie Porsche Design Mobile Drive là ổ cứng di động mỏng nhất hiện nay với độ dày chỉ 10mm (phiên bản 1TB, 2TB) và 21mm (phiên bản 4TB, 5TB) kết hợp cùng vỏ nhôm cực kỳ cứng cáp giúp bảo vệ những linh kiện bên trong cực tốt, mang phong cách thời trang sang trọng và lịch lãm của một doanh nhân. Nhiều dung lượng cho bạn lựa chọn Ổ cứng di động LaCie Porsche Design Mobile Drive có dung lượng 1Tb, 2TB, 4TB và 5TB. Cho bạn nhiều sự lựa chọn phù hợp với từng nhu cầu. Chuẩn giao tiếp USB Type-C tốc độ cao Giao tiếp USB Type-C Dễ dàng kết nối với cổng USB Type-C hỗ trợ đảo chiều. Kết nối mọi thiết bị Cáp USB Type-C to USB Type-A đi kèm giúp bạn kết nối mọi thiết bị. Tốc độ cực cao Với băng thông 5Gbps, bạn có thể di chuyển dữ liệu cực kỳ nhanh chóng. Được thiết kế cho Macbook® của bạn Ổ cứng di động LaCie Porsche Design Mobile Drive được thiết kế đặc biệt để phù hợp với phong cách của Apple, vỏ bọc nhôm phong cách tinh tế phù hợp với MacBook® mới của bạn. Ngoài ra, sản phẩm hỗ trợ tương thích với Time Machine® để bạn có thể Backup dữ liệu vào ổ đĩa bằng cách sử dụng phần mềm trong Mac. Thương hiệu Lacie Cổng kết nối USB 3.1, USB Type-C","NHASANXUAT":"LaCie","MODEL":"STFD2000400","CHUANGIAOTIEP":"– USB 3.1 – USB Type-C","DUNGLUONG":"2TB","BAOHANH":"24 tháng"}]