[{"TEN":"Ổ cứng di động Portable SSD 240GB USB 3.0 ASMini Apacer","GIA":2300000,"HINHANH":"Ổ cứng SSD Di Động/ASMini-03-280x315.jpg","MOTA":"Thông số kĩ thuật Nhà sản xuất Apacer Model ASMini AP240GASMINI Chuẩn giao tiếp – USB 3.0 5Gbps – USB Type-C Dung lượng 240GB Hệ điều hành hỗ trợ Windows, MacOS, Linux,… Tốc độ Lên đến 400 MB/s Random 4K 60.000 IOPs Hỗ trợ công nghệ ECC Có NAND Flash MLC MTBF 1.000.000 giờ Kích thước 54 x 81 x 6 mm (bằng thẻ ATM) Bảo hành 36 tháng Ổ cứng di động Portable Mini SSD Apacer USB 3.0 ASMini Kích thước siêu nhỏ – Trọng lượng siêu nhẹ – Tốc độ cực cao Ổ cứng di động Portable Mini SSD Apacer USB 3.0 ASMini với thiết kế mỏng, nhẹ và kích thước cực kì nhỏ gọn chỉ bằng tấm thẻ ATM sẽ giúp bạn dễ dàng cho vào túi rất gọn gàng mang theo tất cả mọi dữ liệu đến bất kì nơi đâu bạn muốn. Ngoài ra, với chuẩn giao tiếp cực nhanh SuperSpeed USB 3.1 Gen 1 và Type-C sẽ cho tốc độ đạt đến 450 MB/s. Giúp bạn nhanh chóng chuyển dữ liệu và tiết kiệm rất nhiều thời gian. Kích thước siêu nhỏ gọn Với kích thước 54 x 81 x 6 mm, chỉ bằng tấm thẻ ATM, bạn có thể cho ổ cứng di động Portable Mini SSD Apacer USB 3.0 ASMini vào túi áo và mang đi đến bất kì nơi đâu. Dung lượng lớn Ổ cứng di động Portable Mini SSD Apacer USB 3.0 ASMini với dung lượng lên đến 240GB sẽ giúp bạn mang theo rất nhiều dữ liệu bên mình. Hỗ trợ công nghệ tiên tiến nhất Ổ cứng di động Portable Mini SSD Apacer USB 3.0 ASMini được trang bị những công nghệ tiên tiến nhất như: theo dõi và phát hiện lỗi S.M.A.R.T, Trim và NCQ, công nghệ tự sửa lỗi ECC,… Bảo vệ an toàn cho dữ liệu của bạn. Chuẩn giao tiếp tốc độ cao USB Type-C Ổ cứng di động Portable Mini SSD Apacer USB 3.0 ASMini trang bị cổng giao tiếp băng thông rộng USB Type-C giúp chuyển giao dữ liệu cực nhanh với tốc độ lên đến 400 MB/s, khả năng cắm hai chiều sẽ giúp bạn thoải mái khi sử dụng.  Thương hiệu Apacer Cổng kết nối USB 3.0, USB Type-C Dung lượng ổ cứng 240GB – 250GB – 256GB","NHASANXUAT":"Apacer","MODEL":"ASMini AP240GASMINI","CHUANGIAOTIEP":"– USB 3.0 5Gbps – USB Type-C","DUNGLUONG":"240GB","BAOHANH":"36 tháng"},{"TEN":"Ổ cứng di động External SSD 256GB Western Digital My Passport","GIA":2950000,"HINHANH":"Ổ cứng SSD Di Động/WDMyPassport-SSD-2017-Gift-280x315.jpg","MOTA":"Thông số kĩ thuật Nhà sản xuất Western Digital Model WDBK3E2560PSL Chuẩn giao tiếp – USB 3.1 Gen 2 – USB Type-C Dung lượng 256 GB Hệ điều hành hỗ trợ Windows, MacOS, Linux,… Tốc độ Lên đến 515 MB/s Kích thước 95 x 45 x 10 mm Bảo hành 3 năm Ổ cứng di động External SSD Western Digital My Passport Siêu tốc độ – Siêu bảo mật – Siêu tin cậy Ổ cứng di động External SSD Western Digital My Passport là bộ lưu trữ di động với tốc độ siêu nhanh. Bảo vệ mật khẩu bằng mã hóa phần cứng giúp giữ cho dữ liệu của bạn an toàn. Dễ sử dụng, chống sốc, thiết kế nhỏ gọn và trọng lượng rất nhẹ, dễ dàng mang theo bên mình.– Tốc độ siêu nhanh Ổ cứng di động External SSD Western Digital My Passport có tốc độ nhanh nhất hiện nay với tốc độ lên đến 515 MB/s, sử dụng chuẩn giao tiếp USB Type-C giúp truyền dữ liệu nhanh chóng. Tốc độ của nó mang lại hiệu suất tuyệt vời để giúp chạy các máy ảo và di chuyển dữ liệu trên máy tính của bạn, bạn sẽ tiết kiệm rất nhiều thời gian và làm được nhiều việc hơn.– Mã hóa phần cứng Ổ cứng di động External SSD Western Digital My Passport có thể đặt mật khẩu để bảo vệ dữ liệu bằng mã hóa phần cứng AES 256-bit được tích hợp với phần mềm bảo mật của WD.– Công nghệ mới nhất Được thiết kế cho Mac, PC, và Laptop. Ổ cứng di động External SSD Western Digital My Passport tương thích với cổng USB Type-C và USB Type-A. Với băng thông của USB Type-C sẽ cho tốc độ lên tới 515 MB/s. Ổ cứng di động External SSD Western Digital My Passport tương thích với USB 3.1 Gen 2, USB 3.0, 2.0 và USB-A. WD – Chất lượng tuyệt vời Có thể chịu đựng khi rơi từ độ cao 2 mét mà không bị bất kì vấn đề gì, ổ cứng di động External SSD Western Digital My Passport được thiết kế chống sock tuyệt vời theo tiêu chuẩn của Western Digital để trở thành ổ đĩa lưu trữ chất lượng từ bên trong lẫ vẻ bên ngoài để mang lại hiệu suất đáng tin cậy và độ bền cực cao. Tự động sao lưu Phần mềm WD Backup tích hợp giúp bạn dễ dàng sao lưu các tệp có dung lượng cao vào ổ đĩa hoặc các dịch vụ đám mây của Dropbox và hỗ trợ Apple Time Machine. Dễ dàng sử dụng Ổ cứng di động External SSD Western Digital My Passport chỉ cần cắm và chạy mà không cần phải cài bất kì phần mềm nào. Kích thước nhỏ gọn Ổ cứng di động External SSD Western Digital My Passport kích thước siêu nhỏ gọn với 90 x 45 x 10 mm, bạn có thể cho vào túi vào mang đến bất kì nơi đâu. Thương hiệu Western Digital Cổng kết nối USB 3.1, USB Type-C Dung lượng ổ cứng 240GB – 250GB – 256GB","NHASANXUAT":"Western Digital","MODEL":"WDBK3E2560PSL","CHUANGIAOTIEP":"– USB 3.1 Gen 2 – USB Type-C","DUNGLUONG":"256 GB","BAOHANH":"3 năm"},{"TEN":"Ổ cứng di động 250GB External SSD Samsung T5 USB 3.1 Gen 2","GIA":3290000,"HINHANH":"Ổ cứng SSD Di Động/Samsung-T5-Blue-Gift-280x315.jpg","MOTA":"Thông số kĩ thuật Nhà sản xuất Samsung Model MU-PA250B Chuẩn giao tiếp USB 3.1 Gen 2 Dung lượng 250 GB Hệ điều hành hỗ trợ Windows, MacOS, Linux,… Tốc độ truyền tải 540 MB/s Màu sắc – Alluring Blue: 250GB, 500GB – Deep Black: 1TB, 2TB Bảo hành 36 tháng Ổ cứng di động SSD Samsung Portable T5 Kích thước nhỏ gọn – Tốc độ cực nhanh Ổ cứng di động SSD Samsung Portable T5 là dòng ổ cứng di động được trang bị chíp SSD và công nghệ độc quyền Samsung V-NAND, cho tốc độ truyền dữ liệu lên mức tối đa và mang lại trải nghiệm tuyệt vời nhất. Với thiết kế nhỏ gọn và cứng cáp, cùng mật khẩu bảo vệ bằng phần cứng, ổ cứng di động SSD Samsung Portable T5 thực sự là một thiết bị mà bạn có thể tin tưởng để mang theo và lưu trữ những dữ liệu quan trọng của bạn. Độ tin cậy cực cao Với tốc độ cực nhanh (~540MB/s), vỏ kim loại cực kỳ cứng cáp, bảo mật an toàn, nhỏ gọn và dễ sử dụng – ổ cứng di động SSD Samsung Portable T5 là bộ lưu trữ dữ liệu mới nhất và đáng tin cậy nhất hiện nay. Tốc độ truyền siêu nhanh Với bộ nhớ flash Samsung V-NAND và chuẩn giao tiếp USB 3.1 Gen 2, ổ cứng di động SSD Samsung Portable T5 cung cấp tốc độ truyền lên đến 540 MB/s, nhanh hơn 4,9x so với ổ cứng HDD gắn ngoài thông thường, giúp bạn di chuyển và sao lưu dữ liệu cực nhanh và tiết kiệm rất nhiều thời gian. Thiết kế vỏ kim loại – Phong cách cổ điển Được thiết kế full kim loại từ trên xuống dưới và kiểu dáng Unibody được bo tròn viền xung quanh với kích thước chỉ bằng lòng bàn tay của bạn, cho bạn cảm giác cầm nắm cực kỳ thoải mái và chắc chắn, không bị trượt. Ổ cứng di động SSD Samsung Portable T5 có hai màu khác nhau: màu xanh quyến rũ cho các mẫu 250 GB và 500 GB và màu đen cho mẫu 1 TB và 2 TB. Siêu nhỏ – siêu nhẹ Ổ cứng di động SSD Samsung Portable T5 với kích thước chỉ bằng chiếc thẻ ATM, trọng lượng 51 gram và độ dày chỉ 10mm. Bạn có thể dễ dàng bỏ vào túi áo và mang đi đến bất kì đâu. Khả năng bảo vệ dữ liệu tuyệt đối Ổ cứng di động SSD Samsung Portable T5 không có bộ phận chuyển động cơ quay và thân làm bằng kim loại chắc chắn, do đó nó có thể chịu đựng khi rơi từ độ cao 2 mét. Cùng với bảo vệ mật khẩu tùy chọn với mã hóa AES 256-bit bằng phần cứng giúp dữ liệu cá nhân của bạn an toàn hơn và có chế độ bảo hành 3 năm tại MemoryZone Tương thích mọi thiết bị Ổ cứng di động SSD Samsung Portable T5 tương thích với tất cả các thiết bị từ máy tính cá nhân PC, Laptop, máy Mac, điện thoại thông minh và các thiết bị khác hỗ trợ cổng USB Type-A và Type-C. Ngoài ra sản phẩm đi kèm với cáp USB Type-C to Type-C và cáp USB Type-C to Type-A giúp bạn kết nối với tất cả các thiết bị của bạn. Luôn sẵn sàng mọi lúc, mọi nơi Mang mọi thứ công việc và phương tiện giải trí của bạn. Ổ cứng di động SSD Samsung Portable T5 giúp bạn dễ dàng truy cập dữ liệu của bạn mọi lúc, mọi nơi bằng tất cả các thiết bị mà bạn có thể sử dụng như PC, Laptop, Điện thoại Smartphone, máy tính bảng,… Thương hiệu Samsung Cổng kết nối USB 3.1, USB Type-C","NHASANXUAT":"Samsung","MODEL":"MU-PA250B","CHUANGIAOTIEP":"USB 3.1 Gen 2","DUNGLUONG":"250 GB","BAOHANH":"36 tháng"},{"TEN":"Ổ cứng di động Portable SSD 500GB USB 3.0 Toshiba X10","GIA":5050000,"HINHANH":"Ổ cứng SSD Di Động/Toshiba-Portable-X10-Gift-280x315.jpg","MOTA":"Thông số kĩ thuật Nhà sản xuất Toshiba Model X10 Chuẩn giao tiếp USB 3.0 5Gbps Dung lượng 500GB Hệ điều hành hỗ trợ Windows, MacOS, Linux,… Tốc độ Lên đến 400 MB/s Hỗ trợ công nghệ ECC Có Kích thước 80 x 49.5 x 9.5mm (bằng thẻ ATM) Bảo hành 36 tháng Ổ cứng di động siêu nhỏ Portable SSD Toshiba USB 3.0 X10 Kích thước siêu nhỏ – Trọng lượng siêu nhẹ – Tốc độ cực cao Ổ cứng di động Portable SSD Toshiba USB 3.0 X10 với thiết kế mỏng, nhẹ và kích thước cực kì nhỏ gọn chỉ bằng tấm thẻ ATM sẽ giúp bạn dễ dàng cho vào túi rất gọn gàng mang theo tất cả mọi dữ liệu đến bất kì nơi đâu bạn muốn. Ngoài ra, với chuẩn giao tiếp cực nhanh SuperSpeed USB 3.0 sẽ cho tốc độ đạt đến 400 MB/s. Giúp bạn nhanh chóng chuyển dữ liệu và tiết kiệm rất nhiều thời gian. Kích thước siêu nhỏ gọn Với kích thước 50 x 80 x 8 mm, chỉ bằng tấm thẻ ATM, bạn có thể cho ổ cứng di động Portable SSD Toshiba USB 3.0 X10 vào túi áo và mang đi đến bất kì nơi đâu. Dung lượng lớn Ổ cứng di động Portable SSD Toshiba USB 3.0 X10 với dung lượng lên đến 500GB sẽ giúp bạn mang theo rất nhiều dữ liệu bên mình. Hỗ trợ công nghệ tiên tiến nhất Ổ cứng di động Portable SSD Toshiba USB 3.0 X10 được trang bị những công nghệ tiên tiến nhất như: theo dõi và phát hiện lỗi S.M.A.R.T, Trim và NCQ, công nghệ tự sửa lỗi ECC,… Bảo vệ an toàn cho dữ liệu của bạn. Chuẩn giao tiếp tốc độ cao USB 3.0 Ổ cứng di động Portable SSD Toshiba USB 3.0 X10 trang bị cổng giao tiếp băng thông rộng USB 3.0 giúp chuyển giao dữ liệu cực nhanh với tốc độ lên đến 400 MB/s, tiết kiệm cho bạn rất nhiều thời gian. Thương hiệu Toshiba Cổng kết nối USB 3.0 Dung lượng ổ cứng 480GB – 500GB – 512GB","NHASANXUAT":"Toshiba","MODEL":"X10","CHUANGIAOTIEP":"USB 3.0 5Gbps","DUNGLUONG":"500GB","BAOHANH":"36 tháng"},{"TEN":"Ổ cứng di động 500GB External SSD Samsung T5 USB 3.1 Gen 2","GIA":5390000,"HINHANH":"Ổ cứng SSD Di Động/Samsung-T5-Blue-Gift-280x315.jpg","MOTA":"Thông số kĩ thuật Nhà sản xuất Samsung Model MU-PA500B Chuẩn giao tiếp USB 3.1 Gen 2 Dung lượng 500 GB Hệ điều hành hỗ trợ Windows, MacOS, Linux,… Tốc độ đọc 540 MB/s Tốc độ ghi 515 MB/s Màu sắc – Alluring Blue: 250GB, 500GB – Deep Black: 1TB, 2TB Bảo hành 36 tháng Ổ cứng di động SSD Samsung Portable T5 Kích thước nhỏ gọn – Tốc độ cực nhanh Ổ cứng di động SSD Samsung Portable T5 là dòng ổ cứng di động được trang bị chíp SSD và công nghệ độc quyền Samsung V-NAND, cho tốc độ truyền dữ liệu lên mức tối đa và mang lại trải nghiệm tuyệt vời nhất. Với thiết kế nhỏ gọn và cứng cáp, cùng mật khẩu bảo vệ bằng phần cứng, ổ cứng di động SSD Samsung Portable T5 thực sự là một thiết bị mà bạn có thể tin tưởng để mang theo và lưu trữ những dữ liệu quan trọng của bạn. Độ tin cậy cực cao Với tốc độ cực nhanh (~540MB/s), vỏ kim loại cực kỳ cứng cáp, bảo mật an toàn, nhỏ gọn và dễ sử dụng – ổ cứng di động SSD Samsung Portable T5 là bộ lưu trữ dữ liệu mới nhất và đáng tin cậy nhất hiện nay. Tốc độ truyền siêu nhanh Với bộ nhớ flash Samsung V-NAND và chuẩn giao tiếp USB 3.1 Gen 2, ổ cứng di động SSD Samsung Portable T5 cung cấp tốc độ truyền lên đến 540 MB/s, nhanh hơn 4,9x so với ổ cứng HDD gắn ngoài thông thường, giúp bạn di chuyển và sao lưu dữ liệu cực nhanh và tiết kiệm rất nhiều thời gian. Thiết kế vỏ kim loại – Phong cách cổ điển Được thiết kế full kim loại từ trên xuống dưới và kiểu dáng Unibody được bo tròn viền xung quanh với kích thước chỉ bằng lòng bàn tay của bạn, cho bạn cảm giác cầm nắm cực kỳ thoải mái và chắc chắn, không bị trượt. Ổ cứng di động SSD Samsung Portable T5 có hai màu khác nhau: màu xanh quyến rũ cho các mẫu 250 GB và 500 GB và màu đen cho mẫu 1 TB và 2 TB. Siêu nhỏ – siêu nhẹ Ổ cứng di động SSD Samsung Portable T5 với kích thước chỉ bằng chiếc thẻ ATM, trọng lượng 51 gram và độ dày chỉ 10mm. Bạn có thể dễ dàng bỏ vào túi áo và mang đi đến bất kì đâu. Khả năng bảo vệ dữ liệu tuyệt đối Ổ cứng di động SSD Samsung Portable T5 không có bộ phận chuyển động cơ quay và thân làm bằng kim loại chắc chắn, do đó nó có thể chịu đựng khi rơi từ độ cao 2 mét. Cùng với bảo vệ mật khẩu tùy chọn với mã hóa AES 256-bit bằng phần cứng giúp dữ liệu cá nhân của bạn an toàn hơn và có chế độ bảo hành 3 năm tại MemoryZone Tương thích mọi thiết bị Ổ cứng di động SSD Samsung Portable T5 tương thích với tất cả các thiết bị từ máy tính cá nhân PC, Laptop, máy Mac, điện thoại thông minh và các thiết bị khác hỗ trợ cổng USB Type-A và Type-C. Ngoài ra sản phẩm đi kèm với cáp USB Type-C to Type-C và cáp USB Type-C to Type-A giúp bạn kết nối với tất cả các thiết bị của bạn. Luôn sẵn sàng mọi lúc, mọi nơi Mang mọi thứ công việc và phương tiện giải trí của bạn. Ổ cứng di động SSD Samsung Portable T5 giúp bạn dễ dàng truy cập dữ liệu của bạn mọi lúc, mọi nơi bằng tất cả các thiết bị mà bạn có thể sử dụng như PC, Laptop, Điện thoại Smartphone, máy tính bảng,… Thương hiệu Samsung Cổng kết nối USB 3.1, USB Type-C","NHASANXUAT":"Samsung","MODEL":"MU-PA500B","CHUANGIAOTIEP":"USB 3.1 Gen 2","DUNGLUONG":"500 GB","BAOHANH":"36 tháng"},{"TEN":"Ổ cứng di động External SSD 512GB Western Digital My Passport","GIA":5450000,"HINHANH":"Ổ cứng SSD Di Động/WDMyPassport-SSD-2017-Gift-280x315.jpg","MOTA":"Thông số kĩ thuật Nhà sản xuất Western Digital Model WDBK3E5120PSL Chuẩn giao tiếp – USB 3.1 Gen 2 – USB Type-C Dung lượng 512 GB Hệ điều hành hỗ trợ Windows, MacOS, Linux,… Tốc độ Lên đến 515 MB/s Kích thước 95 x 45 x 10 mm Bảo hành 3 năm Ổ cứng di động External SSD Western Digital My Passport Siêu tốc độ – Siêu bảo mật – Siêu tin cậy Ổ cứng di động External SSD Western Digital My Passport là bộ lưu trữ di động với tốc độ siêu nhanh. Bảo vệ mật khẩu bằng mã hóa phần cứng giúp giữ cho dữ liệu của bạn an toàn. Dễ sử dụng, chống sốc, thiết kế nhỏ gọn và trọng lượng rất nhẹ, dễ dàng mang theo bên mình.– Tốc độ siêu nhanh Ổ cứng di động External SSD Western Digital My Passport có tốc độ nhanh nhất hiện nay với tốc độ lên đến 515 MB/s, sử dụng chuẩn giao tiếp USB Type-C giúp truyền dữ liệu nhanh chóng. Tốc độ của nó mang lại hiệu suất tuyệt vời để giúp chạy các máy ảo và di chuyển dữ liệu trên máy tính của bạn, bạn sẽ tiết kiệm rất nhiều thời gian và làm được nhiều việc hơn. – Mã hóa phần cứng Ổ cứng di động External SSD Western Digital My Passport có thể đặt mật khẩu để bảo vệ dữ liệu bằng mã hóa phần cứng AES 256-bit được tích hợp với phần mềm bảo mật của WD. – Công nghệ mới nhất Được thiết kế cho Mac, PC, và Laptop. Ổ cứng di động External SSD Western Digital My Passport tương thích với cổng USB Type-C và USB Type-A. Với băng thông của USB Type-C sẽ cho tốc độ lên tới 515 MB/s. Ổ cứng di động External SSD Western Digital My Passport tương thích với USB 3.1 Gen 2, USB 3.0, 2.0 và USB-A. WD – Chất lượng tuyệt vời Có thể chịu đựng khi rơi từ độ cao 2 mét mà không bị bất kì vấn đề gì, ổ cứng di động External SSD Western Digital My Passport được thiết kế chống sock tuyệt vời theo tiêu chuẩn của Western Digital để trở thành ổ đĩa lưu trữ chất lượng từ bên trong lẫ vẻ bên ngoài để mang lại hiệu suất đáng tin cậy và độ bền cực cao. Tự động sao lưu Phần mềm WD Backup tích hợp giúp bạn dễ dàng sao lưu các tệp có dung lượng cao vào ổ đĩa hoặc các dịch vụ đám mây của Dropbox và hỗ trợ Apple Time Machine. Dễ dàng sử dụng Ổ cứng di động External SSD Western Digital My Passport chỉ cần cắm và chạy mà không cần phải cài bất kì phần mềm nào. Kích thước nhỏ gọn Ổ cứng di động External SSD Western Digital My Passport kích thước siêu nhỏ gọn với 90 x 45 x 10 mm, bạn có thể cho vào túi vào mang đến bất kì nơi đâu. Thương hiệu Western Digital Cổng kết nối USB 3.1, USB Type-C Dung lượng ổ cứng 480GB – 500GB – 512GB","NHASANXUAT":"Western Digital","MODEL":"WDBK3E5120PSL","CHUANGIAOTIEP":"– USB 3.1 Gen 2 – USB Type-C","DUNGLUONG":"512 GB","BAOHANH":"3 năm"},{"TEN":"Ổ cứng di động External SSD Sandisk Extreme 900 480GB USB 3.1 Gen 2","GIA":7500000,"HINHANH":"Ổ cứng SSD Di Động/EX-900-01-280x315.jpg","MOTA":"Thông số kĩ thuật Nhà sản xuất Sandisk Model External SSD (SDSSDEX2-480-G25) Chuẩn giao tiếp USB 3.1 ; USB Type-C (Tương thích ngược USB 2.0; 1.0) Dung lượng 480GB Kích thước 133.35 x 82.55 x 17.78 mm Hệ điều hành hỗ trợ Windows, MacOS, Linux,… Tốc độ đọc ~ 850MB/s Tốc độ ghi ~ 850MB/s Bảo hành 36 tháng Ổ cứng di động External SSD SanDisk Extreme 900 Ổ cứng di động External SSD SanDisk Extreme 900 được trang bị tốc độ đọc ghi siêu cao lên đến 850MB/s, hiệu suất gấp 9 lần so với một ổ đĩa cứng gắn ngoài giúp bạn di chuyển dữ liệu chỉ trong vài giây. Ổ cứng di động External SSD SanDisk Extreme 900 có tốc độ truy cập nhanh gấp 35 so với một ổ đĩa cứng gắn ngoài thông thường, vì thế bạn có thể làm việc trực tiếp trên ổ đĩa nhanh hơn. Với công nghệ SSD không có bộ phận chuyển động cơ quay giúp độ bền của SSD được gia tăng rất cao khi không tỏa nhiều nhiệt và chống sock cực tốt. Đi kèm với sản phẩm là phần mềm SanDisk SecureAccess giúp mã hóa để bảo mật các tập tin riêng tư của bạn. Tất cả các sản phẩm của SanDisk được sản xuất với tiêu chuẩn cao nhất và đã được thử nghiệm chặt chẽ. Bạn có thể tự tin vào chất lượng, hiệu suất vượt trội và độ tin cậy của tất cả các sản phẩm SanDisk. Tốc độ đọc và ghi siêu cao lên đến 850MB/s Với hiệu năng lên đến gấp 9 lần tốc độ của một ổ đĩa cứng gắn ngoài thông thường và gấp hai lần tốc độ của các dòng SSD di động khác, ổ cứng di động External SSD SanDisk Extreme 900 giảm đáng kể thời gian chờ đợi, đẩy nhanh tiến trình công việc của bạn giúp bạn tiết kiệm rất nhiều thời gian và làm được nhiều việc hơn. Dung lượng cao đáp ứng mọi nhu cầu Cho dù bạn đang quay phim và biên tập Video 4K Ultra HD, hình ảnh chất lượng cao, hay tạo các file đồ họa lớn,… Với dung lượng lên tới 1.92TB, ổ cứng di động External SSD SanDisk Extreme 900 có thể đáp ứng mọi nhu cầu của bạn. Độ bền cực cao Được thiết kế với một hệ thống đệm lót bằng cao su có độ đàn hồi tốt nhất và đặc biệt không sử dụng hệ thống cơ quay, ổ cứng di động External SSD SanDisk Extreme 900 chống shock và chống rung cực tốt giúp bảo về an toàn cho dữ liệu của bạn. Phần mềm SanDisk SecureAccess – Bảo vệ dữ liệu riêng tư của bạn Với phần mềm đi kèm Sandisk SecureAccess bạn có thể tạo một thư mục riêng trên ổ đĩa của bạn và mã hóa nó với 128-bit AES, sau đó bạn có thể đặt mật khẩu để bảo vệ những tập tin quan trọng của bạn một cách an toàn. Giúp bạn làm việc hiệu quả hơn Với công nghệ SSD bên trong, ổ cứng di động External SSD SanDisk Extreme 900 hoạt động mát mẻ hơn, yên tĩnh hơn, và hiệu quả hơn so với các ổ đĩa cứng HDD thông thường. Chuẩn USB 3.1 mới nhất Ổ cứng di động External SSD SanDisk Extreme 900 được trang bị chuẩn giao tiếp USB 3.1 mới nhất và không cần phải sử dụng dây bổ sung và nguồn cung cấp điện rời, rất gọn gàng và tiện lợi. Thêm vào đó, sản phẩm được đi kèm với 1 sợi dây chuẩn Type-C, giúp bạn có thể làm việc với nhiều chuẩn giao tiếp. Thương hiệu Sandisk Cổng kết nối USB 3.1, USB Type-C Dung lượng ổ cứng 480GB – 500GB – 512GB","NHASANXUAT":"Sandisk","MODEL":"External SSD (SDSSDEX2-480-G25)","CHUANGIAOTIEP":"USB 3.1 ; USB Type-C (Tương thích ngược USB 2.0; 1.0)","DUNGLUONG":"480GB","BAOHANH":"36 tháng"},{"TEN":"Ổ cứng di động SSD 500GB Western Digital My Passport Wireless WDBAMJ5000AGY","GIA":8590000,"HINHANH":"Ổ cứng SSD Di Động/WD-My-Passport-Wireless-SSD-01-280x315.jpg","MOTA":"Thông số kĩ thuật Nhà sản xuất Western Digital Model My Passport Wireless WDBAMJ5000AGY Chuẩn giao tiếp – USB 3.0 – USB 2.0 Felmale (đọc đầu đọc thẻ nhớ và USB) – Wireless 802.11ac/n – SD Card Reader 3.0 Dung lượng 500 GB Pin Li-ion, thời gian sử dụng có thể lên đến 10h Phần mềm hỗ trợ trên thiết bị di động MyCloud (có sẵn trên Appstore, Google Play,…) Hệ điều hành hỗ trợ MacOS, IOS, Android, WindowsPhone,… Bảo hành 36 tháng Ổ cứng di động SSD Western Digital My Passport Wireless Ổ cứng di động SSD Western Digital My Passport Wireless là một ổ đĩa di động giúp bảo vệ ảnh và video được chụp trên máy ảnh và máy Fly-Cam. Nút sao chụp một lần cho phép bạn sao lưu ảnh và video bằng đầu đọc thẻ SD ™ hoặc cổng USB tích hợp mà không cần máy tính xách tay hoặc phần mềm. Hỗ trợ đọc thẻ nhớ chuẩn SD Đầu đọc thẻ nhớ SD 3.0 được tích hợp trên ổ cứng di động SSD Western Digital My Passport Wireless với tốc độ đọc lên đến 65MB/s và nút One-Touch Button sẽ giúp bạn dễ dàng sao lưu ảnh và video từ thẻ nhớ SD sang ổ cứng mà không cần máy tính hoặc sử dụng bất kì phần mềm nào. Công nghệ lưu trữ của SSD và khả năng chống sốc – cho độ bền tuyệt đối Với một ổ SSD bên trong và lớp vỏ Silicon được gia cố để bảo bên ngoài, tất cả các linh kiện bên trong hoàn toàn được bảo vệ khỏi những cú sốc, các chấn động bên ngoài và khả năng chịu được độ rơi lên đến 1 mét, ngay cả khi ổ đĩa đang hoạt động. Tốc độ SSD siêu nhanh Ổ cứng di động SSD Western Digital My Passport Wireless có tốc độ truy cập siêu nhanh (lên tới 390MB/s tốc độ đọc) khi sử dụng cổng USB 3.0 để di chuyển các tập tin. All-Day Battery Life Ổ cứng di động SSD Western Digital My Passport Wireless trang bị Pin bên trong với thời lượng sử dụng lên đến 10 giờ liên tục. Giúp bạn thoải mái sử dụng cả ngày. Truy cập không dây và 4K Streaming Ổ cứng di động SSD Western Digital My Passport Wireless hỗ trợ phát WiFi tốc độ cao chuẩn mới nhất 802.11ac/n giúp bạn có thể kết nối không dây vào ổ đĩa của mình để truy cập và xem các bức ảnh đã lưu hoặc Streaming Video 4K trực tiếp sang điện thoại hoặc máy tính bảng của bạn bằng ứng dụng My Cloud. Sử dụng các ứng dụng của bên thứ ba, FiLMiC Pro, để chụp và lưu lại cảnh quay trực tiếp vào ổ đĩa, hoặc LumaFusion để chỉnh sửa video trong lĩnh vực này. Built-In USB 2.0 Port Một cổng USB 2.0 Female tiện lợi và nút One-Touch Button cho phép bạn dễ dàng chuyển các tập tin từ đầu đọc thẻ hoặc các thiết bị lưu trữ sử dụng cổng USB bên ngoài. Truy cập support.wd.com để xem danh sách đầy đủ các đầu đọc thẻ tương thích. Built-In Power Bank – Hỗ trợ sạc điện thoại Điện thoại bạn hết pin bất chợt trên đường đi? Không vấn đề gì. Ổ cứng di động SSD Western Digital My Passport Wireless hỗ trợ sạc điện thoại, máy ảnh Action Cam của bạn và các thiết bị di động khác. Với dung lượng lên đến 6.700mAh rất tiện dụng và dòng cung cấp lên đến 1.5A cho bạn sạc điện thoại thoải mái. Hỗ trợ hình ảnh File RAW Ổ cứng di động SSD Western Digital My Passport Wireless hỗ trợ xem trước các ảnh RAW trên điện thoại hoặc máy tính bảng của bạn. Lưu Video trực tiếp trên ổ cứng FiLMiC Pro là một ứng dụng quay video tiên tiến cho điện thoại di động được các chuyên gia trên toàn thế giới sử dụng. Nó có thể kết nối với ổ cứng di động SSD Western Digital My Passport Wireless để ghi các đoạn phim trực tiếp vào ổ đĩa khi bạn quay phim để tiết kiệm không gian trên điện thoại của bạn. Bạn có thể tải ứng dụng trên Google Play hoặc Apple App Store. Chỉnh sửa ảnh ở bất cứ nơi đâu LumaFusion là ứng dụng chỉnh sửa video và tạo hiệu ứng Video chuyên nghiệp cho iPhone và iPad, cho phép bạn thoải mái sáng tạo chỉnh sửa hình ảnh, chỉnh sửa màu, điều chỉnh âm thanh và nhiều hơn thế nữa. Kết nối với My Passport Wireless SSD để nhập nội dung trực tiếp vào ứng dụng LumaFusion để chỉnh sửa bất cứ nơi nào bạn muốn. Tải ứng dụng trên Apple App Store. Thương hiệu Western Digital Cổng kết nối Wireless, USB 3.0","NHASANXUAT":"Western Digital","MODEL":"My Passport Wireless WDBAMJ5000AGY","CHUANGIAOTIEP":"– USB 3.0 – USB 2.0 Felmale (đọc đầu đọc thẻ nhớ và USB) – Wireless 802.11ac/n – SD Card Reader 3.0","DUNGLUONG":"500 GB","BAOHANH":"36 tháng"},{"TEN":"Ổ cứng di động External SSD 1TB Western Digital My Passport","GIA":9950000,"HINHANH":"Ổ cứng SSD Di Động/WDMyPassport-SSD-2017-Gift-280x315.jpg","MOTA":"Thông số kĩ thuật Nhà sản xuất Western Digital Model WDBK3E0010PSL Chuẩn giao tiếp – USB 3.1 Gen 2 – USB Type-C Dung lượng 1 TB Hệ điều hành hỗ trợ Windows, MacOS, Linux,… Tốc độ Lên đến 515 MB/s Kích thước 95 x 45 x 10 mm Bảo hành 3 năm Ổ cứng di động External SSD Western Digital My Passport Siêu tốc độ – Siêu bảo mật – Siêu tin cậy Ổ cứng di động External SSD Western Digital My Passport là bộ lưu trữ di động với tốc độ siêu nhanh. Bảo vệ mật khẩu bằng mã hóa phần cứng giúp giữ cho dữ liệu của bạn an toàn. Dễ sử dụng, chống sốc, thiết kế nhỏ gọn và trọng lượng rất nhẹ, dễ dàng mang theo bên mình.– Tốc độ siêu nhanh Ổ cứng di động External SSD Western Digital My Passport có tốc độ nhanh nhất hiện nay với tốc độ lên đến 515 MB/s, sử dụng chuẩn giao tiếp USB Type-C giúp truyền dữ liệu nhanh chóng. Tốc độ của nó mang lại hiệu suất tuyệt vời để giúp chạy các máy ảo và di chuyển dữ liệu trên máy tính của bạn, bạn sẽ tiết kiệm rất nhiều thời gian và làm được nhiều việc hơn. – Mã hóa phần cứng Ổ cứng di động External SSD Western Digital My Passport có thể đặt mật khẩu để bảo vệ dữ liệu bằng mã hóa phần cứng AES 256-bit được tích hợp với phần mềm bảo mật của WD. – Công nghệ mới nhất Được thiết kế cho Mac, PC, và Laptop. Ổ cứng di động External SSD Western Digital My Passport tương thích với cổng USB Type-C và USB Type-A. Với băng thông của USB Type-C sẽ cho tốc độ lên tới 515 MB/s. Ổ cứng di động External SSD Western Digital My Passport tương thích với USB 3.1 Gen 2, USB 3.0, 2.0 và USB-A. WD – Chất lượng tuyệt vời Có thể chịu đựng khi rơi từ độ cao 2 mét mà không bị bất kì vấn đề gì, ổ cứng di động External SSD Western Digital My Passport được thiết kế chống sock tuyệt vời theo tiêu chuẩn của Western Digital để trở thành ổ đĩa lưu trữ chất lượng từ bên trong lẫ vẻ bên ngoài để mang lại hiệu suất đáng tin cậy và độ bền cực cao. Tự động sao lưu Phần mềm WD Backup tích hợp giúp bạn dễ dàng sao lưu các tệp có dung lượng cao vào ổ đĩa hoặc các dịch vụ đám mây của Dropbox và hỗ trợ Apple Time Machine. Dễ dàng sử dụng Ổ cứng di động External SSD Western Digital My Passport chỉ cần cắm và chạy mà không cần phải cài bất kì phần mềm nào. Kích thước nhỏ gọn Ổ cứng di động External SSD Western Digital My Passport kích thước siêu nhỏ gọn với 90 x 45 x 10 mm, bạn có thể cho vào túi vào mang đến bất kì nơi đâu. Thương hiệu Western Digital Cổng kết nối USB 3.1, USB Type-C Dung lượng ổ cứng 960GB – 1TB","NHASANXUAT":"Western Digital","MODEL":"WDBK3E0010PSL","CHUANGIAOTIEP":"– USB 3.1 Gen 2 – USB Type-C","DUNGLUONG":"1 TB","BAOHANH":"3 năm"},{"TEN":"Ổ cứng di động 1TB External SSD Samsung T5 USB 3.1 Gen 2","GIA":10490000,"HINHANH":"Ổ cứng SSD Di Động/Samsung-T5-Black-02-280x315.jpg","MOTA":"Thông số kĩ thuật Nhà sản xuất Samsung Model MU-PA1T0B Chuẩn giao tiếp USB 3.1 Gen 2 Dung lượng 1 TB Hệ điều hành hỗ trợ Windows, MacOS, Linux,… Tốc độ đọc 540 MB/s Tốc độ ghi 515 MB/s Màu sắc – Alluring Blue: 250GB, 500GB – Deep Black: 1TB, 2TB Bảo hành 36 tháng Ổ cứng di động SSD Samsung Portable T5 Kích thước nhỏ gọn – Tốc độ cực nhanh Ổ cứng di động SSD Samsung Portable T5 là dòng ổ cứng di động được trang bị chíp SSD và công nghệ độc quyền Samsung V-NAND, cho tốc độ truyền dữ liệu lên mức tối đa và mang lại trải nghiệm tuyệt vời nhất. Với thiết kế nhỏ gọn và cứng cáp, cùng mật khẩu bảo vệ bằng phần cứng, ổ cứng di động SSD Samsung Portable T5 thực sự là một thiết bị mà bạn có thể tin tưởng để mang theo và lưu trữ những dữ liệu quan trọng của bạn. Độ tin cậy cực cao Với tốc độ cực nhanh (~540MB/s), vỏ kim loại cực kỳ cứng cáp, bảo mật an toàn, nhỏ gọn và dễ sử dụng – ổ cứng di động SSD Samsung Portable T5 là bộ lưu trữ dữ liệu mới nhất và đáng tin cậy nhất hiện nay. Tốc độ truyền siêu nhanh Với bộ nhớ flash Samsung V-NAND và chuẩn giao tiếp USB 3.1 Gen 2, ổ cứng di động SSD Samsung Portable T5 cung cấp tốc độ truyền lên đến 540 MB/s, nhanh hơn 4,9x so với ổ cứng HDD gắn ngoài thông thường, giúp bạn di chuyển và sao lưu dữ liệu cực nhanh và tiết kiệm rất nhiều thời gian. Thiết kế vỏ kim loại – Phong cách cổ điển Được thiết kế full kim loại từ trên xuống dưới và kiểu dáng Unibody được bo tròn viền xung quanh với kích thước chỉ bằng lòng bàn tay của bạn, cho bạn cảm giác cầm nắm cực kỳ thoải mái và chắc chắn, không bị trượt. Ổ cứng di động SSD Samsung Portable T5 có hai màu khác nhau: màu xanh quyến rũ cho các mẫu 250 GB và 500 GB và màu đen cho mẫu 1 TB và 2 TB. Siêu nhỏ – siêu nhẹ Ổ cứng di động SSD Samsung Portable T5 với kích thước chỉ bằng chiếc thẻ ATM, trọng lượng 51 gram và độ dày chỉ 10mm. Bạn có thể dễ dàng bỏ vào túi áo và mang đi đến bất kì đâu. Khả năng bảo vệ dữ liệu tuyệt đối Ổ cứng di động SSD Samsung Portable T5 không có bộ phận chuyển động cơ quay và thân làm bằng kim loại chắc chắn, do đó nó có thể chịu đựng khi rơi từ độ cao 2 mét. Cùng với bảo vệ mật khẩu tùy chọn với mã hóa AES 256-bit bằng phần cứng giúp dữ liệu cá nhân của bạn an toàn hơn và có chế độ bảo hành 3 năm tại MemoryZone Tương thích mọi thiết bị Ổ cứng di động SSD Samsung Portable T5 tương thích với tất cả các thiết bị từ máy tính cá nhân PC, Laptop, máy Mac, điện thoại thông minh và các thiết bị khác hỗ trợ cổng USB Type-A và Type-C. Ngoài ra sản phẩm đi kèm với cáp USB Type-C to Type-C và cáp USB Type-C to Type-A giúp bạn kết nối với tất cả các thiết bị của bạn. Luôn sẵn sàng mọi lúc, mọi nơi Mang mọi thứ công việc và phương tiện giải trí của bạn. Ổ cứng di động SSD Samsung Portable T5 giúp bạn dễ dàng truy cập dữ liệu của bạn mọi lúc, mọi nơi bằng tất cả các thiết bị mà bạn có thể sử dụng như PC, Laptop, Điện thoại Smartphone, máy tính bảng,… Thương hiệu Samsung Cổng kết nối USB 3.1, USB Type-C","NHASANXUAT":"Samsung","MODEL":"MU-PA1T0B","CHUANGIAOTIEP":"USB 3.1 Gen 2","DUNGLUONG":"1 TB","BAOHANH":"36 tháng"},{"TEN":"Ổ cứng di động SSD 1TB Western Digital My Passport Wireless WDBAMJ0010BGY","GIA":13590000,"HINHANH":"Ổ cứng SSD Di Động/WD-My-Passport-Wireless-SSD-01-280x315.jpg","MOTA":"Thông số kĩ thuật Nhà sản xuất Western Digital Model My Passport Wireless WDBAMJ0010BGY Chuẩn giao tiếp – USB 3.0 – USB 2.0 Felmale (đọc đầu đọc thẻ nhớ và USB) – Wireless 802.11ac/n – SD Card Reader 3.0 Dung lượng 1 TB Pin Li-ion, thời gian sử dụng có thể lên đến 10h Phần mềm hỗ trợ trên thiết bị di động MyCloud (có sẵn trên Appstore, Google Play,…) Hệ điều hành hỗ trợ MacOS, IOS, Android, WindowsPhone,… Bảo hành 36 tháng Ổ cứng di động SSD Western Digital My Passport Wireless Ổ cứng di động SSD Western Digital My Passport Wireless là một ổ đĩa di động giúp bảo vệ ảnh và video được chụp trên máy ảnh và máy Fly-Cam. Nút sao chụp một lần cho phép bạn sao lưu ảnh và video bằng đầu đọc thẻ SD ™ hoặc cổng USB tích hợp mà không cần máy tính xách tay hoặc phần mềm. Hỗ trợ đọc thẻ nhớ chuẩn SD Đầu đọc thẻ nhớ SD 3.0 được tích hợp trên ổ cứng di động SSD Western Digital My Passport Wireless với tốc độ đọc lên đến 65MB/s và nút One-Touch Button sẽ giúp bạn dễ dàng sao lưu ảnh và video từ thẻ nhớ SD sang ổ cứng mà không cần máy tính hoặc sử dụng bất kì phần mềm nào. Công nghệ lưu trữ của SSD và khả năng chống sốc – cho độ bền tuyệt đối Với một ổ SSD bên trong và lớp vỏ Silicon được gia cố để bảo bên ngoài, tất cả các linh kiện bên trong hoàn toàn được bảo vệ khỏi những cú sốc, các chấn động bên ngoài và khả năng chịu được độ rơi lên đến 1 mét, ngay cả khi ổ đĩa đang hoạt động. Tốc độ SSD siêu nhanh Ổ cứng di động SSD Western Digital My Passport Wireless có tốc độ truy cập siêu nhanh (lên tới 390MB/s tốc độ đọc) khi sử dụng cổng USB 3.0 để di chuyển các tập tin. All-Day Battery Life Ổ cứng di động SSD Western Digital My Passport Wireless trang bị Pin bên trong với thời lượng sử dụng lên đến 10 giờ liên tục. Giúp bạn thoải mái sử dụng cả ngày. Truy cập không dây và 4K Streaming Ổ cứng di động SSD Western Digital My Passport Wireless hỗ trợ phát WiFi tốc độ cao chuẩn mới nhất 802.11ac/n giúp bạn có thể kết nối không dây vào ổ đĩa của mình để truy cập và xem các bức ảnh đã lưu hoặc Streaming Video 4K trực tiếp sang điện thoại hoặc máy tính bảng của bạn bằng ứng dụng My Cloud. Sử dụng các ứng dụng của bên thứ ba, FiLMiC Pro, để chụp và lưu lại cảnh quay trực tiếp vào ổ đĩa, hoặc LumaFusion để chỉnh sửa video trong lĩnh vực này. Built-In USB 2.0 Port Một cổng USB 2.0 Female tiện lợi và nút One-Touch Button cho phép bạn dễ dàng chuyển các tập tin từ đầu đọc thẻ hoặc các thiết bị lưu trữ sử dụng cổng USB bên ngoài. Truy cập support.wd.com để xem danh sách đầy đủ các đầu đọc thẻ tương thích. Built-In Power Bank – Hỗ trợ sạc điện thoại Điện thoại bạn hết pin bất chợt trên đường đi? Không vấn đề gì. Ổ cứng di động SSD Western Digital My Passport Wireless hỗ trợ sạc điện thoại, máy ảnh Action Cam của bạn và các thiết bị di động khác. Với dung lượng lên đến 6.700mAh rất tiện dụng và dòng cung cấp lên đến 1.5A cho bạn sạc điện thoại thoải mái. Hỗ trợ hình ảnh File RAW Ổ cứng di động SSD Western Digital My Passport Wireless hỗ trợ xem trước các ảnh RAW trên điện thoại hoặc máy tính bảng của bạn. Lưu Video trực tiếp trên ổ cứng FiLMiC Pro là một ứng dụng quay video tiên tiến cho điện thoại di động được các chuyên gia trên toàn thế giới sử dụng. Nó có thể kết nối với ổ cứng di động SSD Western Digital My Passport Wireless để ghi các đoạn phim trực tiếp vào ổ đĩa khi bạn quay phim để tiết kiệm không gian trên điện thoại của bạn. Bạn có thể tải ứng dụng trên Google Play hoặc Apple App Store. Chỉnh sửa ảnh ở bất cứ nơi đâu LumaFusion là ứng dụng chỉnh sửa video và tạo hiệu ứng Video chuyên nghiệp cho iPhone và iPad, cho phép bạn thoải mái sáng tạo chỉnh sửa hình ảnh, chỉnh sửa màu, điều chỉnh âm thanh và nhiều hơn thế nữa. Kết nối với My Passport Wireless SSD để nhập nội dung trực tiếp vào ứng dụng LumaFusion để chỉnh sửa bất cứ nơi nào bạn muốn. Tải ứng dụng trên Apple App Store. Thương hiệu Western Digital Cổng kết nối Wireless, USB 3.0","NHASANXUAT":"Western Digital","MODEL":"My Passport Wireless WDBAMJ0010BGY","CHUANGIAOTIEP":"– USB 3.0 – USB 2.0 Felmale (đọc đầu đọc thẻ nhớ và USB) – Wireless 802.11ac/n – SD Card Reader 3.0","DUNGLUONG":"1 TB","BAOHANH":"36 tháng"},{"TEN":"Ổ cứng di động External SSD 2TB Western Digital My Passport","GIA":19990000,"HINHANH":"Ổ cứng SSD Di Động/WDMyPassport-SSD-2017-Gift-280x315.jpg","MOTA":"Thông số kĩ thuật Nhà sản xuất Western Digital Model WDBK3E0010PSL Chuẩn giao tiếp – USB 3.1 Gen 2 – USB Type-C Dung lượng 2 TB Hệ điều hành hỗ trợ Windows, MacOS, Linux,… Tốc độ Lên đến 515 MB/s Kích thước 95 x 45 x 10 mm Bảo hành 3 năm Ổ cứng di động External SSD Western Digital My Passport Siêu tốc độ – Siêu bảo mật – Siêu tin cậy Ổ cứng di động External SSD Western Digital My Passport là bộ lưu trữ di động với tốc độ siêu nhanh. Bảo vệ mật khẩu bằng mã hóa phần cứng giúp giữ cho dữ liệu của bạn an toàn. Dễ sử dụng, chống sốc, thiết kế nhỏ gọn và trọng lượng rất nhẹ, dễ dàng mang theo bên mình.– Tốc độ siêu nhanh Ổ cứng di động External SSD Western Digital My Passport có tốc độ nhanh nhất hiện nay với tốc độ lên đến 515 MB/s, sử dụng chuẩn giao tiếp USB Type-C giúp truyền dữ liệu nhanh chóng. Tốc độ của nó mang lại hiệu suất tuyệt vời để giúp chạy các máy ảo và di chuyển dữ liệu trên máy tính của bạn, bạn sẽ tiết kiệm rất nhiều thời gian và làm được nhiều việc hơn. – Mã hóa phần cứng Ổ cứng di động External SSD Western Digital My Passport có thể đặt mật khẩu để bảo vệ dữ liệu bằng mã hóa phần cứng AES 256-bit được tích hợp với phần mềm bảo mật của WD. – Công nghệ mới nhất Được thiết kế cho Mac, PC, và Laptop. Ổ cứng di động External SSD Western Digital My Passport tương thích với cổng USB Type-C và USB Type-A. Với băng thông của USB Type-C sẽ cho tốc độ lên tới 515 MB/s. Ổ cứng di động External SSD Western Digital My Passport tương thích với USB 3.1 Gen 2, USB 3.0, 2.0 và USB-A. WD – Chất lượng tuyệt vời Có thể chịu đựng khi rơi từ độ cao 2 mét mà không bị bất kì vấn đề gì, ổ cứng di động External SSD Western Digital My Passport được thiết kế chống sock tuyệt vời theo tiêu chuẩn của Western Digital để trở thành ổ đĩa lưu trữ chất lượng từ bên trong lẫ vẻ bên ngoài để mang lại hiệu suất đáng tin cậy và độ bền cực cao. Tự động sao lưu Phần mềm WD Backup tích hợp giúp bạn dễ dàng sao lưu các tệp có dung lượng cao vào ổ đĩa hoặc các dịch vụ đám mây của Dropbox và hỗ trợ Apple Time Machine. Dễ dàng sử dụng Ổ cứng di động External SSD Western Digital My Passport chỉ cần cắm và chạy mà không cần phải cài bất kì phần mềm nào. Kích thước nhỏ gọn Ổ cứng di động External SSD Western Digital My Passport kích thước siêu nhỏ gọn với 90 x 45 x 10 mm, bạn có thể cho vào túi vào mang đến bất kì nơi đâu. Thương hiệu Western Digital Cổng kết nối USB 3.1, USB Type-C Dung lượng ổ cứng 2TB – 4TB","NHASANXUAT":"Western Digital","MODEL":"WDBK3E0010PSL","CHUANGIAOTIEP":"– USB 3.1 Gen 2 – USB Type-C","DUNGLUONG":"2 TB","BAOHANH":"3 năm"},{"TEN":"Ổ cứng di động SSD 2TB Western Digital My Passport Wireless WDBAMJ0020BGY","GIA":21590000,"HINHANH":"Ổ cứng SSD Di Động/WD-My-Passport-Wireless-SSD-01-280x315.jpg","MOTA":"Thông số kĩ thuật Nhà sản xuất Western Digital Model My Passport Wireless WDBAMJ0010BGY Chuẩn giao tiếp – USB 3.0 – USB 2.0 Felmale (đọc đầu đọc thẻ nhớ và USB) – Wireless 802.11ac/n – SD Card Reader 3.0 Dung lượng 2 TB Pin Li-ion, thời gian sử dụng có thể lên đến 10h Phần mềm hỗ trợ trên thiết bị di động MyCloud (có sẵn trên Appstore, Google Play,…) Hệ điều hành hỗ trợ MacOS, IOS, Android, WindowsPhone,… Bảo hành 36 tháng Ổ cứng di động SSD Western Digital My Passport Wireless Ổ cứng di động SSD Western Digital My Passport Wireless là một ổ đĩa di động giúp bảo vệ ảnh và video được chụp trên máy ảnh và máy Fly-Cam. Nút sao chụp một lần cho phép bạn sao lưu ảnh và video bằng đầu đọc thẻ SD ™ hoặc cổng USB tích hợp mà không cần máy tính xách tay hoặc phần mềm. Hỗ trợ đọc thẻ nhớ chuẩn SD Đầu đọc thẻ nhớ SD 3.0 được tích hợp trên ổ cứng di động SSD Western Digital My Passport Wireless với tốc độ đọc lên đến 65MB/s và nút One-Touch Button sẽ giúp bạn dễ dàng sao lưu ảnh và video từ thẻ nhớ SD sang ổ cứng mà không cần máy tính hoặc sử dụng bất kì phần mềm nào. Công nghệ lưu trữ của SSD và khả năng chống sốc – cho độ bền tuyệt đối Với một ổ SSD bên trong và lớp vỏ Silicon được gia cố để bảo bên ngoài, tất cả các linh kiện bên trong hoàn toàn được bảo vệ khỏi những cú sốc, các chấn động bên ngoài và khả năng chịu được độ rơi lên đến 1 mét, ngay cả khi ổ đĩa đang hoạt động. Tốc độ SSD siêu nhanh Ổ cứng di động SSD Western Digital My Passport Wireless có tốc độ truy cập siêu nhanh (lên tới 390MB/s tốc độ đọc) khi sử dụng cổng USB 3.0 để di chuyển các tập tin. All-Day Battery Life Ổ cứng di động SSD Western Digital My Passport Wireless trang bị Pin bên trong với thời lượng sử dụng lên đến 10 giờ liên tục. Giúp bạn thoải mái sử dụng cả ngày. Truy cập không dây và 4K Streaming Ổ cứng di động SSD Western Digital My Passport Wireless hỗ trợ phát WiFi tốc độ cao chuẩn mới nhất 802.11ac/n giúp bạn có thể kết nối không dây vào ổ đĩa của mình để truy cập và xem các bức ảnh đã lưu hoặc Streaming Video 4K trực tiếp sang điện thoại hoặc máy tính bảng của bạn bằng ứng dụng My Cloud. Sử dụng các ứng dụng của bên thứ ba, FiLMiC Pro, để chụp và lưu lại cảnh quay trực tiếp vào ổ đĩa, hoặc LumaFusion để chỉnh sửa video trong lĩnh vực này. Built-In USB 2.0 Port Một cổng USB 2.0 Female tiện lợi và nút One-Touch Button cho phép bạn dễ dàng chuyển các tập tin từ đầu đọc thẻ hoặc các thiết bị lưu trữ sử dụng cổng USB bên ngoài. Truy cập support.wd.com để xem danh sách đầy đủ các đầu đọc thẻ tương thích. Built-In Power Bank – Hỗ trợ sạc điện thoại Điện thoại bạn hết pin bất chợt trên đường đi? Không vấn đề gì. Ổ cứng di động SSD Western Digital My Passport Wireless hỗ trợ sạc điện thoại, máy ảnh Action Cam của bạn và các thiết bị di động khác. Với dung lượng lên đến 6.700mAh rất tiện dụng và dòng cung cấp lên đến 1.5A cho bạn sạc điện thoại thoải mái. Hỗ trợ hình ảnh File RAW Ổ cứng di động SSD Western Digital My Passport Wireless hỗ trợ xem trước các ảnh RAW trên điện thoại hoặc máy tính bảng của bạn. Lưu Video trực tiếp trên ổ cứng FiLMiC Pro là một ứng dụng quay video tiên tiến cho điện thoại di động được các chuyên gia trên toàn thế giới sử dụng. Nó có thể kết nối với ổ cứng di động SSD Western Digital My Passport Wireless để ghi các đoạn phim trực tiếp vào ổ đĩa khi bạn quay phim để tiết kiệm không gian trên điện thoại của bạn. Bạn có thể tải ứng dụng trên Google Play hoặc Apple App Store. Chỉnh sửa ảnh ở bất cứ nơi đâu LumaFusion là ứng dụng chỉnh sửa video và tạo hiệu ứng Video chuyên nghiệp cho iPhone và iPad, cho phép bạn thoải mái sáng tạo chỉnh sửa hình ảnh, chỉnh sửa màu, điều chỉnh âm thanh và nhiều hơn thế nữa. Kết nối với My Passport Wireless SSD để nhập nội dung trực tiếp vào ứng dụng LumaFusion để chỉnh sửa bất cứ nơi nào bạn muốn. Tải ứng dụng trên Apple App Store. Thương hiệu Western Digital Cổng kết nối Wireless, USB 3.0","NHASANXUAT":"Western Digital","MODEL":"My Passport Wireless WDBAMJ0010BGY","CHUANGIAOTIEP":"– USB 3.0 – USB 2.0 Felmale (đọc đầu đọc thẻ nhớ và USB) – Wireless 802.11ac/n – SD Card Reader 3.0","DUNGLUONG":"2 TB","BAOHANH":"36 tháng"},{"TEN":"Ổ cứng di động 2TB External SSD Samsung T5 USB 3.1 Gen 2","GIA":21600000,"HINHANH":"Ổ cứng SSD Di Động/Samsung-T5-Black-02-280x315.jpg","MOTA":"Thông số kĩ thuật Nhà sản xuất Samsung Model MU-PA2T0B Chuẩn giao tiếp USB 3.1 Gen 2 Dung lượng 2 TB Hệ điều hành hỗ trợ Windows, MacOS, Linux,… Tốc độ đọc 540 MB/s Tốc độ ghi 515 MB/s Màu sắc – Alluring Blue: 250GB, 500GB – Deep Black: 1TB, 2TB Bảo hành 36 tháng Ổ cứng di động SSD Samsung Portable T5 Kích thước nhỏ gọn – Tốc độ cực nhanh Ổ cứng di động SSD Samsung Portable T5 là dòng ổ cứng di động được trang bị chíp SSD và công nghệ độc quyền Samsung V-NAND, cho tốc độ truyền dữ liệu lên mức tối đa và mang lại trải nghiệm tuyệt vời nhất. Với thiết kế nhỏ gọn và cứng cáp, cùng mật khẩu bảo vệ bằng phần cứng, ổ cứng di động SSD Samsung Portable T5 thực sự là một thiết bị mà bạn có thể tin tưởng để mang theo và lưu trữ những dữ liệu quan trọng của bạn. Độ tin cậy cực cao Với tốc độ cực nhanh (~540MB/s), vỏ kim loại cực kỳ cứng cáp, bảo mật an toàn, nhỏ gọn và dễ sử dụng – ổ cứng di động SSD Samsung Portable T5 là bộ lưu trữ dữ liệu mới nhất và đáng tin cậy nhất hiện nay. Tốc độ truyền siêu nhanh Với bộ nhớ flash Samsung V-NAND và chuẩn giao tiếp USB 3.1 Gen 2, ổ cứng di động SSD Samsung Portable T5 cung cấp tốc độ truyền lên đến 540 MB/s, nhanh hơn 4,9x so với ổ cứng HDD gắn ngoài thông thường, giúp bạn di chuyển và sao lưu dữ liệu cực nhanh và tiết kiệm rất nhiều thời gian. Thiết kế vỏ kim loại – Phong cách cổ điển Được thiết kế full kim loại từ trên xuống dưới và kiểu dáng Unibody được bo tròn viền xung quanh với kích thước chỉ bằng lòng bàn tay của bạn, cho bạn cảm giác cầm nắm cực kỳ thoải mái và chắc chắn, không bị trượt. Ổ cứng di động SSD Samsung Portable T5 có hai màu khác nhau: màu xanh quyến rũ cho các mẫu 250 GB và 500 GB và màu đen cho mẫu 1 TB và 2 TB. Siêu nhỏ – siêu nhẹ Ổ cứng di động SSD Samsung Portable T5 với kích thước chỉ bằng chiếc thẻ ATM, trọng lượng 51 gram và độ dày chỉ 10mm. Bạn có thể dễ dàng bỏ vào túi áo và mang đi đến bất kì đâu. Khả năng bảo vệ dữ liệu tuyệt đối Ổ cứng di động SSD Samsung Portable T5 không có bộ phận chuyển động cơ quay và thân làm bằng kim loại chắc chắn, do đó nó có thể chịu đựng khi rơi từ độ cao 2 mét. Cùng với bảo vệ mật khẩu tùy chọn với mã hóa AES 256-bit bằng phần cứng giúp dữ liệu cá nhân của bạn an toàn hơn và có chế độ bảo hành 3 năm tại MemoryZone Tương thích mọi thiết bị Ổ cứng di động SSD Samsung Portable T5 tương thích với tất cả các thiết bị từ máy tính cá nhân PC, Laptop, máy Mac, điện thoại thông minh và các thiết bị khác hỗ trợ cổng USB Type-A và Type-C. Ngoài ra sản phẩm đi kèm với cáp USB Type-C to Type-C và cáp USB Type-C to Type-A giúp bạn kết nối với tất cả các thiết bị của bạn. Luôn sẵn sàng mọi lúc, mọi nơi Mang mọi thứ công việc và phương tiện giải trí của bạn. Ổ cứng di động SSD Samsung Portable T5 giúp bạn dễ dàng truy cập dữ liệu của bạn mọi lúc, mọi nơi bằng tất cả các thiết bị mà bạn có thể sử dụng như PC, Laptop, Điện thoại Smartphone, máy tính bảng,… Thương hiệu Samsung Cổng kết nối USB 3.1, USB Type-C","NHASANXUAT":"Samsung","MODEL":"MU-PA2T0B","CHUANGIAOTIEP":"USB 3.1 Gen 2","DUNGLUONG":"2 TB","BAOHANH":"36 tháng"}]